Workbook

Sheet MOMO,AIRTEL,CARDS
A3: ITEMS | B3: 44204 | C3: 44965 | D3: 44993 | E3: 45024 | F3: 45054 | G3: 45085 | H3: 45115 | I3: 45146 | J3: 45177 | K3: 45207 | L3: 45238 | M3: 45268 | N3: 13/8/23 | O3: 14/8/23 | P3: 15/8/23 | Q3: 16/8/23 | R3: 17/8/23 | S3: 18/8/23 | T3: 19/8/23 | U3: 20/8/23 | V3: 21/8/23 | W3: 22/8/23 | X3: 23/8/23 | Y3: 24/8/23 | Z3: 25/8/23 | AA3: 26/8/23 | AB3: 27/8/23 | AC3: 28/8/23 | AD3: 29/8/23 | AE3: 30/8/23 | AF3: 31/8/23 | AG3: MONTHLY TOTAL | AH3: 45170 | AI3: =AH3+1 | AJ3: =AI3+1 | AK3: =AJ3+1 | AL3: =AK3+1 | AM3: =AL3+1 | AN3: =AM3+1 | AO3: =AN3+1 | AP3: =AO3+1 | ... BK3: =BJ3+1 | BL3: Monthly Total | BM3: =AH3+30 | BN3: =AI3+30 | BO3: =AJ3+30 | BP3: =AK3+30 | BQ3: =AL3+30 | BR3: =AM3+30 | BS3: =AN3+30 | BT3: =AO3+30 | ... CP3: =BK3+30 | CQ3: =BM3+30 | CR3: Monthly total | CS3: =BN3+30 | CT3: =BO3+30 | CU3: =BP3+30 | CV3: =BQ3+30 | CW3: =BR3+30 | CX3: =BS3+30 | CY3: =BT3+30 | CZ3: =BU3+30 | ... DV3: =CQ3+30 | DW3: MONTHLY TOTAL | DX3: 45261 | DY3: =DX3+1 | DZ3: =DY3+1 | EA3: =DZ3+1 | EB3: =EA3+1 | EC3: =EB3+1 | ED3: =EC3+1 | EE3: =ED3+1 | EF3: =EE3+1 | ... FB3: =FA3+1 | FC3: MONTHLY TOTAL | FD3: =FB3+1 | FE3: =FD3+1 | FF3: =FE3+1 | FG3: =FF3+1 | FH3: =FG3+1 | FI3: =FH3+1 | FJ3: =FI3+1 | FK3: =FJ3+1 | FL3: =FK3+1 | ... GH3: =GG3+1 | GI3: MONTHLY TOTAL | GJ3: =GH3+1 | GK3: =GJ3+1 | GL3: =GK3+1 | GM3: =GL3+1 | GN3: =GM3+1 | GO3: =GN3+1 | GP3: =GO3+1 | GQ3: =GP3+1 | GR3: =GQ3+1 | ... HJ3: =HI3+1 | HK3: 45350 | HL3: 45351 | HM3: MONTHLY TOTAL | HN3: =HL3+1 | HO3: =HN3+1 | HP3: =HO3+1 | HQ3: =HP3+1 | HR3: =HQ3+1 | HS3: =HR3+1 | HT3: =HS3+1 | HU3: =HT3+1 | HV3: =HU3+1 | ... IR3: =IQ3+1 | IS3: monthly total | IT3: 45383 | IU3: =IT3+1 | IV3: =IU3+1 | IW3: =IV3+1 | IX3: =IW3+1 | IY3: =IX3+1 | IZ3: =IY3+1 | JA3: =IZ3+1 | JB3: =JA3+1 | ... JW3: =JV3+1 | JX3: total | JY3: 45413 | JZ3: =JY3+1 | KA3: =JZ3+1 | KB3: =KA3+1 | KC3: =KB3+1 | KD3: =KC3+1 | KE3: =KD3+1 | KF3: =KE3+1 | KG3: =KF3+1 | ... LC3: =LB3+1 | LD3: total | LE3: 1st -june | LF3: 2nd -june | LG3: 3rd -june | LH3: 4th -june | LI3: 5th -june | LJ3: 6th -june | LK3: 7th -june | LL3: 8th -june | LM3: 9th -june | LN3: 10th -june | LO3: 11th -june | LP3: 12th -june | LQ3: 13th -june | LR3: 14th -june | LS3: 15th -june | LT3: 16th -june | LU3: 17th -june | LV3: 18th -june | LW3: 19th -june | LX3: 20th -june | LY3: 21st -june | LZ3: 22nd -june | MA3: 23rd -june | MB3: 24th -june | MC3: 25th -june | MD3: 26th -june | ME3: 27th -june | MF3: 28th -june | MG3: 29th -june | MH3: 30th -june | MI3: total | MJ3: 1st july | MK3: 2nd july | ML3: 3rd july | MM3: 4th july | MN3: 5th july | MO3: 6th july | MP3: 7th july | MQ3: 8th july | MR3: 9th july | MS3: 10th july | MT3: 11th july | MU3: 12th july | MV3: 13th july | MW3: 14th july | MX3: 15th july | MY3: 16th july | MZ3: 17th july | NA3: 18th july | NB3: 19th july | NC3: 20th july | ND3: 21st july | NE3: 22nd july | NF3: 23rd july | NG3: 24th july | NH3: 25th july | NI3: 26th july | NJ3: 27th july | NK3: 28th july | NL3: 29th july | NM3: 30th july | NN3: 31st july | NO3: total | NP3: 1st august | NQ3: 2nd august | NR3: 3rd august | NS3: 4th august | NT3: 5th august | NU3: 6th august | NV3: 7th august | NW3: 8th august | NX3: 9th august | NY3: 10th august | NZ3: 11th august | OA3: 12th august | OB3: 13th august | OC3: 14th august | OD3: 15th august | OE3: 16th august | OF3: 17th august | OG3: 18th august | OH3: 19th august | OI3: 20th august | OJ3: 21st august | OK3: 22nd august | OL3: 23rd august | OM3: 24th august | ON3: 25th august | OO3: 26th august | OP3: 27th august | OQ3: 28th august | OR3: 29th august | OS3: 30th august | OT3: 31st august | OU3: total | OV3: 1st sep | OW3: 2nd sep | OX3: 3rd sep | OY3: 4th sep | OZ3: 5th sep | PA3: 6th sep | PB3: 7th sep | PC3: 8th sep | PD3: 9th sep | PE3: 10th sep | PF3: 11th sep | PG3: 12th sep | PH3: 13th sep | PI3: 14th sep | PJ3: 15th sep | PK3: 16th sep | PL3: 17th sep | PM3: 18th sep | PN3: 19th sep | PO3: 20th sep | PP3: 21st sep | PQ3: 22nd sep | PR3: 23rd sep | PS3: 24th sep | PT3: 25th sep | PU3: 26th sep | PV3: 27th sep | PW3: 28th sep | PX3: 29th sep | PY3: 30th sep | PZ3: total | QA3: 1st oct-24 | QB3: 2nd oct-24 | QC3: 3rd oct-24 | QD3: 4th oct-24 | QE3: 5th oct-24 | QF3: 6th oct-24 | QG3: 7th oct-24 | QH3: 8th oct-24 | QI3: 9th oct-24 | QJ3: 10th oct-24 | QK3: 11th oct-24 | QL3: 12th oct-24 | QM3: 13th oct-24 | QN3: 14th oct-24 | QO3: 15th oct-24 | QP3: 16th oct-24 | QQ3: 17th oct-24 | QR3: 18th oct-24 | QS3: 19th oct-24 | QT3: 20th oct-24 | QU3: 21st oct-24 | QV3: 22nd oct-24 | QW3: 23rd oct-24 | QX3: 24th oct-24 | QY3: 25th oct-24 | QZ3: 26th oct-24 | RA3: 27th oct-24 | RB3: 28th oct-24 | RC3: 29th oct-24 | RD3: 30th oct-24 | RE3: 31st oct-24 | RF3: total | RG3: 1st nov-2024 | RH3: 2nd nov-2024 | RI3: 3rd nov-2024 | RJ3: 4th nov-2024 | RK3: 5th nov-2024 | RL3: 6th nov-2024 | RM3: 7th nov-2024 | RN3: 8th nov-2024 | RO3: 9th nov-2024 | RP3: 10th nov-2024 | RQ3: 11th nov-2024 | RR3: 12th nov-2024 | RS3: 13th nov-2024 | RT3: 14th nov-2024 | RU3: 15th nov-2024 | RV3: 16th nov-2024 | RW3: 17th nov-2024 | RX3: 18th nov-2024 | RY3: 19th nov-2024 | RZ3: 20th nov-2024 | SA3: 21st nov-2024 | SB3: 22nd nov-2024 | SC3: 23rd nov-2024 | SD3: 24th nov-2024 | SE3: 25th nov-2024 | SF3: 26th nov-2024 | SG3: 27th nov-2024 | SH3: 28th nov-2024 | SI3: 29th nov-2024 | SJ3: 30th nov-2024 | SK3: total | SL3: 1st dec-2024 | SM3: 2nd dec-2024 | SN3: 3rd dec-2024 | SO3: 4th dec-2024 | SP3: 5th dec-2024 | SQ3: 6th dec-2024 | SR3: 7th dec-2024 | SS3: 8th dec-2024 | ST3: 9th dec-2024 | SU3: 10th dec-2024 | SV3: 11th dec-2024 | SW3: 12th dec-2024 | SX3: 13th dec-2024 | SY3: 14th dec-2024 | SZ3: 15th dec-2024 | TA3: 16th dec-2024 | TB3: 17th dec-2024 | TC3: 18th dec-2024 | TD3: 19th dec-2024 | TE3: 20th dec-2024 | TF3: 21st dec-2024 | TG3: 22nd dec-2024 | TH3: 23rd dec-2024 | TI3: 24th dec-2024 | TJ3: 25th dec-2024 | TK3: 26th dec-2024 | TL3: 27th dec-2024 | TM3: 28th dec-2024 | TN3: 29th dec-2024 | TO3: 30th dec-2024 | TP3: 31st dec-2024 | TQ3: total | TR3: 1st jan -2025 | TS3: 2nd jan -2025 | TT3: 3rd jan -2025 | TU3: 4th jan -2025 | TV3: 5th jan -2025 | TW3: 6th jan -2025 | TX3: 7th jan -2025 | TY3: 8th jan -2025 | TZ3: 9th jan -2025 | UA3: 10th jan -2025 | UB3: 11th jan -2025 | UC3: 12th jan -2025 | UD3: 13th jan -2025 | UE3: 14th jan -2025 | UF3: 15th jan -2025 | UG3: 16th jan -2025 | UH3: 17th jan -2025 | UI3: 18th jan -2025 | UJ3: 19th jan -2025 | UK3: 20th jan -2025 | UL3: 21st jan -2025 | UM3: 22nd jan -2025 | UN3: 23rd jan -2025 | UO3: 24th jan -2025 | UP3: 25th jan -2025 | UQ3: 26th jan -2025 | UR3: 27th jan -2025 | US3: 28th jan -2025 | UT3: 29th jan -2025 | UU3: 30th jan -2025 | UV3: 31st jan -2025 | UW3: tptal | UX3: 1st feb 2025 | UY3: 2nd feb 2025 | UZ3: 3rd feb 2025 | VA3: 4th feb 2025 | VB3: 5th feb 2025 | VC3: 6th feb 2025 | VD3: 7th feb 2025 | VE3: 8th feb 2025 | VF3: 9th feb 2025 | VG3: 10th feb 2025 | VH3: 11th feb 2025 | VI3: 12th feb 2025 | VJ3: 13th feb 2025 | VK3: 14th feb 2025 | VL3: 15th feb 2025 | VM3: 16th feb 2025 | VN3: 17th feb 2025 | VO3: 18th feb 2025 | VP3: 19th feb 2025 | VQ3: 20th feb 2025 | VR3: 21st feb 2025 | VS3: 22nd feb 2025 | VT3: 23rd feb 2025 | VU3: 24th feb 2025 | VV3: 25th feb 2025 | VW3: 26th feb 2025 | VX3: 27th feb 2025 | VY3: 28th feb 2025 | VZ3: Total | WA3: 1st mar 2025 | WB3: 2nd mar 2025 | WC3: 3rd mar 2025 | WD3: 4th mar 2025 | WE3: 5th mar 2025 | WF3: 6th mar 2025 | WG3: 7th mar 2025 | WH3: 8th mar 2025 | WI3: 9th mar 2025 | WJ3: 10th mar 2025 | WK3: 11th mar 2025 | WL3: 12th mar 2025 | WM3: 13th mar 2025 | WN3: 14th mar 2025 | WO3: 15th mar 2025 | WP3: 16th mar 2025 | WQ3: 17th mar 2025 | WR3: 18th mar 2025 | WS3: 19th mar 2025 | WT3: 20th mar 2025 | WU3: 21st mar 2025 | WV3: 22nd mar 2025 | WW3: 23rd mar 2025 | WX3: 24th mar 2025 | WY3: 25th mar 2025 | WZ3: 26th mar 2025 | XA3: 27th mar 2025 | XB3: 28th mar 2025 | XC3: 29th mar 2025 | XD3: 30th mar 2025 | XE3: 31st mar 2025 | XF3: T0tal | XG3: 1st -apr2025 | XH3: 2nd -apr2025 | XI3: 3rd -apr2025 | XJ3: 4th -apr2025 | XK3: 5th -apr2025 | XL3: 6th -apr2025 | XM3: 7th -apr2025 | XN3: 8th -apr2025 | XO3: 9th -apr2025 | XP3: 10th -apr2025 | XQ3: 11th -apr2025 | XR3: 12th -apr2025 | XS3: 13th -apr2025 | XT3: 14th -apr2025 | XU3: 15th -apr2025 | XV3: 16th -apr2025 | XW3: 17th -apr2025 | XX3: 18th -apr2025 | XY3: 19th -apr2025 | XZ3: 20th -apr2025 | YA3: 21st -apr2025 | YB3: 22nd -apr2025 | YC3: 23rd -apr2025 | YD3: 24th -apr2025 | YE3: 25th -apr2025 | YF3: 26th -apr2025 | YG3: 27th -apr2025 | YH3: 28th -apr2025 | YI3: 29th -apr2025 | YJ3: 30th -apr2025 | YK3: T0tal | YL3: 1st May-2025 | YM3: 2nd May-2025 | YN3: 3rd May-2025 | YO3: 4th May-2025 | YP3: 5th May-2025 | YQ3: 6th May-2025 | YR3: 7th May-2025 | YS3: 8th May-2025 | YT3: 9th May-2025 | YU3: 10th May-2025 | YV3: 11th May-2025 | YW3: 12th May-2025 | YX3: 13th May-2025 | YY3: 14th May-2025 | YZ3: 15th May-2025 | ZA3: 16th May-2025 | ZB3: 17th May-2025 | ZC3: 18th May-2025 | ZD3: 19th May-2025 | ZE3: 20th May-2025 | ZF3: 21st May-2025 | ZG3: 22nd May-2025 | ZH3: 23rd May-2025 | ZI3: 24th May-2025 | ZJ3: 25th May-2025 | ZK3: 26th May-2025 | ZL3: 27th May-2025 | ZM3: 28th May-2025 | ZN3: 29th May-2025 | ZO3: 30th May-2025 | ZP3: 31st May-2025 | ZQ3: T0tal | ZR3: 1st june | ZS3: 2nd june | ZT3: 3rd june | ZU3: 4th june | ZV3: 5th june | ZW3: 6th june | ZX3: 7th june | ZY3: 8th june | ZZ3: 9th june | AAA3: 10th june | AAB3: 11th june | AAC3: 12th june | AAD3: 13th june | AAE3: 14th june | AAF3: 15th june | AAG3: 16th june | AAH3: 17th june | AAI3: 18th june | AAJ3: 19th june | AAK3: 20th june | AAL3: 21st june | AAM3: 22nd june | AAN3: 23rd june | AAO3: 24th june | AAP3: 25th june | AAQ3: 26th june | AAR3: 27th june | AAS3: 28th june | AAT3: 29th june | AAU3: 30th june | AAV3: T0tal | AAW3: 1st july | AAX3: 2nd july | AAY3: 3rd july | AAZ3: 4th july | ABA3: 5th july | ABB3: 6th july | ABC3: 7th july | ABD3: 8th july | ABE3: 9th july | ABF3: 10th july | ABG3: 11th july | ABH3: 12th july | ABI3: 13th july | ABJ3: 14th july | ABK3: 15th july | ABL3: 16th july | ABM3: 17th july | ABN3: 18th july | ABO3: 19th july | ABP3: 20th july | ABQ3: 21st july | ABR3: 22nd july | ABS3: 23rd july | ABT3: 24th july | ABU3: 25th july | ABV3: 26th july | ABW3: 27th july | ABX3: 28th july | ABY3: 29th july | ABZ3: 30th july | ACA3: 31st july | ACB3: T0tal | ACC3: 1st aug | ACD3: 2nd aug | ACE3: 3rd aug | ACF3: 4th aug | ACG3: 5th aug | ACH3: 6th aug | ACI3: 7th aug | ACJ3: 8th aug | ACK3: 9th aug | ACL3: 10th aug | ACM3: 11th aug | ACN3: 12th aug | ACO3: 13th aug | ACP3: 14th aug | ACQ3: 15th aug | ACR3: 16th aug | ACS3: 17th aug | ACT3: 18th aug | ACU3: 19th aug | ACV3: 20th aug | ACW3: 21st aug | ACX3: 22nd aug | ACY3: 23rd aug | ACZ3: 24th aug | ADA3: 25th aug | ADB3: 26th aug | ADC3: 27th aug | ADD3: 28th aug | ADE3: 29th aug | ADF3: 30th aug | ADG3: 31st aug | ADI3: 1st -sep25 | ADJ3: 2nd -sep25 | ADK3: 3rd -sep25 | ADL3: 4th -sep25 | ADM3: 5th -sep25 | ADN3: 6th -sep25 | ADO3: 7th -sep25 | ADP3: 8th -sep25 | ADQ3: 9th -sep25 | ADR3: 10th -sep25 | ADS3: 11th -sep25 | ADT3: 12th -sep25 | ADU3: 13th -sep25 | ADV3: 14th -sep25 | ADW3: 15th -sep25 | ADX3: 16th -sep25 | ADY3: 17th -sep25 | ADZ3: 18th -sep25 | AEA3: 19th -sep25 | AEB3: 20th -sep25 | AEC3: 21st -sep25 | AED3: 22nd -sep25 | AEE3: 23rd -sep25 | AEF3: 24th -sep25 | AEG3: 25th -sep25 | AEH3: 26th -sep25 | AEI3: 27th -sep25 | AEJ3: 28th -sep25 | AEK3: 29th -sep25 | AEL3: 30th -sep25 | AEM3: Total | AEN3: 1st -oct25 | AEO3: 2nd -oct25 | AEP3: 3rd -oct25 | AEQ3: 4th -oct25 | AER3: 5th -oct25 | AES3: 6th -oct25 | AET3: 7th -oct25 | AEU3: 8th -oct25 | AEV3: 9th -oct25 | AEW3: 10th -oct25 | AEX3: 11th -oct25 | AEY3: 12th -oct25 | AEZ3: 13th -oct25 | AFA3: 14th -oct25 | AFB3: 15th -oct25 | AFC3: 16th -oct25 | AFD3: 17th -oct25 | AFE3: 18th -oct25 | AFF3: 19th -oct25 | AFG3: 20th -oct25 | AFH3: 21st -oct25 | AFI3: 22nd -oct25 | AFJ3: 23rd -oct25 | AFK3: 24th -oct25 | AFL3: 25th -oct25 | AFM3: 26th -oct25 | AFN3: 27th -oct25 | AFO3: 28th -oct25 | AFP3: 29th -oct25 | AFQ3: 30th -oct25 | AFR3: 31st -oct25 | AFS3: total | AFT3: 1st -nov25 | AFU3: 2nd -nov25 | AFV3: 3rd -nov25 | AFW3: 4th -nov25 | AFX3: 5th -nov25 | AFY3: 6th -nov25 | AFZ3: 7th -nov25 | AGA3: 8th -nov25 | AGB3: 9th -nov25 | AGC3: 10th -nov25 | AGD3: 11th -nov25 | AGE3: 12th -nov25 | AGF3: 13th -nov25 | AGG3: 14th -nov25 | AGH3: 15th -nov25 | AGI3: 16th -nov25 | AGJ3: 17th -nov25 | AGK3: 18th -nov25 | AGL3: 19th -nov25 | AGM3: 20th -nov25 | AGN3: 21st -nov25 | AGO3: 22nd -nov25 | AGP3: 23rd -nov25 | AGQ3: 24th -nov25 | AGR3: 25th -nov25 | AGS3: 26th -nov25 | AGT3: 27th -nov25 | AGU3: 28th -nov25 | AGV3: 29th -nov25 | AGW3: 30th -nov25 | AGX3: total | AGY3: 1st -dec25 | AGZ3: 2nd -dec25 | AHA3: 3rd -dec25 | AHB3: 4th -dec25 | AHC3: 5th -dec25 | AHD3: 6th -dec25 | AHE3: 7th -dec25 | AHF3: 8th -dec25 | AHG3: 9th -dec25 | AHH3: 10th -dec25 | AHI3: 11th -dec25 | AHJ3: 12th -dec25 | AHK3: 13th -dec25 | AHL3: 14th -dec25 | AHM3: 15th -dec25 | AHN3: 16th -dec25 | AHO3: 17th -dec25 | AHP3: 18th -dec25 | AHQ3: 19th -dec25 | AHR3: 20th -dec25 | AHS3: 21st -dec25 | AHT3: 22nd -dec25 | AHU3: 23rd -dec25 | AHV3: 24th -dec25 | AHW3: 25th -dec25 | AHX3: 26th -dec25 | AHY3: 27th -dec25 | AHZ3: 28th -dec25 | AIA3: 29th -dec25 | AIB3: 30th -dec25 | AIC3: 31st -dec25 | AID3: total | AIE3: 1st -jan26 | AIF3: 2nd -jan26 | AIG3: 3rd -jan26 | AIH3: 4th -jan26 | AII3: 5th -jan26 | AIJ3: 6th -jan26 | AIK3: 7th -jan26 | AIL3: 8th -jan26 | AIM3: 9th -jan26 | AIN3: 10th -jan26 | AIO3: 11th -jan26 | AIP3: 12th -jan26 | AIQ3: 13th -jan26 | AIR3: 14th -jan26 | AIS3: 15th -jan26 | AIT3: 16th -jan26 | AIU3: 17th -jan26 | AIV3: 18th -jan26 | AIW3: 19th -jan26 | AIX3: 20th -jan26 | AIY3: 21st -jan26 | AIZ3: 22nd -jan26 | AJA3: 23rd -jan26 | AJB3: 24th -jan26 | AJC3: 25th -jan26 | AJD3: 26th -jan26 | AJE3: 27th -jan26 | AJF3: 28th -jan26 | AJG3: 29th -jan26 | AJH3: 30th -jan26 | AJI3: 31st -jan26 | AJJ3: total | AJK3: 1st -feb2026 | AJL3: 2nd -feb2026 | AJM3: 3rd -feb2026 | AJN3: 4th -feb2026 | AJO3: 5th -feb2026 | AJP3: 6th -feb2026 | AJQ3: 7th -feb2026 | AJR3: 8th -feb2026 | AJS3: 9th -feb2026 | AJT3: 10th -feb2026 | AJU3: 11th -feb2026 | AJV3: 12th -feb2026 | AJW3: 13th -feb2026 | AJX3: 14th -feb2026 | AJY3: 15th -feb2026 | AJZ3: 16th -feb2026 | AKA3: 17th -feb2026 | AKB3: 18th -feb2026 | AKC3: 19th -feb2026 | AKD3: 20th -feb2026 | AKE3: 21st -feb2026 | AKF3: 22nd -feb2026 | AKG3: 23rd -feb2026 | AKH3: 24th -feb2026 | AKI3: 25th -feb2026 | AKJ3: 26th -feb2026 | AKK3: 27th -feb2026 | AKL3: 28th -feb2026 | AKM3: total | AKN3: 1st -mar2026 | AKO3: 2nd -mar2026 | AKP3: 3rd -mar2026 | AKQ3: 4th -mar2026 | AKR3: 5th -mar2026 | AKS3: 6th -mar2026 | AKT3: 7th -mar2026 | AKU3: 8th -mar2026 | AKV3: 9th -mar2026 | AKW3: 10th -mar2026 | AKX3: 11th -mar2026 | AKY3: 12th -mar2026 | AKZ3: 13th -mar2026 | ALA3: 14th -mar2026 | ALB3: 15th -mar2026 | ALC3: 16th -mar2026 | ALD3: 17th -mar2026 | ALE3: 18th -mar2026 | ALF3: 19th -mar2026 | ALG3: 20th -mar2026 | ALH3: 21st -mar2026 | ALI3: 22nd -mar2026 | ALJ3: 23rd -mar2026 | ALK3: 24th -mar2026 | ALL3: 25th -mar2026 | ALM3: 26th -mar2026 | ALN3: 27th -mar2026 | ALO3: 28th -mar2026 | ALP3: 29th -mar2026 | ALQ3: 30th -mar2026 | ALR3: 31st -mar2026 | ALS3: total | ALT3: 1st apr2026 | ALU3: 2nd apr2026 | ALV3: 3rd apr2026 | ALW3: 4th apr2026 | ALX3: 5th apr2026 | ALY3: 6th apr2026 | ALZ3: 7th apr2026 | AMA3: 8th apr2026 | AMB3: 9th apr2026 | AMC3: 10th apr2026 | AMD3: 11th apr2026 | AME3: 12th apr2026 | AMF3: 13th apr2026 | AMG3: 14th apr2026 | AMH3: 15th apr2026 | AMI3: 16th apr2026 | AMJ3: 17th apr2026 | AMK3: 18th apr2026 | AML3: 19th apr2026 | AMM3: 20th apr2026 | AMN3: 21st apr2026 | AMO3: 22nd apr2026 | AMP3: 23rd apr2026 | AMQ3: 24th apr2026 | AMR3: 25th apr2026 | AMS3: 26th apr2026 | AMT3: 27th apr2026 | AMU3: 28th apr2026 | AMV3: 29th apr2026 | AMW3: 30th apr2026 | AMX3: total | AMY3: 1st -may2026 | AMZ3: 2nd -may2026 | ANA3: 3rd -may2026 | ANB3: 4th -may2026 | ANC3: 5th -may2026 | AND3: 6th -may2026 | ANE3: 7th -may2026 | ANF3: 8th -may2026 | ANG3: 9th -may2026 | ANH3: 10th -may2026 | ANI3: 11th -may2026 | ANJ3: 12th -may2026 | ANK3: 13th -may2026 | ANL3: 14th -may2026 | ANM3: 15th -may2026 | ANN3: 16th -may2026 | ANO3: 17th -may2026 | ANP3: 18th -may2026 | ANQ3: 19th -may2026 | ANR3: 20th -may2026 | ANS3: 21st -may2026 | ANT3: 22nd -may2026 | ANU3: 23rd -may2026 | ANV3: 24th -may2026 | ANW3: 25th -may2026 | ANX3: 26th -may2026 | ANY3: 27th -may2026 | ANZ3: 28th -may2026 | AOA3: 29th -may2026 | AOB3: 30th -may2026 | AOC3: 10th -June2026 | AOD3: 26th -August2026
A4: MOMOPAY | B4: 1656008 | C4: 1896485 | D4: 1900500 | E4: 1307000 | F4: 1320600 | G4: 1245000 | H4: 1337725 | I4: 931700 | J4: 1315000 | K4: 1250500 | L4: 911563 | M4: 1656000 | N4: 842000 | O4: 667000 | P4: 1099000 | Q4: 802000 | R4: 1051000 | S4: 1177000 | T4: 766000 | U4: 610500 | V4: 2100000 | W4: 1108000 | X4: 2044000 | Y4: 2241654 | Z4: 1168000 | AA4: 1201200 | AB4: 771400 | AC4: 645000 | AD4: 491000 | AE4: 731000 | AF4: 1242000 | AG4: =SUM(B4:AF4) | AH4: 608500 | AI4: 834000 | AJ4: 1216886 | AK4: 2198000 | AL4: 1906595 | AM4: 1435300 | AN4: 1208000 | AO4: 2029000 | AP4: 1333600 | AQ4: 1128600 | AR4: 1288100 | AS4: 671000 | AT4: 869000 | AU4: 1012400 | AV4: 1722800 | AW4: 1033000 | AX4: 480000 | AY4: 1244000 | AZ4: 2092000 | BA4: 692000 | BB4: 1152500 | BC4: 1122300 | BD4: 1436500 | BE4: 1322100 | BF4: 1458000 | BG4: 854800 | BH4: 782000 | BI4: 684560 | BJ4: 1953463 | BK4: 1323600 | BL4: =SUM(AH4:BK4) | BM4: 1047000 | BN4: 1627000 | BO4: 1751000 | BP4: 1141000 | BQ4: 511000 | BR4: 1372312 | BS4: 1370000 | BT4: 158000 | BU4: 974700 | BV4: 951750 | BW4: 832000 | BX4: 973000 | BY4: 1484500 | BZ4: 2322000 | CA4: 1078000 | CB4: 1190000 | CC4: 847000 | CD4: 383000 | CE4: 1761170 | CF4: 723000 | CG4: 1178980 | CH4: 1037000 | CI4: 766500 | CJ4: 1736000 | CK4: 917000 | CL4: 1370000 | CM4: 1496000 | CN4: 1106000 | CO4: 1061552 | CP4: 1350421 | CQ4: 803000 | CR4: =SUM(BM4:CQ4) | CS4: 2575000 | CT4: 1032512 | CU4: 1549453 | CV4: 1163078 | CW4: 1572000 | CX4: 1357500 | CY4: 1145000 | CZ4: 711000 | DA4: 630000 | DB4: 1686000 | DC4: 842000 | DD4: 565969 | DE4: 1019000 | DF4: 1122842 | DG4: 1012000 | DH4: 773000 | DI4: 1700200 | DJ4: 1580000 | DK4: 684000 | DL4: 1780218 | DM4: 1258000 | DN4: 1173082 | DO4: 1887050 | DP4: 1415000 | DQ4: 2460200 | DR4: 1009258 | DS4: 2444200 | DT4: 1119653 | DU4: 1084650 | DV4: 1015000 | DW4: =SUM(CS4:DV4) | DX4: 894200 | DY4: 1658286 | DZ4: 708900 | EA4: 610000 | EB4: 1304500 | EC4: 1055000 | ED4: 811000 | EE4: 1426100 | EF4: 1220000 | EG4: 1530000 | EH4: 1299000 | EI4: 1527610 | EJ4: 1136000 | EK4: 850000 | EL4: 1403011 | EM4: 1591859 | EN4: 1323950 | EO4: 2499000 | EP4: 1147000 | EQ4: 632400 | ER4: 1138000 | ES4: 1527865 | ET4: 1924000 | EU4: 1501128 | EV4: 1240000 | EW4: 1299000 | EX4: 851000 | EY4: 1338078 | EZ4: 1748500 | FA4: 1992021 | FB4: 1585000 | FC4: =SUM(DX4:FB4) | FD4: 1823895 | FE4: 1199000 | FF4: 1462000 | FG4: 600000 | FH4: 445000 | FI4: 733000 | FJ4: 1637000 | FK4: 1143500 | FL4: 967000 | FM4: 1801689 | FN4: 1132600 | FO4: 949000 | FP4: 1347000 | FQ4: 2005000 | FR4: 1237000 | FS4: 902000 | FT4: 1289000 | FU4: 1318000 | FV4: 665000 | FW4: 1365500 | FX4: 1156979 | FY4: 895000 | FZ4: 1785682 | GA4: 719000 | GB4: 1006000 | GC4: 1835092 | GD4: 1320000 | GE4: 2044500 | GF4: 1124000 | GG4: 736000 | GH4: 2328000 | GI4: =SUM(FD4:GH4) | GJ4: 642000 | GK4: 774000 | GL4: 1126300 | GM4: 555000 | GN4: 1010000 | GO4: 1627300 | GP4: 1329000 | GQ4: 1568000 | GR4: 1248000 | GS4: 1427000 | GT4: 986912 | GU4: 643000 | GV4: 1649922 | GW4: 706000 | GX4: 804608 | GY4: 1237000 | GZ4: 2156432 | HA4: 1381061 | HB4: 1128000 | HC4: 1363000 | HD4: 830000 | HE4: 840000 | HF4: 2185450 | HG4: 576000 | HH4: 557000 | HI4: 468000 | HJ4: 789000 | HK4: 1208817 | HL4: 426000 | HM4: =SUM(GJ4:HL4) | HN4: 880000 | HO4: 1598000 | HP4: 1206000 | HQ4: 1775232 | HR4: 1131700 | HS4: 1820000 | HT4: 2131900 | HU4: 1653900 | HV4: 713000 | HW4: 870000 | HX4: 1099000 | HY4: 1089000 | HZ4: 2110432 | IA4: 942000 | IB4: 1376000 | IC4: 1829300 | ID4: 576200 | IE4: 1260680 | IF4: 608000 | IG4: 1719836 | IH4: 677000 | II4: 1651000 | IJ4: 1404620 | IK4: 783000 | IL4: 1419000 | IM4: 1167700 | IN4: 665400 | IO4: 1703022 | IP4: 1386003 | IQ4: 508000 | IR4: 807025 | IS4: =SUM(HN4:IR4) | IT4: 223000 | IU4: 2000169 | IV4: 496000 | IW4: 785343 | IX4: 1149000 | IY4: 870000 | IZ4: 1485000 | JA4: 2238052 | JB4: 697851 | JC4: 673000 | JD4: 1672000 | JE4: 2524583 | JF4: 1073000 | JG4: 725000 | JH4: 1193000 | JI4: 837000 | JJ4: 717000 | JK4: 1095000 | JL4: 1084500 | JM4: 685000 | JN4: 1076968 | JO4: 832700 | JP4: 704000 | JQ4: 399000 | JR4: 999950 | JS4: 1296000 | JT4: 2398500 | JU4: 1230000 | JV4: 1666500 | JW4: 877000 | JX4: =SUM(IT4:JW4) | JY4: 1235700 | JZ4: 790000 | KA4: 870000 | KB4: 709000 | KC4: 1210112 | KD4: 1168000 | KE4: 1510500 | KF4: 1061750 | KG4: 1311900 | KH4: 554000 | KI4: 788000 | KJ4: 919000 | KK4: 2611400 | KL4: 878000 | KM4: 1270500 | KN4: 1827542 | KO4: 420000 | KP4: 1465000 | KQ4: 513500 | KR4: 953000 | KS4: 2302050 | KT4: 817000 | KU4: 799000 | KV4: 1117900 | KW4: 1078000 | KX4: 1481038 | KY4: 1311000 | KZ4: 1513500 | LA4: 1107250 | LB4: 540000 | LC4: 2368000 | LD4: =SUM(JY4:LC4) | LE4: 1837864 | LF4: 1156000 | LG4: 927000 | LH4: 1204000 | LI4: 1366500 | LJ4: 592500 | LK4: 1462000 | LL4: 1097931 | LM4: 790000 | LN4: 911000 | LO4: 724000 | LP4: 1050042 | LQ4: 1363000 | LR4: 1145300 | LS4: 1831000 | LT4: 1249000 | LU4: 1374000 | LV4: 1502250 | LW4: 1583500 | LX4: 1275000 | LY4: 1700014 | LZ4: 589450 | MA4: 1317000 | MB4: 546000 | MC4: 708750 | MD4: 1398198 | ME4: 697142 | MF4: 2145500 | MG4: 938500 | MH4: 960045 | MI4: =SUM(LD4:MH4) | MJ4: 1090164 | MK4: 1156500 | ML4: 593900 | MM4: 860900 | MN4: 818000 | MO4: 994000 | MP4: 801000 | MQ4: 904000 | MR4: 596000 | MS4: 1277378 | MT4: 1370468 | MU4: 1847344 | MV4: 952450 | MW4: 1058000 | MX4: 970000 | MY4: 1527000 | MZ4: 1187800 | NA4: 1215025 | NB4: 1618998 | NC4: 1332000 | ND4: 869500 | NE4: 1747960 | NF4: 721000 | NG4: 1173000 | NH4: 1137000 | NI4: 913886 | NJ4: 1064000 | NK4: 459000 | NL4: 815000 | NM4: 1519688 | NN4: 914000 | NO4: =SUM(MJ4:NN4) | NP4: 573000 | NQ4: 1917456 | NR4: 1123504 | NS4: 1260200 | NT4: 710500 | NU4: 1030000 | NV4: 985650 | NW4: 744000 | NX4: 772900 | NY4: 462000 | NZ4: 452000 | OA4: 557000 | OB4: 1035830 | OC4: 1547000 | OD4: 1918400 | OE4: 2252000 | OF4: 1551900 | OG4: 677000 | OH4: 982200 | OI4: 1115000 | OJ4: 986000 | OK4: 924000 | OL4: 342000 | OM4: 1314000 | ON4: 490000 | OO4: 1405094 | OP4: 1147003 | OQ4: 696412 | OR4: 1178398 | OS4: 1292000 | OT4: 1059000 | OU4: =SUM(NP4:OT4) | OV4: 1082000 | OW4: 1121495 | OX4: 1266980 | OY4: 770000 | OZ4: 968000 | PA4: 1111000 | PB4: 862500 | PC4: 1625000 | PD4: 788200 | PE4: 718000 | PF4: 1261000 | PG4: 1345000 | PH4: 1730538 | PI4: 892000 | PJ4: 734900 | PK4: 1055132 | PL4: 355000 | PM4: 1257500 | PN4: 1540200 | PO4: 2783148 | PP4: 812000 | PQ4: 542014 | PR4: 695000 | PS4: 724000 | PT4: 659980 | PU4: 1191000 | PV4: 799000 | PW4: 843500 | PX4: 590000 | PY4: 736000 | PZ4: =SUM(OV4:PY4) | QA4: 768000 | QB4: 320000 | QC4: 907100 | QD4: 469000 | QE4: 1572150 | QF4: 798000 | QG4: 1112000 | QH4: 578980 | QI4: 836100 | QJ4: 624000 | QK4: 857550 | QL4: 909000 | QM4: 1440902 | QN4: 1675400 | QO4: 971700 | QP4: 1343500 | QQ4: 1050850 | QR4: 1140450 | QS4: 1231500 | QT4: 380000 | QU4: 753400 | QV4: 842100 | QW4: 485000 | QX4: 402960 | QY4: 2106000 | QZ4: 1477000 | RA4: 267000 | RB4: 1260000 | RC4: 596188 | RD4: 790000 | RE4: 953500 | RF4: =SUM(QA4:RE4) | RG4: 888000 | RH4: 1097000 | RI4: 658000 | RJ4: 837017 | RK4: 809985 | RL4: 1352780 | RM4: 758000 | RN4: 1177000 | RO4: 1104000 | RP4: 646752 | RQ4: 620000 | RR4: 2178000 | RS4: 1079599 | RT4: 410000 | RU4: 458000 | RV4: 521000 | RW4: 882000 | RX4: 734000 | RY4: 934000 | RZ4: 1192000 | SA4: 837842 | SB4: 840000 | SC4: 588000 | SD4: 450000 | SE4: 1165800 | SF4: 834333 | SG4: 2060000 | SH4: 925380 | SI4: 1140000 | SJ4: 1205000 | SK4: =SUM(RG4:SJ4) | SL4: 408900 | SM4: 820000 | SN4: 1275400 | SO4: 1181500 | SP4: 1570850 | SQ4: 803500 | SR4: 1469000 | SS4: 1278802 | ST4: 1370000 | SU4: 1715128 | SV4: 1590000 | SW4: 822800 | SX4: 2290090 | SY4: 1148109 | SZ4: 956000 | TA4: 1747890 | TB4: 2034950 | TC4: 601000 | TD4: 1859222 | TE4: 1181429 | TF4: 1247000 | TG4: 3046264 | TH4: 1196000 | TI4: 572000 | TJ4: 779559 | TK4: 671000 | TL4: 1661352 | TM4: 618000 | TN4: 1313500 | TO4: 643000 | TP4: 1383000 | TQ4: =SUM(SL4:TP4) | TR4: 641000 | TS4: 847000 | TT4: 755000 | TU4: 1901000 | TV4: 1267800 | TW4: 1721000 | TX4: 840000 | TY4: 1630000 | TZ4: 902000 | UA4: 2456590 | UB4: 538000 | UC4: 1376000 | UD4: 1391700 | UE4: 1799600 | UF4: 2289000 | UG4: 1722500 | UH4: 1480000 | UI4: 1904000 | UJ4: 1559000 | UK4: 1093000 | UL4: 1025063 | UM4: 774500 | UN4: 1146000 | UO4: 1679000 | UP4: 1427000 | UQ4: 851000 | UR4: 1651000 | US4: 1429000 | UT4: 781000 | UU4: 368000 | UV4: 1191000 | UW4: =SUM(TR4:UV4) | UX4: 796000 | UY4: 866000 | UZ4: 2355260 | VA4: 905000 | VB4: 1027000 | VC4: 1294000 | VD4: 826500 | VE4: 2025000 | VF4: 226000 | VG4: 1033000 | VH4: 462000 | VI4: 950000 | VJ4: 884000 | VK4: 864000 | VL4: 1089000 | VM4: 1230520 | VN4: 562000 | VO4: 384000 | VP4: 910000 | VQ4: 1249106 | VR4: 1495000 | VS4: 1860000 | VT4: 1260500 | VU4: 1965332 | VV4: 1037000 | VW4: 1880000 | VX4: 1884000 | VY4: 1250000 | VZ4: =SUM(UX4:VY4) | WA4: 1608652 | WB4: 917000 | WC4: 911500 | WD4: 840000 | WE4: 967200 | WF4: 1130000 | WG4: 729000 | WH4: 382000 | WI4: 484000 | WJ4: 841000 | WK4: 1610000 | WL4: 511000 | WM4: 611500 | WN4: 1051000 | WO4: 1661050 | WP4: 885000 | WQ4: 104000 | WR4: 0 | WS4: 478705 | WT4: 560000 | WU4: 578000 | WV4: 1439000 | WW4: 922000 | WX4: 2004000 | WY4: 355000 | WZ4: 1618000 | XA4: 1428800 | XB4: 1293474 | XC4: 653000 | XD4: 2462000 | XE4: 1386000 | XF4: =SUM(WA4:XE4) | XG4: 1520000 | XH4: 1163890 | XI4: 2025000 | XJ4: 997000 | XK4: 1226585 | XL4: 646000 | XM4: 1453965 | XN4: 727200 | XO4: 548850 | XP4: 758000 | XQ4: 707000 | XR4: 1865954 | XS4: 745000 | XT4: 1457850 | XU4: 1290000 | XV4: 1035000 | XW4: 1092000 | XX4: 530000 | XY4: 625030 | XZ4: 350000 | YA4: 986000 | YB4: 996000 | YC4: 1942000 | YD4: 532000 | YE4: 921000 | YF4: 770000 | YG4: 686000 | YH4: 373000 | YI4: 1210266 | YJ4: 358000 | YK4: =SUM(XF4:YJ4) | YL4: 2827000 | YM4: 1098256 | YN4: 937000 | YO4: 864500 | YP4: 1315000 | YQ4: 1103000 | YR4: 1169676 | YS4: 736500 | YT4: 982000 | YU4: 1235832 | YV4: 1252000 | YW4: 840450 | YX4: 824000 | YY4: 733500 | YZ4: 1793000 | ZA4: 1392000 | ZB4: 642000 | ZC4: 881000 | ZD4: 1561000 | ZE4: 470000 | ZF4: 1294700 | ZG4: 1474750 | ZH4: 1068000 | ZI4: 1325000 | ZJ4: 806500 | ZK4: 1456719 | ZL4: 2515000 | ZM4: 1405000 | ZN4: 662500 | ZO4: 842500 | ZP4: 806000 | ZQ4: =SUM(YL4:ZP4) | ZR4: 1700000 | ZS4: 1007000 | ZT4: 1258000 | ZU4: 2037740 | ZV4: 1400000 | ZW4: 1558046 | ZX4: 1067950 | ZY4: 874500 | ZZ4: 1500000 | AAA4: 820000 | AAB4: 557000 | AAC4: 1795000 | AAD4: 1264000 | AAE4: 1283816 | AAF4: 846472 | AAG4: 862700 | AAH4: 1286000 | AAI4: 1083832 | AAJ4: 1737482 | AAK4: 1940600 | AAL4: 856880 | AAM4: 1585000 | AAN4: 1065000 | AAO4: 1299500 | AAP4: 902509 | AAQ4: 1707000 | AAR4: 1340000 | AAS4: 1388500 | AAT4: 904000 | AAU4: 1704000 | AAV4: =SUM(ZR4:AAU4) | AAW4: 989000 | AAX4: 475000 | AAY4: 878000 | AAZ4: 1711000 | ABA4: 1003500 | ABB4: 1699500 | ABC4: 540200 | ABD4: 1891997 | ABE4: 643000 | ABF4: 1083542 | ABG4: 2508235 | ABH4: 930000 | ABI4: 1800000 | ABJ4: 1536831 | ABK4: 928000 | ABL4: 655000 | ABM4: 2021000 | ABN4: 1669800 | ABO4: 1325000 | ABP4: 1076200 | ABQ4: 1162626 | ABR4: 1196500 | ABS4: 1151404 | ABT4: 952009 | ABU4: 930000 | ABV4: 1084000 | ABW4: 650000 | ABX4: 1264000 | ABY4: 838500 | ABZ4: 1313000 | ACA4: 1996500 | ACB4: =SUM(AAX4:ACA4) | ACC4: 913000 | ACD4: 2157364 | ACE4: 1061000 | ACF4: 2929500 | ACG4: 872000 | ACH4: 1941000 | ACI4: 2588547 | ACJ4: 1466250 | ACK4: 1385000 | ACL4: 540000 | ACM4: 1318000 | ACN4: 1194500 | ACO4: 916153 | ACP4: 966076 | ACQ4: 841000 | ACR4: 1688600 | ACS4: 1151000 | ACT4: 1667535 | ACU4: 819000 | ACV4: 967190 | ACW4: 710190 | ACX4: 2732000 | ACY4: 770333 | ACZ4: 1530500 | ADA4: 1464731 | ADB4: 751200 | ADC4: 815000 | ADD4: 473000 | ADE4: 939000 | ADF4: 1066000 | ADG4: 478000 | ADH4: =SUM(ACC4:ADG4) | ADI4: 1126000 | ADJ4: 1642601 | ADK4: 1538000 | ADL4: 1410746 | ADM4: 1099000 | ADN4: 1186000 | ADO4: 1107800 | ADP4: 742000 | ADQ4: 1020000 | ADR4: 920580 | ADS4: 1103095 | ADT4: 2227109 | ADU4: 962000 | ADV4: 1262000 | ADW4: 882500 | ADX4: 511000 | ADY4: 946060 | ADZ4: 1408400 | AEA4: 1323000 | AEB4: 968000 | AEC4: 1361000 | AED4: 935000 | AEE4: 1044000 | AEF4: 1372000 | AEG4: 1276000 | AEH4: 1004000 | AEI4: 1901000 | AEJ4: 992000 | AEK4: 632000 | AEL4: 1646000 | AEM4: =SUM(ADI4:AEL4) | AEN4: 935893 | AEO4: 890000 | AEP4: 1040040 | AEQ4: 2119000 | AER4: 1027103 | AES4: 944500 | AET4: 703000 | AEU4: 2110142 | AEV4: 1684900 | AEW4: 2658489 | AEX4: 1535000 | AEY4: 1361788 | AEZ4: 2107984 | AFA4: 354000 | AFB4: 657142 | AFC4: 761000 | AFD4: 730024 | AFE4: 889000 | AFF4: 849000 | AFG4: 625000 | AFH4: 1102000 | AFI4: 1283000 | AFJ4: 1236827 | AFK4: 974000 | AFL4: 1400000 | AFM4: 2008974 | AFN4: 886330 | AFO4: 415000 | AFP4: 630725 | AFQ4: 2195000 | AFR4: 1531000 | AFS4: =SUM(AEN4:AFR4) | AFT4: 599500 | AFU4: 1221000 | AFV4: 1785000 | AFW4: 515000 | AFX4: 1283490 | AFY4: 1077000 | AFZ4: 866000 | AGE4: 60000 | AGN4: 130000 | AGX4: =SUM(AFT4:AGW4) | AID4: =SUM(AGZ4:AIC4) | AJJ4: =SUM(AIF4:AJI4) | AKM4: =SUM(AJI4:AKL4) | ALS4: =SUM(AKO4:ALR4) | AMX4: =SUM(ALT4:AMW4)
A5: AIRTEL | B5: 2169300 | C5: 1204500 | D5: 2185500 | E5: 1573000 | F5: 1008600 | G5: 2899500 | H5: 1116000 | I5: 2236800 | J5: 3300500 | K5: 1593000 | L5: 1335000 | M5: 1260000 | N5: 1038000 | O5: 1021000 | P5: 1538000 | Q5: 582600 | R5: 1396000 | S5: 959000 | T5: 815000 | U5: 1463300 | V5: 1017000 | W5: 790000 | X5: 1052300 | Y5: 1261000 | Z5: 1507800 | AA5: 1014100 | AB5: 1187000 | AC5: 518000 | AD5: 2516000 | AE5: 979000 | AF5: 758000 | AG5: =SUM(B5:AF5) | AH5: 1437000 | AI5: 1046100 | AJ5: 1065000 | AK5: 1675000 | AL5: 1615462 | AM5: 604000 | AN5: 1560238 | AO5: 2003764 | AP5: 867500 | AQ5: 1468000 | AR5: 523400 | AS5: 875000 | AT5: 755900 | AU5: 780000 | AV5: 1337500 | AW5: 1193000 | AX5: 1332000 | AY5: 1432800 | AZ5: 672000 | BA5: 1271300 | BB5: 386700 | BC5: 940740 | BD5: 1522010 | BE5: 540100 | BF5: 904000 | BG5: 2004900 | BH5: 892000 | BI5: 902000 | BJ5: 732000 | BK5: 921000 | BL5: =SUM(AH5:BK5) | BM5: 293000 | BN5: 778000 | BO5: 421900 | BP5: 1368000 | BQ5: 1064560 | BR5: 1124000 | BS5: 1139000 | BT5: 1305800 | BU5: 1657500 | BV5: 828500 | BW5: 306950 | BX5: 947000 | BY5: 639000 | BZ5: 939000 | CA5: 661500 | CB5: 1073000 | CC5: 1259500 | CD5: 314000 | CE5: 860500 | CF5: 712000 | CG5: 1014754 | CH5: 601000 | CI5: 924500 | CJ5: 480000 | CK5: 1637500 | CL5: 1332000 | CM5: 1067900 | CN5: 1758000 | CO5: 507950 | CP5: 1675700 | CQ5: 922000 | CR5: =SUM(BM5:CQ5) | CS5: 1279000 | CT5: 1380000 | CU5: 1038000 | CV5: 1588010 | CW5: 622053 | CX5: 1828800 | CY5: 1008122 | CZ5: 838000 | DA5: 1369500 | DB5: 972073 | DC5: 694000 | DD5: 1175500 | DE5: 1133695 | DF5: 1438390 | DG5: 1093000 | DH5: 612100 | DI5: 2553150 | DJ5: 497100 | DK5: 969000 | DL5: 1626490 | DM5: 1000900 | DN5: 903500 | DO5: 953000 | DP5: 679000 | DQ5: 1415100 | DR5: 819500 | DS5: 981500 | DT5: 2126000 | DU5: 514000 | DV5: 1322000 | DW5: =SUM(CS5:DV5) | DX5: 1631000 | DY5: 898000 | DZ5: 352000 | EA5: 370500 | EB5: 1413000 | EC5: 724000 | ED5: 914000 | EE5: 1747780 | EF5: 1047000 | EG5: 1539400 | EH5: 1161000 | EI5: 1748000 | EJ5: 2177962 | EK5: 1605850 | EL5: 961000 | EM5: 1564000 | EN5: 684000 | EO5: 1224900 | EP5: 803000 | EQ5: 1502000 | ER5: 2153000 | ES5: 1266500 | ET5: 2187000 | EU5: 717112 | EV5: 1548038 | EW5: 1201000 | EX5: 1383205 | EY5: 1702500 | EZ5: 1892700 | FA5: 1325000 | FB5: 789540 | FC5: =SUM(DX5:FB5) | FD5: 626333 | FE5: 439000 | FF5: 532000 | FG5: 1204900 | FH5: 2003124 | FI5: 518000 | FJ5: 955000 | FK5: 789000 | FL5: 1582000 | FM5: 275000 | FN5: 1662000 | FO5: 1093044 | FP5: 974000 | FQ5: 1022000 | FR5: 1178674 | FS5: 650000 | FT5: 1880000 | FU5: 1582000 | FV5: 1813000 | FW5: 884000 | FX5: 853000 | FY5: 662000 | FZ5: 569000 | GA5: 1526170 | GB5: 1524000 | GC5: 2441200 | GD5: 947000 | GE5: 1374000 | GF5: 1462000 | GG5: 785000 | GH5: 1781000 | GI5: =SUM(FD5:GH5) | GJ5: 1640000 | GK5: 1490000 | GL5: 1449034 | GM5: 453000 | GN5: 932000 | GO5: 800000 | GP5: 1696000 | GQ5: 957000 | GR5: 1689000 | GS5: 1344500 | GT5: 1077000 | GU5: 1599000 | GV5: 1359300 | GW5: 823703 | GX5: 1075000 | GY5: 1126972 | GZ5: 967602 | HA5: 814900 | HB5: 695000 | HC5: 1540390 | HD5: 1150200 | HE5: 715000 | HF5: 991160 | HG5: 1064000 | HH5: 771000 | HI5: 834000 | HJ5: 1032000 | HK5: 1441808 | HL5: 1368946 | HM5: =SUM(GJ5:HL5) | HN5: 1175000 | HO5: 1055000 | HP5: 1062000 | HQ5: 1519000 | HR5: 1896823 | HS5: 805900 | HT5: 1278160 | HU5: 1486160 | HV5: 1685000 | HW5: 1362000 | HX5: 1367000 | HY5: 1354000 | HZ5: 610000 | IA5: 1363500 | IB5: 3145400 | IC5: 828000 | ID5: 1249650 | IE5: 882000 | IF5: 1695000 | IG5: 924000 | IH5: 470400 | II5: 1703000 | IJ5: 1364500 | IK5: 1592250 | IL5: 1259400 | IM5: 1312500 | IN5: 932700 | IO5: 2296900 | IP5: 816000 | IQ5: 1421500 | IR5: 588400 | IS5: =SUM(HN5:IR5) | IT5: 1128000 | IU5: 1561182 | IV5: 785400 | IW5: 1354000 | IX5: 1117000 | IY5: 1191500 | IZ5: 953000 | JA5: 797500 | JB5: 1702000 | JC5: 1038000 | JD5: 1434000 | JE5: 1106900 | JF5: 2077500 | JG5: 1378500 | JH5: 983000 | JI5: 1536780 | JJ5: 1079000 | JK5: 641000 | JL5: 2637636 | JM5: 1292500 | JN5: 1081000 | JO5: 2728500 | JP5: 1455080 | JQ5: 2339531 | JR5: 465000 | JS5: 1207000 | JT5: 2168000 | JU5: 811500 | JV5: 1463085 | JW5: 1701000 | JX5: =SUM(IT5:JW5) | JY5: 1371000 | JZ5: 1212900 | KA5: 1798700 | KB5: 1761460 | KC5: 1253744 | KD5: 2674320 | KE5: 3076340 | KF5: 1821680 | KG5: 2480880 | KH5: 3013300 | KI5: 2133730 | KJ5: 830000 | KK5: 2986700 | KL5: 2926900 | KM5: 1457000 | KN5: 3459050 | KO5: 2108730 | KP5: 2337500 | KQ5: 1024000 | KR5: 2445590 | KS5: 2456370 | KT5: 2496500 | KU5: 2019000 | KV5: 2412200 | KW5: 2207880 | KX5: 1173000 | KY5: 3002660 | KZ5: 3333000 | LA5: 2541000 | LB5: 5008500 | LC5: 1319950 | LD5: =SUM(JY5:LC5) | LE5: 3509660 | LF5: 1950100 | LG5: 2454000 | LH5: 2263350 | LI5: 1815450 | LJ5: 3072850 | LK5: 2489700 | LL5: 3426000 | LM5: 854000 | LN5: 2294000 | LO5: 4265268 | LP5: 1658740 | LQ5: 2202000 | LR5: 2962213 | LS5: 2793343 | LT5: 888200 | LU5: 1877900 | LV5: 2867000 | LW5: 2999209 | LX5: 2113000 | LY5: 3588000 | LZ5: 2049000 | MA5: 514000 | MB5: 3290450 | MC5: 1602350 | MD5: 2205740 | ME5: 1228000 | MF5: 3280836 | MG5: 1326000 | MH5: 2044500 | MI5: =SUM(LD5:MH5) | MJ5: 2181100 | MK5: 1937000 | ML5: 2369000 | MM5: 1965000 | MN5: 3602000 | MO5: 1638900 | MP5: 1732500 | MQ5: 3546370 | MR5: 2896501 | MS5: 1682000 | MT5: 3423000 | MU5: 3320000 | MV5: 2853000 | MW5: 1558000 | MX5: 2680100 | MY5: 2541000 | MZ5: 1547700 | NA5: 2616018 | NB5: 1513117 | NC5: 1290000 | ND5: 960320 | NE5: 1776600 | NF5: 2696000 | NG5: 1796000 | NH5: 2729300 | NI5: 3264100 | NJ5: 1277000 | NK5: 1236000 | NL5: 2005000 | NM5: 2110300 | NN5: 1924000 | NO5: =SUM(MJ5:NN5) | NP5: 2068500 | NQ5: 2502000 | NR5: 3647892 | NS5: 1743500 | NT5: 2372800 | NU5: 3323409 | NV5: 2913000 | NW5: 3078500 | NX5: 2473000 | NY5: 1880700 | NZ5: 1440904 | OA5: 1790000 | OB5: 1453000 | OC5: 2304900 | OD5: 962000 | OE5: 2684415 | OF5: 1532500 | OG5: 1156500 | OH5: 1015000 | OI5: 1457000 | OJ5: 1379300 | OK5: 1078000 | OL5: 1264500 | OM5: 1287000 | ON5: 329000 | OO5: 1526500 | OP5: 3350963 | OQ5: 889760 | OR5: 1603260 | OS5: 1257010 | OT5: 1341760 | OU5: =SUM(NP5:OT5) | OV5: 947500 | OW5: 1358900 | OX5: 2014100 | OY5: 2974000 | OZ5: 2374500 | PA5: 1228000 | PB5: 1187500 | PC5: 1214000 | PD5: 1520000 | PE5: 2447500 | PF5: 1702300 | PG5: 619500 | PH5: 2894600 | PI5: 829400 | PJ5: 1721500 | PK5: 1283000 | PL5: 712000 | PM5: 2373000 | PN5: 1161100 | PO5: 740000 | PP5: 422000 | PQ5: 1482000 | PR5: 924500 | PS5: 1501000 | PT5: 852000 | PU5: 1416714 | PV5: 868000 | PW5: 626500 | PX5: 1067675 | PY5: 1623400 | PZ5: =SUM(OV5:PY5) | QA5: 1145000 | QB5: 740000 | QC5: 1339000 | QD5: 1784600 | QE5: 1214000 | QF5: 2010100 | QG5: 1409000 | QH5: 1523000 | QI5: 1283750 | QJ5: 865250 | QK5: 1958900 | QL5: 1147000 | QM5: 1577500 | QN5: 1405000 | QO5: 2060000 | QP5: 636000 | QQ5: 1711000 | QR5: 1315000 | QS5: 4169700 | QT5: 853500 | QU5: 831500 | QV5: 1104500 | QW5: 1050485 | QX5: 939985 | QY5: 1774000 | QZ5: 596000 | RA5: 1093500 | RB5: 1490750 | RC5: 2072300 | RD5: 1685000 | RE5: 2108908 | RF5: =SUM(QA5:RE5) | RG5: 1267000 | RH5: 626648 | RI5: 1975000 | RJ5: 1515380 | RK5: 972785 | RL5: 1026000 | RM5: 1492000 | RN5: 844000 | RO5: 1084000 | RP5: 993500 | RQ5: 1229000 | RR5: 1433285 | RS5: 1174304 | RT5: 1170400 | RU5: 1685500 | RV5: 1750500 | RW5: 1255500 | RX5: 2286285 | RY5: 2582300 | RZ5: 1316500 | SA5: 710500 | SB5: 1230500 | SC5: 1655500 | SD5: 2170740 | SE5: 2753500 | SF5: 1166755 | SG5: 1054800 | SH5: 1045000 | SI5: 1615900 | SJ5: 1176049 | SK5: =SUM(RG5:SJ5) | SL5: 861500 | SM5: 1074355 | SN5: 1597000 | SO5: 1542000 | SP5: 1968868 | SQ5: 1706000 | SR5: 1294000 | SS5: 678000 | ST5: 2844355 | SU5: 1632350 | SV5: 854000 | SW5: 1259000 | SX5: 2575000 | SY5: 829000 | SZ5: 2259840 | TA5: 1790355 | TB5: 1891560 | TC5: 2340000 | TD5: 2092230 | TE5: 1170000 | TF5: 1300500 | TG5: 1575033 | TH5: 982355 | TI5: 2000000 | TJ5: 1085000 | TK5: 947000 | TL5: 1260500 | TM5: 1830000 | TN5: 1073000 | TO5: 708000 | TP5: 1759910 | TQ5: =SUM(SL5:TP5) | TR5: 353474 | TS5: 1026000 | TT5: 1354000 | TU5: 707560 | TV5: 1308000 | TW5: 845355 | TX5: 776000 | TY5: 1414500 | TZ5: 1806000 | UA5: 2354000 | UB5: 1835000 | UC5: 747000 | UD5: 960000 | UE5: 1686061 | UF5: 1732500 | UG5: 1172000 | UH5: 1116700 | UI5: 1748000 | UJ5: 950000 | UK5: 1577355 | UL5: 1413000 | UM5: 1553000 | UN5: 1473000 | UO5: 1733058 | UP5: 1290800 | UQ5: 1771500 | UR5: 912655 | US5: 1415000 | UT5: 598000 | UU5: 975000 | UV5: 1190241 | UW5: =SUM(TR5:UV5) | UX5: 2338275 | UY5: 1534000 | UZ5: 774000 | VA5: 3229000 | VB5: 1496900 | VC5: 1212000 | VD5: 446900 | VE5: 1182000 | VF5: 1342000 | VG5: 1559500 | VH5: 2429000 | VI5: 1141500 | VJ5: 1779852 | VK5: 1360350 | VL5: 1431900 | VM5: 2328000 | VN5: 694384 | VO5: 1181490 | VP5: 779970 | VQ5: 2053000 | VR5: 1687000 | VS5: 1416000 | VT5: 998096 | VU5: 979000 | VV5: 2288200 | VW5: 1209000 | VX5: 1479710 | VY5: 1340000 | VZ5: =SUM(UX5:VY5) | WA5: 1793000 | WB5: 767800 | WC5: 1308417 | WD5: 1200000 | WE5: 1136000 | WF5: 879000 | WG5: 1398000 | WH5: 1195710 | WI5: 882000 | WJ5: 1475000 | WK5: 1826000 | WL5: 957500 | WM5: 1655000 | WN5: 545000 | WO5: 1730000 | WP5: 966700 | WQ5: 998000 | WR5: 0 | WS5: 773500 | WT5: 1114962 | WU5: 1188000 | WV5: 2092000 | WW5: 1486000 | WX5: 1547000 | WY5: 2942000 | WZ5: 837000 | XA5: 2102000 | XB5: 1461000 | XC5: 1935500 | XD5: 907000 | XE5: 2456059 | XF5: =SUM(WA5:XE5) | XG5: 1335500 | XH5: 1223000 | XI5: 1796400 | XJ5: 1669620 | XK5: 987000 | XL5: 2099520 | XM5: 1922587 | XN5: 1718200 | XO5: 1281540 | XP5: 1406800 | XQ5: 3226734 | XR5: 1601743 | XS5: 1498000 | XT5: 1722000 | XU5: 2090826 | XV5: 1640550 | XW5: 1180000 | XX5: 2219900 | XY5: 2042700 | XZ5: 1665000 | YA5: 1651000 | YB5: 847500 | YC5: 946000 | YD5: 1965000 | YE5: 3158207 | YF5: 1514000 | YG5: 1588000 | YH5: 1262000 | YI5: 677500 | YJ5: 939000 | YK5: =SUM(XF5:YJ5) | YL5: 1639500 | YM5: 2209500 | YN5: 1083000 | YO5: 618600 | YP5: 1447000 | YQ5: 902000 | YR5: 820000 | YS5: 300000 | YT5: 1322222 | YU5: 1256000 | YV5: 1026000 | YW5: 1207000 | YX5: 1634100 | YY5: 1019000 | YZ5: 955000 | ZA5: 1267179 | ZB5: 1449000 | ZC5: 1049800 | ZD5: 956000 | ZE5: 1937059 | ZF5: 1925000 | ZG5: 1302000 | ZH5: 1800000 | ZI5: 1537000 | ZJ5: 1018000 | ZK5: 2519750 | ZL5: 1507000 | ZM5: 1362500 | ZN5: 2789000 | ZO5: 1091000 | ZP5: 1843000 | ZQ5: =SUM(YL5:ZP5) | ZR5: 1001000 | ZS5: 2577500 | ZT5: 1070000 | ZU5: 1873000 | ZV5: 1305000 | ZW5: 865000 | ZX5: 1109126 | ZY5: 896000 | ZZ5: 577000 | AAA5: 760000 | AAB5: 570500 | AAC5: 986000 | AAD5: 1238910 | AAE5: 1803000 | AAF5: 1769000 | AAG5: 1166331 | AAH5: 1083000 | AAI5: 1913000 | AAJ5: 1152500 | AAK5: 3011624 | AAL5: 1532000 | AAM5: 1725200 | AAN5: 1507000 | AAO5: 1281000 | AAP5: 1384450 | AAQ5: 1794000 | AAR5: 1074000 | AAS5: 2144905 | AAT5: 1223000 | AAU5: 1762500 | AAV5: =SUM(ZR5:AAU5) | AAW5: 2785500 | AAX5: 2495500 | AAY5: 690000 | AAZ5: 1472950 | ABA5: 1637000 | ABB5: 1435620 | ABC5: 522000 | ABD5: 2259300 | ABE5: 1249800 | ABF5: 784800 | ABG5: 1543000 | ABH5: 2222000 | ABI5: 2834100 | ABJ5: 2086000 | ABK5: 2130000 | ABL5: 1464423 | ABM5: 1012000 | ABN5: 2304000 | ABO5: 1219000 | ABP5: 1872000 | ABQ5: 1451756 | ABR5: 1703000 | ABS5: 1161000 | ABT5: 1376919 | ABU5: 3343700 | ABV5: 2548165 | ABW5: 1789000 | ABX5: 2167500 | ABY5: 2920555 | ABZ5: 856000 | ACA5: 1518122 | ACB5: =SUM(AAX5:ACA5) | ACC5: 880000 | ACD5: 2694000 | ACE5: 715000 | ACF5: 1902000 | ACG5: 1794000 | ACH5: 2131000 | ACI5: 1135000 | ACJ5: 1842500 | ACK5: 1679000 | ACL5: 1831500 | ACM5: 1384000 | ACN5: 1030100 | ACO5: 1275000 | ACP5: 1949636 | ACQ5: 1883000 | ACR5: 1315000 | ACS5: 1908831 | ACT5: 965000 | ACU5: 1316000 | ACV5: 1061000 | ACW5: 899500 | ACX5: 1284500 | ACY5: 1039841 | ACZ5: 1944500 | ADA5: 1203400 | ADB5: 190000 | ADC5: 1313810 | ADD5: 1376000 | ADE5: 2718047 | ADF5: 942500 | ADG5: 1488000 | ADH5: =SUM(ACC5:ADG5) | ADI5: 1329841 | ADJ5: 1307000 | ADK5: 965500 | ADL5: 1118000 | ADM5: 1168000 | ADN5: 1031500 | ADO5: 1091000 | ADP5: 1293258 | ADQ5: 2401300 | ADR5: 1708000 | ADS5: 2010800 | ADT5: 2558500 | ADU5: 1596000 | ADV5: 843095 | ADW5: 1831000 | ADX5: 1046000 | ADY5: 1386000 | ADZ5: 1149500 | AEA5: 1362500 | AEB5: 1764900 | AEC5: 1399000 | AED5: 1269500 | AEE5: 1351000 | AEF5: 775000 | AEG5: 596000 | AEH5: 1415000 | AEI5: 1336000 | AEJ5: 613500 | AEK5: 1426595 | AEL5: 3026000 | AEM5: =SUM(ADI5:AEL5) | AEN5: 1106700 | AEO5: 1305000 | AEP5: 1132000 | AEQ5: 1816506 | AER5: 1511595 | AES5: 456000 | AET5: 868000 | AEU5: 1516000 | AEV5: 2305000 | AEW5: 1115000 | AEX5: 1866609 | AEY5: 1938632 | AEZ5: 1668000 | AFA5: 2289500 | AFB5: 1227000 | AFC5: 1079000 | AFD5: 1200500 | AFE5: 1198100 | AFF5: 1668000 | AFG5: 1181000 | AFH5: 1140000 | AFI5: 1120000 | AFJ5: 1875206 | AFK5: 1968848 | AFL5: 2085000 | AFM5: 1869600 | AFN5: 979000 | AFO5: 760000 | AFP5: 1840500 | AFQ5: 2492800 | AFR5: 1472000 | AFS5: =SUM(AEN5:AFR5) | AFT5: 2164800 | AFU5: 2186435 | AFV5: 838600 | AFW5: 1976800 | AFX5: 2283800 | AFY5: 2140255 | AFZ5: 662000 | AGA5: 30000 | AGF5: 0 | AGX5: =SUM(AFT5:AGW5) | AID5: =SUM(AGZ5:AIC5) | AJJ5: =SUM(AIF5:AJI5) | AKM5: =SUM(AJI5:AKL5) | ALS5: =SUM(AKO5:ALR5) | AMC5: 10000 | AMX5: =SUM(ALT5:AMW5) | ANS5: 284000 | ANT5: 753500 | ANU5: 856000 | ANV5: 742300 | ANW5: 2482975 | ANX5: 3207095 | ANY5: 474400 | ANZ5: 1656250 | AOA5: 1653800 | AOB5: 2389033 | AOC5: 1055808 | AOD5: 1055808
A6: VISA CARD | B6: 710000 | C6: 330000 | D6: 55000 | E6: 1316400 | F6: 1692230 | G6: 1004268 | H6: 372000 | I6: 472250 | J6: 490000 | K6: 771000 | L6: 2024588 | M6: 440000 | N6: 913865 | O6: 585000 | P6: 170000 | Q6: 887317 | R6: 164000 | S6: 641000 | T6: =837500+(563500) | U6: 260000 | V6: 492000 | W6: 360000 | X6: 1266321 | Y6: 835700 | Z6: 1106385 | AA6: 488300 | AB6: 1433857 | AC6: 575000 | AD6: 623000 | AE6: 1086000 | AF6: 415000 | AG6: =SUM(B6:AF6) | AH6: 897366 | AI6: 886028 | AJ6: 830500 | AK6: 555941 | AL6: 518000 | AM6: 312000 | AN6: 494503 | AO6: 575746 | AP6: 455000 | AQ6: 634000 | AR6: 415822 | AS6: 400600 | AT6: 1052000 | AU6: 886500 | AV6: =190000+170000 | AW6: 470200 | AX6: 520000 | AY6: 426000 | AZ6: 260000 | BA6: 257000 | BB6: 465000 | BC6: 522000 | BD6: 300900 | BE6: 549042 | BF6: 425958 | BG6: 728000 | BH6: 895800 | BI6: 771833 | BJ6: 60000 | BK6: 726071 | BL6: =SUM(AH6:BK6) | BM6: 595500 | BN6: 396500 | BO6: 702558 | BP6: 310000 | BQ6: 695663 | BR6: 894000 | BS6: 366000 | BT6: 740500 | BU6: 728950 | BV6: 641000 | BW6: 600600 | BX6: 1840000 | BY6: 1052574 | BZ6: 197800 | CA6: 668000 | CB6: 418000 | CC6: 459000 | CD6: 434000 | CE6: 470565 | CF6: 820124 | CG6: 422000 | CH6: 588000 | CI6: 203500 | CJ6: 898400 | CK6: 320000 | CL6: 871900 | CM6: 445000 | CN6: 577200 | CO6: 522000 | CP6: 527000 | CQ6: 540400 | CR6: =SUM(BM6:CQ6) | CS6: 17500 | CT6: 436500 | CU6: 130000 | CV6: 315000 | CW6: 911800 | CX6: 588696 | CY6: 160500 | CZ6: 224500 | DA6: 183000 | DB6: 293000 | DC6: 235000 | DD6: 427000 | DE6: 443000 | DF6: 1057612 | DG6: 120000 | DH6: 592800 | DI6: 193000 | DJ6: 263000 | DK6: 399500 | DL6: 669370 | DN6: 180000 | DO6: 946000 | DP6: 140000 | DQ6: 649500 | DR6: 160000 | DS6: 30000 | DT6: 0 | DU6: 100000 | DV6: 182000 | DW6: =SUM(CS6:DV6) | DX6: 899800 | DY6: 123500 | DZ6: 237000 | EA6: 571000 | EB6: 46000 | EC6: 110000 | ED6: 9500 | EE6: 56000 | EF6: 999600 | EG6: 510900 | EH6: 892013 | EI6: 785000 | EJ6: 470000 | EK6: 254000 | EL6: 1184911 | EM6: 430300 | EN6: 1065500 | EO6: 689000 | EP6: 668849 | EQ6: 689800 | ER6: 1842300 | ES6: 643800 | ET6: 311042 | EU6: 823000 | EV6: 1224751 | EW6: 10000 | EX6: 190500 | EY6: 1169700 | EZ6: 933150 | FA6: 451000 | FB6: 96000 | FC6: =SUM(DX6:FB6) | FD6: 498300 | FE6: 444600 | FF6: 150000 | FG6: 710061 | FH6: 130000 | FI6: 233500 | FJ6: 247200 | FK6: 737988 | FL6: 415000 | FM6: 110000 | FO6: 535900 | FP6: 849633 | FQ6: 313400 | FR6: 811443 | FS6: 309500 | FT6: 752500 | FU6: 286500 | FV6: 205000 | FW6: 416000 | FX6: 1159300 | FY6: 1955500 | GA6: 394372 | GB6: 565000 | GC6: 716900 | GD6: 476500 | GE6: 560000 | GF6: 516929 | GG6: 410000 | GH6: 404500 | GI6: =SUM(FD6:GH6) | GJ6: 30000 | GK6: 421000 | GL6: 674553 | GM6: 546964 | GN6: 576500 | GO6: 1559030 | GP6: 100000 | GQ6: 655500 | GR6: 229000 | GS6: 202000 | GT6: 135500 | GU6: 687592 | GV6: 0 | GW6: 80000 | GX6: 495000 | GY6: 200000 | GZ6: 710000 | HA6: 150000 | HB6: 173000 | HC6: 60000 | HD6: 512000 | HE6: 0 | HF6: 1030000 | HG6: 700000 | HH6: 482000 | HI6: 405500 | HJ6: 345000 | HK6: 540500 | HL6: 215500 | HM6: =SUM(GJ6:HL6) | HN6: 595236 | HO6: 1229495 | HP6: 241000 | HQ6: 935000 | HR6: 427500 | HS6: 485900 | HT6: 508856 | HU6: 270000 | HV6: 82500 | HW6: 150000 | HY6: 0 | IA6: 0 | ID6: 217000 | IE6: 181000 | IF6: 147400 | IH6: 500000 | II6: 180000 | IJ6: 1014861 | IK6: 39000 | IL6: 1102000 | IM6: 225500 | IN6: 289200 | IO6: 50000 | IS6: =SUM(HN6:IR6) | IX6: 195200 | IY6: 316100 | IZ6: 830000 | JA6: 212500 | JB6: 131800 | JC6: 672710 | JD6: 512051 | JE6: 0 | JF6: 456000 | JG6: 270000 | JH6: 150000 | JI6: 311000 | JJ6: 15400 | JK6: 446400 | JL6: 30000 | JM6: 130000 | JN6: 270000 | JO6: 425000 | JP6: 230000 | JQ6: 250000 | JR6: 350000 | JS6: 105000 | JT6: 1214791 | JU6: 1471648 | JV6: 622165 | JW6: 130000 | JX6: =SUM(IT6:JW6) | JY6: 755000 | JZ6: 373000 | KA6: 390000 | KB6: 870656 | KC6: 570000 | KD6: 70000 | KE6: 485000 | KF6: 360000 | KG6: 450000 | KH6: 799117 | KI6: 930000 | KJ6: 600000 | KK6: 90000 | KL6: 993800 | KN6: 687500 | KO6: 389146 | KP6: 1128300 | KQ6: 1103556 | KR6: 300000 | KS6: 966000 | KT6: 330000 | KU6: 497000 | KV6: 220000 | KW6: 360000 | KX6: 678200 | KY6: 731000 | KZ6: 50000 | LA6: 399500 | LB6: 414000 | LC6: 1090000 | LD6: =SUM(JY6:LC6) | LE6: 921600 | LF6: 365000 | LG6: 554000 | LH6: 1308465 | LI6: 285000 | LJ6: 122000 | LK6: 1396128 | LL6: 494500 | LM6: 451500 | LN6: 740000 | LO6: 880000 | LP6: 852000 | LQ6: 140000 | LR6: 248000 | LS6: 330000 | LT6: 607000 | LU6: 500785 | LV6: 1053000 | LW6: 876000 | LX6: 577000 | LY6: 1220000 | LZ6: 836000 | MA6: 472994 | MB6: 570900 | MC6: 692700 | MD6: 585877 | ME6: 154000 | MF6: 250000 | MG6: 441400 | MH6: 360000 | MI6: =SUM(LD6:MH6) | MJ6: 1381874 | MK6: 901000 | ML6: 355000 | MM6: 245000 | MN6: 612000 | MO6: 630967 | MP6: 875000 | MQ6: 218000 | MR6: 195000 | MS6: 416500 | MT6: 660000 | MU6: 395000 | MV6: 1202153 | MW6: 308000 | MX6: 245000 | MY6: 428000 | MZ6: 310000 | NA6: 375000 | NB6: 435500 | NC6: 220000 | ND6: 1334000 | NE6: 450000 | NF6: 683156 | NG6: 200000 | NH6: 295032 | NI6: 679152 | NJ6: 865604 | NK6: 688000 | NL6: 711000 | NM6: 305000 | NN6: 601000 | NO6: =SUM(MJ6:NN6) | NP6: 597000 | NQ6: 385000 | NR6: 872000 | NS6: 1037332 | NT6: 950000 | NU6: 420000 | NV6: 107000 | NW6: 558000 | NX6: 1105956 | NY6: 1068000 | NZ6: 566616 | OA6: 1150000 | OB6: 33500 | OC6: 70000 | OD6: 165500 | OE6: 444400 | OF6: 1043024 | OG6: 196000 | OH6: 340000 | OI6: 100000 | OJ6: 439823 | OK6: 440000 | OL6: 342000 | OM6: 319000 | ON6: 105000 | OO6: 575000 | OP6: 240000 | OQ6: 71900 | OR6: 625000 | OS6: 593800 | OT6: 776277 | OU6: =SUM(NP6:OT6) | OV6: 648791 | OW6: 570700 | OX6: 533500 | OY6: 520000 | OZ6: 515000 | PA6: 1129576 | PB6: 170000 | PC6: 206000 | PD6: 750000 | PE6: 215000 | PF6: 252415 | PG6: 206900 | PH6: 497500 | PI6: 125000 | PJ6: 463000 | PK6: 132000 | PL6: 831000 | PM6: 473162 | PN6: 57000 | PO6: 331500 | PP6: 320000 | PQ6: 281750 | PR6: 389000 | PS6: 476900 | PT6: 50000 | PU6: 275000 | PV6: 385900 | PW6: 714596 | PX6: 738800 | PY6: 399000 | PZ6: =SUM(OV6:PY6) | QA6: 240000 | QB6: 450000 | QC6: 350000 | QD6: 562950 | QE6: 335000 | QF6: 235000 | QG6: 760000 | QH6: 488000 | QI6: 200000 | QJ6: 300000 | QK6: 674909 | QL6: 282000 | QM6: 465700 | QN6: 470000 | QO6: 325000 | QP6: 330000 | QQ6: 271000 | QR6: 637550 | QS6: 343900 | QT6: 484000 | QU6: 356000 | QV6: 314000 | QW6: 430000 | QX6: 610000 | QY6: 400000 | QZ6: 410000 | RA6: 266000 | RB6: 480000 | RC6: 799500 | RD6: 170000 | RE6: 220000 | RF6: =SUM(QA6:RE6) | RG6: 824890 | RH6: 70000 | RI6: 45000 | RJ6: 665000 | RK6: 0 | RL6: 235000 | RM6: 126000 | RN6: 207000 | RO6: 25000 | RP6: 276000 | RQ6: 638711 | RR6: 150000 | RS6: 1243466 | RT6: 200000 | RU6: 380000 | RV6: 310000 | RW6: 625742 | RX6: 881400 | RY6: 1161000 | RZ6: 200000 | SA6: 55000 | SB6: 758802 | SC6: 79500 | SD6: 176000 | SE6: 767000 | SF6: 424500 | SG6: 275500 | SH6: 313000 | SI6: 360000 | SJ6: 552496 | SK6: =SUM(RG6:SJ6) | SL6: 320000 | SM6: 510000 | SN6: 230000 | SO6: 325000 | SP6: 120000 | SQ6: 385000 | SR6: 80000 | SS6: 210000 | ST6: 697150 | SU6: 270000 | SV6: 1065000 | SW6: 315000 | SX6: 723000 | SY6: 219000 | SZ6: 110000 | TA6: 172000 | TB6: 148000 | TC6: 289000 | TD6: 546663 | TE6: 270000 | TF6: 450000 | TG6: 285000 | TH6: 320000 | TI6: 194500 | TJ6: 612000 | TK6: 330000 | TL6: 961400 | TM6: 932500 | TN6: 253000 | TO6: 461500 | TP6: 280000 | TQ6: =SUM(SL6:TP6) | TR6: 1005085 | TS6: 191000 | TT6: 45500 | TU6: 450000 | TV6: 324500 | TW6: 190000 | TX6: 574371 | TY6: 670978 | TZ6: 330000 | UA6: 400000 | UB6: 448900 | UC6: 170000 | UD6: 120000 | UE6: 486011 | UF6: 250000 | UG6: 448864 | UH6: 625000 | UI6: 743314 | UJ6: 350000 | UK6: 725000 | UL6: 315524 | UM6: 700000 | UN6: 550000 | UO6: 611000 | UP6: 525000 | UQ6: 1040000 | UR6: 380000 | US6: 187000 | UT6: 112000 | UU6: 120000 | UV6: 410000 | UW6: =SUM(TR6:UV6) | UX6: 228000 | UY6: 520000 | UZ6: 310000 | VA6: 167000 | VB6: 263766 | VC6: 603000 | VD6: 470000 | VE6: 390500 | VF6: 288500 | VG6: 211000 | VH6: 858500 | VI6: 430000 | VJ6: 9500 | VK6: 433500 | VL6: 195000 | VM6: 177000 | VN6: 779200 | VO6: 301500 | VP6: 120000 | VQ6: 20000 | VR6: 378500 | VS6: 175300 | VT6: 245000 | VU6: 221000 | VV6: 159101 | VW6: 338500 | VX6: 354000 | VY6: 354000 | VZ6: =SUM(UX6:VY6) | WA6: 143000 | WB6: 563955 | WC6: 300000 | WD6: 1452456 | WE6: 173000 | WF6: 214000 | WG6: 561000 | WH6: 400000 | WI6: 384000 | WJ6: 260000 | WK6: 150000 | WL6: 526000 | WM6: 240000 | WN6: 615000 | WO6: 500000 | WP6: 239000 | WQ6: 10000 | WR6: 1078795 | WS6: 250000 | WT6: 50000 | WU6: 205000 | WV6: 522036 | WW6: 450000 | WX6: 316000 | WY6: 405000 | WZ6: 230000 | XA6: 1320000 | XB6: 658863 | XC6: 476441 | XD6: 182000 | XE6: 140000 | XF6: =SUM(WA6:XE6) | XG6: 395000 | XH6: 122000 | XI6: 500000 | XJ6: 232000 | XK6: 160000 | XL6: 840424 | XM6: 461462 | XN6: 0 | XO6: 88000 | XP6: 145000 | XQ6: 410000 | XR6: 596310 | XS6: 307578 | XT6: 80000 | XU6: 496000 | XV6: 150000 | XW6: 470000 | XX6: 255000 | XY6: 400000 | XZ6: 303786 | YA6: 615000 | YB6: 50000 | YC6: 160000 | YD6: 713728 | YE6: 445000 | YF6: 1309036 | YG6: 618000 | YH6: 20000 | YI6: 40000 | YJ6: 550000 | YK6: =SUM(XF6:YJ6) | YL6: 477000 | YM6: 584320 | YN6: 343000 | YO6: 275000 | YP6: 120000 | YQ6: 417000 | YR6: 410000 | YS6: 435000 | YT6: 150000 | YU6: 565000 | YV6: 33000 | YW6: 212000 | YX6: 520000 | YY6: 579850 | YZ6: 222500 | ZA6: 100000 | ZB6: 543990 | ZC6: 50000 | ZD6: 180000 | ZE6: 50000 | ZF6: 200000 | ZG6: 479500 | ZH6: 220000 | ZI6: 514186 | ZJ6: 201500 | ZK6: 265000 | ZL6: 410000 | ZM6: 110000 | ZN6: 360000 | ZO6: 173000 | ZP6: 80000 | ZQ6: =SUM(YL6:ZP6) | ZR6: 230000 | ZS6: 195000 | ZT6: 185000 | ZU6: 135000 | ZV6: 308449 | ZW6: 1201950 | ZX6: 120000 | ZY6: 405500 | ZZ6: 40000 | AAA6: 80000 | AAB6: 220000 | AAC6: 405000 | AAD6: 395000 | AAE6: 1682500 | AAF6: 638146 | AAG6: 421822 | AAH6: 348000 | AAI6: 217000 | AAJ6: 200000 | AAK6: 220000 | AAL6: 838500 | AAM6: 513500 | AAN6: 260000 | AAO6: 0 | AAP6: 1171000 | AAQ6: 847000 | AAR6: 729260 | AAS6: 823737 | AAT6: 488595 | AAU6: 120000 | AAV6: =SUM(ZR6:AAU6) | AAW6: 791000 | AAX6: 420500 | AAY6: 82000 | AAZ6: 632242 | ABA6: 417000 | ABB6: 217500 | ABC6: 286000 | ABD6: 477000 | ABE6: 60000 | ABF6: 262600 | ABG6: 150000 | ABH6: 127000 | ABI6: 274400 | ABJ6: 129000 | ABK6: 20000 | ABL6: 335129 | ABM6: 98500 | ABN6: 36000 | ABO6: 491000 | ABP6: 388000 | ABQ6: 365000 | ABS6: 260000 | ABT6: 100000 | ABU6: 498000 | ABV6: 100000 | ABW6: 1117000 | ABX6: 2250000 | ABY6: 10000 | ABZ6: 100000 | ACA6: 127000 | ACB6: =SUM(AAX6:ACA6) | ACC6: 277500 | ACD6: 320000 | ACE6: 810000 | ACF6: 645000 | ACG6: 180000 | ACH6: 271000 | ACJ6: 644642 | ACK6: 126000 | ACL6: 315169 | ACM6: 950000 | ACN6: 470000 | ACO6: 624378 | ACP6: 270000 | ACQ6: 491203 | ACR6: 643122 | ACS6: 345912 | ACT6: 929000 | ACU6: 28000 | ACV6: 163000 | ACW6: 850000 | ACX6: 210500 | ACY6: 586499 | ACZ6: 200000 | ADA6: 0 | ADB6: 1488050 | ADC6: 93000 | ADD6: 504828 | ADE6: 390000 | ADF6: 760000 | ADG6: 509270 | ADH6: =SUM(ACC6:ADG6) | ADI6: 60000 | ADJ6: 427501 | ADK6: 613000 | ADL6: 220095 | ADM6: 204000 | ADN6: 450000 | ADO6: 235000 | ADP6: 210000 | ADQ6: 166000 | ADR6: 848000 | ADS6: 360000 | ADT6: 456000 | ADU6: 411000 | ADV6: 70000 | ADW6: 402541 | ADX6: 631281 | ADY6: 350000 | ADZ6: 250000 | AEA6: 60000 | AEB6: 270000 | AEC6: 290000 | AED6: 270000 | AEE6: 100000 | AEF6: 50000 | AEG6: 150000 | AEH6: 455000 | AEI6: 448416 | AEJ6: 450000 | AEK6: 613048 | AEL6: 235000 | AEM6: =SUM(ADI6:AEL6) | AEN6: 90000 | AEP6: 50000 | AEQ6: 230000 | AER6: 150000 | AES6: 550000 | AET6: 100000 | AEU6: 157000 | AEV6: 1172538 | AEW6: 20000 | AEX6: 165000 | AEZ6: 130000 | AFA6: 327510 | AFB6: 410000 | AFC6: 180000 | AFD6: 210000 | AFE6: 694787 | AFF6: 120000 | AFG6: 390000 | AFH6: 220000 | AFI6: 535892 | AFJ6: 20000 | AFK6: 613558 | AFL6: 465000 | AFM6: 1141975 | AFN6: 252000 | AFO6: 300000 | AFP6: 550000 | AFQ6: 322000 | AFR6: 745000 | AFS6: =SUM(AEN6:AFR6) | AFT6: 30000 | AFU6: 435000 | AFV6: 142000 | AFW6: 240000 | AFX6: 752000 | AFY6: 320000 | AFZ6: 50000 | AGA6: 145000 | AGB6: 253700 | AGC6: 484490 | AGD6: 630000 | AGE6: 425000 | AGF6: 500000 | AGG6: 357227 | AGH6: 510000 | AGI6: 135490 | AGJ6: 864908 | AGK6: 131000 | AGL6: 30000 | AGM6: 110000 | AGN6: 753000 | AGO6: 210000 | AGP6: 379000 | AGQ6: 310000 | AGR6: 824500 | AGS6: 100000 | AGT6: 203790 | AGU6: 412000 | AGV6: 545000 | AGW6: 550000 | AGX6: =SUM(AFT6:AGW6) | AGY6: 630000 | AHA6: 150000 | AHC6: 390000 | AHD6: 634976 | AHE6: 353000 | AHF6: 0 | AHG6: 225000 | AHH6: 1392000 | AHI6: 555700 | AHJ6: 150000 | AHK6: 235000 | AHL6: 930000 | AHM6: 400000 | AHN6: 100000 | AHO6: 250000 | AHP6: 152945 | AHQ6: 775000 | AHR6: 555000 | AHS6: 829235 | AHT6: 500000 | AHU6: 120000 | AHV6: 299490 | AHW6: 664669 | AHX6: 761797 | AHY6: 245000 | AHZ6: 321109 | AIA6: 235000 | AIB6: 430000 | AIC6: 170000 | AID6: =SUM(AGY6:AIC6) | AIE6: 350000 | AIF6: 650000 | AIG6: 270000 | AIH6: 459490 | AII6: 865000 | AIJ6: 440989 | AIK6: 231000 | AIL6: 170000 | AIM6: 880000 | AIN6: 886505 | AIO6: 406093 | AIP6: 402012 | AIQ6: 160000 | AIR6: 150000 | AIS6: 55000 | AIT6: 265000 | AIU6: 130000 | AIV6: 189000 | AIW6: 395000 | AIY6: 150000 | AIZ6: 555500 | AJA6: 210000 | AJB6: 508000 | AJC6: 330000 | AJD6: 170000 | AJE6: 430000 | AJF6: 200000 | AJG6: 410000 | AJH6: 800000 | AJI6: 273000 | AJJ6: =SUM(AIE6:AJI6) | AJK6: 369400 | AJL6: 80000 | AJM6: 286000 | AJN6: 1304077 | AJO6: 357716 | AJP6: 655000 | AJQ6: 346923 | AJR6: 200000 | AJS6: 354960 | AJT6: 80000 | AJU6: 275389 | AJV6: 80000 | AJW6: 150000 | AJX6: 515316 | AJY6: 438000 | AJZ6: 370000 | AKA6: 130000 | AKB6: 324936 | AKC6: 551960 | AKD6: 90000 | AKE6: 355000 | AKF6: 603233 | AKG6: 870000 | AKH6: 886198 | AKI6: 250000 | AKJ6: 672000 | AKK6: 300000 | AKL6: 173000 | AKM6: =SUM(AJK6:AKL6) | AKN6: 1014000 | AKO6: 90000 | AKP6: 350000 | AKQ6: 270000 | AKR6: 100000 | AKS6: 390000 | AKT6: 600000 | AKU6: 105000 | AKV6: 495000 | AKW6: 694109 | AKX6: 320000 | AKY6: 661000 | AKZ6: 370000 | ALA6: 796980 | ALB6: 380000 | ALC6: 1454314 | ALD6: 201000 | ALF6: 1400000 | ALG6: 610000 | ALH6: 220000 | ALI6: 200000 | ALJ6: 356490 | ALK6: 752000 | ALL6: 575000 | ALM6: 450000 | ALN6: 130000 | ALO6: 854486 | ALP6: 749081 | ALQ6: 150000 | ALR6: 100000 | ALS6: =SUM(AKN6:ALR6) | ALT6: 880000 | ALU6: 290000 | ALV6: 626351 | ALW6: 205000 | ALX6: 288000 | ALY6: 813000 | ALZ6: 301515 | AMA6: 119000 | AMB6: 545000 | AMC6: 811200 | AMD6: 130000 | AME6: 50000 | AMF6: 350000 | AMG6: 474000 | AMH6: 480000 | AMI6: 260000 | AMJ6: 95000 | AMK6: 510000 | AML6: 545000 | AMM6: 390000 | AMN6: 1060000 | AMO6: 2173700 | AMP6: 803534 | AMQ6: 1381899 | AMR6: 625000 | AMS6: 575000 | AMT6: 826983 | AMU6: 277500 | AMV6: 873000 | AMW6: 214173 | AMX6: =SUM(ALT6:AMW6) | AMY6: 600000 | AMZ6: 729850 | ANA6: 80000 | ANB6: 164000 | ANC6: 974859 | AND6: 260000 | ANE6: 1992000 | ANF6: 500000 | ANG6: 831816 | ANH6: 300000 | ANI6: 110000 | ANJ6: 979848 | ANK6: 600000 | ANL6: 358586 | ANM6: 842000 | ANN6: 532500 | ANO6: 530000 | ANP6: 300000 | ANQ6: 120000 | ANR6: 520000 | ANS6: 250000 | ANT6: 605000 | ANU6: 1268689 | ANV6: 361648 | ANW6: 978000 | ANX6: 480000 | ANY6: 90000 | ANZ6: 430000 | AOA6: 959887 | AOB6: 498890 | AOC6: 585000 | AOD6: 585000
A7: RUBIS CARD | B7: =699700+730650 | C7: 1207350 | D7: 80750 | E7: 650751 | F7: 301510 | G7: 385500 | H7: 618780 | I7: 100000 | J7: 576500 | K7: 100000 | L7: 1257450 | M7: 246700 | N7: 318030 | O7: 642370 | P7: 1293500 | Q7: 58680 | R7: 2310700 | S7: 336560 | T7: 209250 | U7: 0 | V7: 513640 | W7: 130000 | X7: 1059760 | Z7: 588250 | AA7: 286300 | AB7: 214460 | AC7: 903450 | AD7: 383520 | AE7: 32830 | AF7: 990987 | AG7: =SUM(B7:AF7) | AH7: 305658 | AI7: 195500 | AJ7: 905650 | AK7: 367600 | AL7: 178220 | AM7: 312050 | AN7: 560850 | AO7: 234500 | AP7: 823500 | AQ7: 1087050 | AU7: 792500 | AV7: =147000+196000 | AW7: 367200 | AX7: 199000 | AY7: 546330 | AZ7: 343600 | BB7: 536750 | BC7: 539000 | BD7: 80000 | BE7: 288500 | BF7: 50000 | BG7: 196000 | BH7: 223900 | BI7: 1085500 | BJ7: 891000 | BK7: 173250 | BL7: =SUM(AH7:BK7) | BM7: 237000 | BN7: 247500 | BO7: 611470 | BQ7: 2476000 | BR7: 188420 | BS7: 978190 | BT7: 415090 | BU7: 1905750 | BV7: 695500 | BW7: 819280 | BX7: 0 | BY7: 690867 | BZ7: 869052 | CA7: 628000 | CB7: 267500 | CC7: 386600 | CD7: 2213905 | CF7: 497700 | CG7: 60000 | CH7: 110000 | CI7: 30000 | CK7: 639150 | CL7: 150000 | CM7: 371250 | CO7: 20000 | CP7: 30000 | CQ7: 297500 | CR7: =SUM(BM7:CQ7) | CS7: 207800 | CT7: 1097890 | CU7: 239500 | CV7: 309000 | CW7: 321750 | CX7: 575000 | CY7: 1965279 | CZ7: 332443 | DA7: 1588445 | DB7: 411500 | DC7: 1272170 | DD7: 203000 | DE7: 499243 | DF7: 587079 | DG7: 1108300 | DI7: 2337500 | DJ7: 658453 | DK7: 567000 | DL7: 979200 | DM7: 424350 | DN7: 2125700 | DO7: 290250 | DS7: 3644800 | DT7: 436500 | DV7: 509400 | DW7: =SUM(CS7:DV7) | DX7: 1108003 | DY7: 1696000 | DZ7: 420000 | EA7: 100000 | EC7: 650000 | ED7: 888900 | EF7: 315250 | EG7: 103500 | EH7: 1035000 | EI7: 1548609 | EJ7: 647750 | EK7: 291000 | EL7: 1843000 | EM7: 681000 | EN7: 201000 | EO7: 160000 | EP7: 242500 | EQ7: 582000 | ER7: 1940000 | ES7: 100000 | EV7: 102960 | EW7: 32000 | FA7: 542500 | FB7: 339500 | FC7: =SUM(DX7:FB7) | FD7: 339400 | FE7: 1661900 | FF7: 1812500 | FG7: 277000 | FI7: 1528900 | FJ7: 194000 | FK7: 194000 | FL7: 545362 | FO7: 2449250 | FQ7: 194000 | FR7: 1908250 | FS7: 0 | FT7: 175000 | FU7: 315250 | FW7: 100000 | FX7: 214750 | FZ7: 2677867 | GB7: 127000 | GC7: 205000 | GD7: 1727380 | GF7: 318250 | GG7: 1600000 | GH7: 339500 | GI7: =SUM(FD7:GH7) | GJ7: 1635200 | GK7: 1623530 | GL7: 5290 | GM7: 890982 | GN7: 1050900 | GO7: 582500 | GP7: 1996700 | GQ7: 528969 | GR7: 342307 | GS7: 2002500 | GT7: 262500 | GU7: 324950 | GV7: 100000 | GW7: 1982400 | GX7: 349200 | GY7: 291000 | GZ7: 720000 | HA7: 100000 | HB7: 1700500 | HC7: 642350 | HD7: 258550 | HE7: 200000 | HF7: 197000 | HG7: 2282500 | HI7: 955515 | HK7: 420500 | HL7: 927000 | HM7: =SUM(GJ7:HL7) | HN7: 1939453 | HO7: 388000 | HP7: 1000000 | HQ7: 2589326 | HR7: 1164150 | HS7: 50000 | HT7: 366750 | HU7: 777864 | HV7: 2513650 | HW7: 0 | HX7: 1290000 | HY7: 0 | HZ7: 250000 | IA7: 1287337 | IB7: 452250 | IC7: 299000 | ID7: 398500 | IE7: 1478000 | IF7: 1232000 | IG7: 399530 | IH7: 2235450 | II7: 321000 | IJ7: 97000 | IK7: 0 | IL7: 1466000 | IM7: 441000 | IN7: 224217 | IO7: 250000 | IP7: 1700000 | IQ7: 740000 | IR7: 100000 | IS7: =SUM(HN7:IR7) | IT7: 1370750 | IU7: 2598808 | IV7: 280000 | IW7: 1728964 | IX7: 2065142 | IY7: 618807 | IZ7: 30000 | JA7: 2619750 | JB7: 304700 | JC7: 200000 | JD7: 70000 | JE7: 394450 | JF7: 3379965 | JG7: 314000 | JH7: 400000 | JJ7: 2287842 | JK7: 250000 | JL7: 539900 | JO7: 3443300 | JP7: 274450 | JQ7: 138000 | JR7: 444000 | JS7: 784362 | JV7: 1050000 | JW7: 294400 | JX7: =SUM(IT7:JW7) | JY7: 284720 | JZ7: 1495000 | KA7: 1295306 | KB7: 45000 | KC7: 50000 | KD7: 429969 | KE7: 655662 | KF7: 0 | KG7: 787344 | KH7: 295991 | KI7: 244500 | KJ7: 0 | KK7: 5797650 | KL7: 86050 | KM7: 714807 | KN7: 408769 | KO7: 322740 | KP7: 11000 | KR7: 951357 | KS7: 39120 | KT7: 1583170 | KU7: 900184 | KV7: 416970 | KW7: 600000 | KX7: 65120 | KY7: 298240 | KZ7: 643266 | LA7: 914539 | LB7: 505000 | LC7: 444350 | LD7: =SUM(JY7:LC7) | LE7: 1045950 | LF7: 203700 | LG7: 753064 | LH7: 1217460 | LI7: 281620 | LJ7: 38800 | LK7: 556750 | LL7: 541392 | LM7: 38800 | LN7: 160050 | LO7: 742853 | LP7: 792050 | LQ7: 244997 | LR7: 77600 | LS7: 581750 | LU7: 567262 | LV7: 767864 | LW7: 38800 | LX7: 631125 | LY7: 660820 | LZ7: 138800 | MA7: 90000 | MD7: 578862 | ME7: 40000 | MF7: 454500 | MG7: 66500 | MH7: 665660 | MI7: =SUM(LD7:MH7) | MJ7: 720950 | MK7: 533550 | ML7: 92900 | MN7: 370450 | MO7: 40000 | MP7: 626682 | MQ7: 290950 | MR7: 310000 | MS7: 273430 | MT7: 478000 | MU7: 40000 | MV7: 559000 | MW7: 126000 | MX7: 110000 | MY7: 330950 | MZ7: 90000 | NA7: 360725 | NB7: 742262 | ND7: 440000 | NE7: 493750 | NF7: 40000 | NH7: 20000 | NI7: 531502 | NJ7: 400000 | NL7: 299842 | NM7: 20000 | NN7: 322338 | NO7: =SUM(MJ7:NN7) | NQ7: 686000 | NR7: 190000 | NS7: 65000 | NU7: 340042 | NV7: 373250 | NW7: 970416 | NX7: 537026 | NZ7: 209708 | OA7: 330000 | OB7: 412362 | OC7: 106000 | OD7: 30000 | OE7: 260000 | OF7: 100000 | OG7: 412322 | OI7: 528576 | OJ7: 343638 | OK7: 480000 | OL7: 361283 | ON7: 40000 | OO7: 1327250 | OP7: 78473 | OQ7: 806597 | OR7: 210000 | OS7: 100000 | OT7: 3633399 | OU7: =SUM(NP7:OT7) | OW7: 2543563 | OX7: 247490 | OY7: 158000 | OZ7: 518499 | PA7: 1500118 | PB7: =1187250+295000 | PC7: 629880 | PD7: 822399 | PE7: 522900 | PF7: 899840 | PG7: 1124754 | PH7: 654980 | PI7: 80000 | PJ7: 40000 | PK7: 926765 | PL7: 1141526 | PM7: 40000 | PN7: 1485700 | PO7: 1206446 | PP7: 475450 | PQ7: 400000 | PR7: 300000 | PS7: 401195 | PT7: 450000 | PU7: 120000 | PV7: 533278 | PW7: 1995975 | PX7: 60000 | PY7: 1304631 | PZ7: =SUM(OV7:PY7) | QA7: 410000 | QB7: 715450 | QC7: 449960 | QD7: 1932110 | QE7: 460000 | QF7: 60000 | QG7: 725450 | QH7: 90000 | QI7: 433373 | QJ7: 537920 | QK7: 436000 | QL7: 1530677 | QM7: 1052887 | QN7: 2567539 | QO7: 110000 | QP7: 2186686 | QQ7: 569237 | QR7: 1416890 | QS7: 989800 | QT7: 841812 | QU7: 239148 | QV7: 363000 | QW7: 231980 | QX7: 4751544 | QY7: 684049 | QZ7: 835000 | RA7: 308346 | RB7: 1244769 | RC7: 1543000 | RD7: 528346 | RE7: 859703 | RF7: =SUM(QA7:RE7) | RG7: 140000 | RH7: 110000 | RI7: 462945 | RJ7: 3063297 | RK7: 165000 | RL7: 256980 | RM7: 854148 | RN7: 566843 | RO7: 794295 | RP7: 351380 | RQ7: 1224500 | RR7: 835300 | RS7: 754395 | RT7: 1716390 | RU7: 1095020 | RV7: 1842967 | RW7: 1287365 | RX7: 645860 | RY7: 501228 | RZ7: 590000 | SA7: 956660 | SB7: 197800 | SC7: 194100 | SD7: 372670 | SE7: 457600 | SF7: 1062779 | SG7: 338000 | SH7: 1980900 | SJ7: 374764 | SK7: =SUM(RG7:SJ7) | SL7: 827000 | SM7: 2147199 | SN7: 417568 | SO7: 1968000 | SP7: 250000 | SQ7: 60000 | SR7: 907600 | SS7: 518950 | ST7: 1888000 | SU7: 60000 | SV7: 368510 | SW7: 956000 | SX7: 409984 | SY7: 729050 | SZ7: 1108900 | TA7: 2410440 | TB7: 200000 | TC7: 326500 | TD7: 1186910 | TE7: 60000 | TF7: 717000 | TG7: 558400 | TH7: 760000 | TI7: 777940 | TL7: 160000 | TM7: 199900 | TN7: 304500 | TO7: 80000 | TP7: 0 | TQ7: =SUM(SL7:TP7) | TR7: 468950 | TS7: 60000 | TT7: 300000 | TU7: 40000 | TV7: 775950 | TW7: 523400 | TX7: 954000 | TY7: 1832950 | TZ7: 150000 | UA7: 187200 | UB7: 90000 | UC7: 618520 | UD7: 2267950 | UE7: 568950 | UF7: 100000 | UG7: 537970 | UH7: 680430 | UI7: 175000 | UJ7: 328950 | UK7: 80000 | UL7: 1110000 | UM7: 801773 | UN7: 517400 | UO7: 595000 | UP7: 950000 | UQ7: 700000 | UR7: 2192720 | US7: 810000 | UT7: 40000 | UU7: 1153302 | UV7: 60000 | UW7: =SUM(TR7:UV7) | UX7: 868950 | UY7: 569978 | UZ7: 2949203 | VA7: 449435 | VB7: 813840 | VC7: 195000 | VD7: 1411762 | VE7: 1353000 | VF7: 830063 | VG7: 860445 | VH7: 3250110 | VI7: 350120 | VJ7: 774344 | VK7: 451060 | VL7: 455000 | VM7: 777000 | VN7: 350000 | VO7: 269445 | VP7: 1776000 | VQ7: 368010 | VR7: 550000 | VS7: 765000 | VT7: 795700 | VU7: 27060 | VV7: 2875605 | VW7: 125000 | VX7: 2170000 | VY7: 70000 | VZ7: =SUM(UX7:VY7) | WA7: 632000 | WB7: 960250 | WC7: 3445412 | WD7: 1287292 | WE7: 1135960 | WF7: 127000 | WG7: 755492 | WH7: 2182000 | WI7: 617778 | WJ7: 1300000 | WK7: 2208460 | WL7: 557500 | WM7: 1542883 | WN7: 1628000 | WO7: 967000 | WP7: 801650 | WQ7: 1458700 | WR7: 90000 | WS7: 931970 | WT7: 110000 | WU7: 2466570 | WV7: 355000 | WW7: 1188248 | WX7: 1045000 | XB7: 250000 | XF7: =SUM(WA7:XE7) | XG7: 0 | XH7: 0 | XI7: 0 | XL7: 0 | XN7: 0 | XR7: 0 | XS7: 0 | XT7: 0 | XU7: 0 | XV7: 56000 | XW7: 200000 | XX7: 300000 | XY7: 255750 | XZ7: 465000 | YA7: 190000 | YB7: 490972 | YC7: 558422 | YD7: 398245 | YE7: 383000 | YF7: 40000 | YH7: 479000 | YJ7: 566000 | YK7: =SUM(XG7:YJ7) | YL7: 1935000 | YM7: 326555 | YN7: 200000 | YO7: 1177000 | YP7: 1541000 | YQ7: 792412 | YR7: 1301060 | YS7: 0 | YT7: 1495000 | YU7: 1037200 | YV7: 645200 | YW7: 1530988 | YY7: 30000 | ZA7: 922500 | ZB7: 310000 | ZC7: 915000 | ZD7: 923614 | ZE7: 333900 | ZF7: 1053000 | ZG7: 0 | ZI7: 1162900 | ZK7: 100000 | ZL7: 60000 | ZM7: 250000 | ZN7: 830096 | ZO7: 941268 | ZQ7: =SUM(YM7:ZP7) | ZR7: 3040750 | ZS7: 930000 | ZT7: 426057 | ZU7: 265000 | ZV7: 1079760 | ZW7: 80000 | ZX7: 420850 | ZY7: 70000 | ZZ7: 670000 | AAA7: 4301250 | AAB7: 2526714 | AAC7: 293000 | AAD7: 367564 | AAE7: 360000 | AAF7: 1025000 | AAG7: 80000 | AAH7: 200000 | AAI7: 400000 | AAJ7: 1410400 | AAK7: 1265900 | AAL7: 1804000 | AAM7: 406117 | AAN7: 287000 | AAO7: 250000 | AAP7: 110000 | AAS7: 873000 | AAV7: =SUM(ZR7:AAU7) | AAW7: 68000 | AAX7: 160000 | AAY7: 867800 | ABA7: 2025877 | ABB7: 543005 | ABD7: 300000 | ABE7: 423661 | ABG7: 772000 | ABH7: 1333000 | ABI7: 140000 | ABJ7: 0 | ABK7: 309051 | ABN7: 571402 | ABO7: 1270977 | ABP7: 159000 | ABQ7: 20000 | ABR7: 72700 | ABS7: 672904 | ABU7: 379000 | ABV7: 1152500 | ABZ7: 111427 | ACB7: =SUM(AAX7:ACA7) | ACC7: 314450 | ACD7: 1046800 | ACE7: 100000 | ACF7: 872000 | ACG7: 534740 | ACH7: 200000 | ACI7: 698760 | ACJ7: 275593 | ACK7: 485000 | ACM7: 921510 | ACN7: 500000 | ACO7: 818450 | ACP7: 368750 | ACQ7: 70000 | ACR7: 837000 | ACS7: 1219068 | ACT7: 533281 | ACU7: 120000 | ACW7: 323760 | ACX7: 443548 | ACY7: 837000 | ADA7: 672000 | ADB7: 200000 | ADC7: 395129 | ADF7: 553500 | ADG7: 784724 | ADH7: =SUM(ACC7:ADG7) | ADI7: 901989 | ADJ7: 343000 | ADK7: 348750 | ADL7: 100000 | ADM7: 450760 | ADN7: 1010615 | ADO7: 562500 | ADP7: 801493 | ADQ7: 352558 | ADR7: 395250 | ADS7: 170000 | ADT7: 253961 | ADU7: 838000 | ADV7: 668000 | ADW7: 859500 | ADY7: 150000 | ADZ7: 481824 | AEB7: 232500 | AEC7: 245300 | AED7: 566328 | AEE7: 311298 | AEF7: 50000 | AEG7: 645000 | AEH7: 93000 | AEI7: 8000 | AEK7: 150000 | AEL7: 255750 | AEM7: =SUM(ADI7:AEL7) | AEN7: 789945 | AEO7: 160000 | AEP7: 0 | AEQ7: 0 | AER7: 593938 | AES7: 308750 | AEU7: 724500 | AEV7: 255750 | AEW7: 866867 | AEZ7: 616000 | AFB7: 439480 | AFC7: 250000 | AFE7: 372000 | AFI7: 139500 | AFJ7: 93000 | AFK7: 180000 | AFL7: 150000 | AFN7: 139500 | AFQ7: 121000 | AFR7: 8000 | AFS7: =SUM(AEN7:AFR7) | AFT7: 693998 | AFU7: 50000 | AFW7: 255750 | AFX7: 150000 | AFY7: 250000 | AFZ7: 255750 | AGB7: 359199 | AGE7: 100000 | AGF7: 150000 | AGG7: 150000 | AGH7: 151538 | AGI7: 1349348 | AGJ7: 200000 | AGK7: 500000 | AGL7: 211025 | AGN7: 260000 | AGO7: 702234 | AGP7: 406990 | AGQ7: 150917 | AGU7: 30000 | AGV7: 201000 | AGW7: 50000 | AGX7: =SUM(AFT7:AGW7) | AGZ7: 634000 | AHA7: 220033 | AHB7: 445404 | AHC7: 672395 | AHE7: 847120 | AHH7: 250000 | AHJ7: 128478 | AHK7: 180000 | AHL7: 413010 | AHM7: 100000 | AHO7: 270109 | AHP7: 220000 | AHQ7: 114725 | AHS7: 100000 | AHX7: 100000 | AHY7: 140000 | AHZ7: 226565 | AIB7: 202000 | AID7: =SUM(AGY7:AIC7) | AIF7: 155646 | AIH7: 364049 | AII7: 548000 | AIK7: 1482666 | AIL7: 835000 | AIM7: 157774 | AIN7: 1666150 | AIO7: 70000 | AIP7: 1000100 | AIW7: 400000 | AIX7: 150000 | AIY7: 444147 | AIZ7: 199980 | AJB7: 16000 | AJE7: 84000 | AJF7: 1639650 | AJH7: 375969 | AJI7: 191458 | AJJ7: =SUM(AIE7:AJI7) | AJL7: 541930 | AJM7: 1024171 | AJN7: 252945 | AJO7: 99900 | AJQ7: 310000 | AJR7: 1305485 | AJS7: 229950 | AJT7: 99980 | AJV7: 200000 | AJW7: 280000 | AJY7: 50000 | AJZ7: 326953 | AKA7: 60033 | AKB7: 99980 | AKD7: 1096068 | AKE7: 196571 | AKF7: 100000 | AKH7: 99980 | AKI7: 515925 | AKJ7: 24000 | AKK7: 530000 | AKL7: 600000 | AKM7: =SUM(AJK7:AKL7) | AKN7: 501971 | AKO7: 298868 | AKP7: 727755 | AKQ7: 219200 | AKR7: 196154 | AKS7: 549000 | AKT7: 2408704 | AKU7: 150000 | AKV7: 1441074 | AKW7: 442205 | AKX7: 499103 | AKY7: 50000 | ALC7: 343747 | ALD7: 331994 | ALE7: 50000 | ALG7: 255000 | ALH7: 10000 | ALK7: 160000 | ALL7: 60000 | ALM7: 50000 | ALN7: 403000 | ALO7: 155000 | ALP7: 557005 | ALQ7: 782000 | ALR7: 554905 | ALS7: =SUM(AKN7:ALR7) | ALT7: 342000 | ALU7: 50000 | ALW7: 81768 | ALX7: 0 | ALY7: 277748 | ALZ7: 501000 | AMA7: 1221278 | AMB7: 1224362 | AMC7: 350000 | AMD7: 550000 | AME7: 389188 | AMF7: 1158740 | AMG7: 105000 | AMH7: 678891 | AMI7: 320050 | AMJ7: 400000 | AMK7: 90000 | AML7: 160000 | AMM7: 296945 | AMO7: 66000 | AMQ7: 290000 | AMS7: 500000 | AMT7: 200000 | AMU7: 183000 | AMW7: 100000 | AMX7: =SUM(ALT7:AMW7) | AMY7: 368818 | AMZ7: 1150879 | ANA7: 235027 | ANB7: 723136 | ANC7: 270000 | AND7: 1378020 | ANE7: 763990 | ANF7: 100000 | ANG7: 260000 | ANH7: 973830 | ANI7: 1232310 | ANJ7: 40000 | ANK7: 50000 | ANL7: 369828 | ANM7: 180000 | ANO7: 129000 | ANQ7: 957000 | ANR7: 722207 | ANS7: 0 | ANT7: 632647 | ANU7: 135000 | ANV7: 180000 | ANW7: 516000 | ANX7: 247000 | ANY7: 868022 | AOB7: 100161 | AOC7: 604200 | AOD7: 604200
A8: RUBIS APP | B8: 0 | C8: 30000 | D8: 0 | I8: 50000 | R8: 62000 | U8: 0 | W8: 90000 | X8: 0 | AG8: =SUM(B8:AF8) | AM8: 200000 | BL8: =SUM(AH8:BK8) | CM8: 130000 | CR8: =SUM(BM8:CQ8) | CY8: 100000 | DA8: 205000 | DK8: 280000 | DM8: 302000 | DO8: 126000 | DW8: =SUM(CS8:DV8) | FB8: 0 | HE8: 24000 | HF8: 310000 | HG8: 0 | HI8: 312000 | HL8: 384000 | HM8: =SUM(GJ8:HL8) | HN8: 0 | HO8: 0 | HP8: 0 | HS8: 312000 | HY8: 0 | HZ8: 312000 | IE8: 385000 | IL8: 312000 | IQ8: 382000 | IS8: =SUM(HN8:IR8) | IU8: 313000 | IY8: 312000 | JD8: 318000 | JE8: 0 | JH8: 384000 | JL8: 312000 | JO8: 312000 | JR8: 383000 | JV8: 313000 | JX8: =SUM(IT8:JW8) | KA8: 312000 | KB8: 0 | KE8: 383000 | KF8: 0 | KL8: 312000 | KO8: 382000 | KR8: 312000 | KU8: 17000 | KV8: 382000 | KY8: 307000 | KZ8: 20000 | LB8: 332200 | LD8: =SUM(JY8:LC8) | MB8: 40000 | MI8: =SUM(LD8:MH8) | NO8: =SUM(MJ8:NN8) | OU8: =SUM(NP8:OT8) | PZ8: =SUM(OV8:PY8) | SK8: =SUM(RG8:SJ8) | TQ8: =SUM(SL8:TP8) | WV8: 170000 | XF8: =SUM(WA8:XE8) | XK8: 6000 | XL8: 779000 | XN8: 680000 | XO8: 669000 | XQ8: 240000 | XR8: 0 | XS8: 0 | XT8: 0 | XU8: 0 | YK8: =SUM(XG8:YJ8) | YN8: =510000+900000 | YZ8: 400000 | ZQ8: =SUM(YM8:ZP8) | AAV8: =SUM(ZR8:AAU8) | AAW8: 0 | ACB8: =SUM(AAX8:ACA8) | AEM8: =SUM(ADI8:AEL8) | AFS8: =SUM(AEN8:AFR8) | AGX8: =SUM(AFT8:AGW8) | AID8: =SUM(AGZ8:AIC8) | AJJ8: =SUM(AIF8:AJI8) | AKM8: =SUM(AJI8:AKL8) | ALS8: =SUM(AKO8:ALR8) | AMX8: =SUM(ALT8:AMW8)
BU12: 10000 | BV12: 5290 | BW12: =BU12*BV12
BU13: 5000 | BV13: 4850 | BW13: =BU13*BV13
AHP14: 2
ADP15: 12904 | ADQ15: 4936 | AIJ15: UIU university
ADP16: 132 | ADQ16: 7968
ADP17: =ADP15-ADP16 | ADQ17: =SUM(ADQ15:ADQ16)
ADQ18: 132
ADQ19: =ADQ17-ADQ18
ADQ20: 12800
ADQ21: =ADQ20-ADQ19

Sheet EXPENSES
A2: ITEMS | B2: PARTICULARS | C2: 44204 | D2: 44965 | E2: 44993 | F2: 45024 | G2: 45054 | H2: 45085 | I2: 45115 | J2: 45146 | K2: 45177 | L2: 45207 | M2: 45238 | N2: 45268 | O2: 13/8/23 | P2: 14/8/23 | Q2: 15/8/23 | R2: 16/8/23 | S2: 17/8/23 | T2: 18/8/23 | U2: 19/8/23 | V2: 20/8/23 | W2: 21/8/23 | X2: 22/8/23 | Y2: 23/8/23 | Z2: 24/8/23 | AA2: 25/8/23 | AB2: 26/8/23 | AC2: 27/8/23 | AD2: 28/8/23 | AE2: 29/8/23 | AF2: 30/8/23 | AG2: 31/8/23 | AH2: MONTHLY TOTAL | AI2: 45170 | AJ2: =AI2+1 | AK2: =AJ2+1 | AL2: =AK2+1 | AM2: =AL2+1 | AN2: =AM2+1 | AO2: =AN2+1 | AP2: =AO2+1 | AQ2: =AP2+1 | ... BL2: =BK2+1 | BM2: Monthly Total | BN2: =AI2+30 | BO2: =AJ2+30 | BP2: =AK2+30 | BQ2: =AL2+30 | BR2: =AM2+30 | BS2: =AN2+30 | BT2: =AO2+30 | BU2: =AP2+30 | ... CQ2: =BL2+30 | CR2: =BN2+30 | CS2: Monthly Total | CT2: =BO2+30 | CU2: =BP2+30 | CV2: =BQ2+30 | CW2: =BR2+30 | CX2: =BS2+30 | CY2: =BT2+30 | CZ2: =BU2+30 | DA2: =BV2+30 | ... DW2: =CR2+30 | DX2: MONTHLY TOTAL | DY2: 45261 | DZ2: =DY2+1 | EA2: =DZ2+1 | EB2: =EA2+1 | EC2: =EB2+1 | ED2: =EC2+1 | EE2: =ED2+1 | EF2: =EE2+1 | EG2: =EF2+1 | ... FC2: =FB2+1 | FD2: MONTHLY TOTAL | FE2: =FC2+1 | FF2: =FE2+1 | FG2: =FF2+1 | FH2: =FG2+1 | FI2: =FH2+1 | FJ2: =FI2+1 | FK2: =FJ2+1 | FL2: =FK2+1 | FM2: =FL2+1 | ... GI2: =GH2+1 | GJ2: MONTHLY TOTAL | GK2: =GI2+1 | GL2: =GK2+1 | GM2: =GL2+1 | GN2: =GM2+1 | GO2: =GN2+1 | GP2: =GO2+1 | GQ2: =GP2+1 | GR2: =GQ2+1 | GS2: =GR2+1 | ... HM2: =HL2+1 | HN2: MONTHLY TOTAL | HO2: 45352 | HP2: =HO2+1 | HQ2: =HP2+1 | HR2: =HQ2+1 | HS2: =HR2+1 | HT2: =HS2+1 | HU2: =HT2+1 | HV2: =HU2+1 | HW2: =HV2+1 | ... IS2: =IR2+1 | IT2: monthly total | IU2: 45383 | IV2: =IU2+1 | IW2: =IV2+1 | IX2: =IW2+1 | IY2: =IX2+1 | IZ2: =IY2+1 | JA2: =IZ2+1 | JB2: =JA2+1 | JC2: =JB2+1 | ... JX2: =JW2+1 | JY2: monthly total | JZ2: 45413 | KA2: =JZ2+1 | KB2: =KA2+1 | KC2: =KB2+1 | KD2: =KC2+1 | KE2: =KD2+1 | KF2: =KE2+1 | KG2: =KF2+1 | KH2: =KG2+1 | ... LD2: =LC2+1 | LE2: monthly total | LF2: 1st - june | LG2: 2nd - june | LH2: 3rd - june | LI2: 4th - june | LJ2: 5th - june | LK2: 6th - june | LL2: 7th - june | LM2: 8th - june | LN2: 9th - june | LO2: 10th - june | LP2: 11th - june | LQ2: 12th - june | LR2: 13th - june | LS2: 14th - june | LT2: 15th - june | LU2: 16th - june | LV2: 17th - june | LW2: 18th - june | LX2: 19th - june | LY2: 20th - june | LZ2: 21st - june | MA2: 22nd - june | MB2: 23rd - june | MC2: 24th - june | MD2: 25th - june | ME2: 26th - june | MF2: 27th - june | MG2: 28th - june | MH2: 29th - june | MI2: 30th - june | MJ2: monthly total | MK2: 1st July | ML2: 2nd July | MM2: 3rd July | MN2: 4th July | MO2: 5th July | MP2: 6th July | MQ2: 7th July | MR2: 8th July | MS2: 9th July | MT2: 10th July | MU2: 11th July | MV2: 12th July | MW2: 13th July | MX2: 14th July | MY2: 15th July | MZ2: 16th July | NA2: 17th July | NB2: 18th July | NC2: 19th July | ND2: 20th July | NE2: 21st July | NF2: 22nd July | NG2: 23rd July | NH2: 24th July | NI2: 25th July | NJ2: 26th July | NK2: 27th July | NL2: 28th July | NM2: 29th July | NN2: 30th July | NO2: 31st July | NP2: monthly total | NQ2: 1st aug | NR2: 2nd aug | NS2: 3rd aug | NT2: 4th aug | NU2: 5th aug | NV2: 6th aug | NW2: 7th aug | NX2: 8th aug | NY2: 9th aug | NZ2: 10th aug | OA2: 11th aug | OB2: 12th aug | OC2: 13th aug | OD2: 14th aug | OE2: 15th aug | OF2: 16th aug | OG2: 17th aug | OH2: 18th aug | OI2: 19th aug | OJ2: 20th aug | OK2: 21st aug | OL2: 22nd aug | OM2: 23rd aug | ON2: 24th aug | OO2: 25th aug | OP2: 26th aug | OQ2: 27th aug | OR2: 28th aug | OS2: 29th aug | OT2: 30th aug | OU2: 31st aug | OV2: monthly total | OW2: 1st sep | OX2: 2nd sep | OY2: 3rd sep | OZ2: 4th sep | PA2: 5th sep | PB2: 6th sep | PC2: 7th sep | PD2: 8th sep | PE2: 9th sep | PF2: 10th sep | PG2: 11th sep | PH2: 12th sep | PI2: 13th sep | PJ2: 14th sep | PK2: 15th sep | PL2: 16th sep | PM2: 17th sep | PN2: 18th sep | PO2: 19th sep | PP2: 20th sep | PQ2: 21st sep | PR2: 22nd sep | PS2: 23rd sep | PT2: 24th sep | PU2: 25th sep | PV2: 26th sep | PW2: 27th sep | PX2: 28th sep | PY2: 29th sep | PZ2: 30th sep | QA2: monthly total | QB2: 1st oct-24 | QC2: 2nd oct-24 | QD2: 3rd oct-24 | QE2: 4th oct-24 | QF2: 5th oct-24 | QG2: 6th oct-24 | QH2: 7th oct-24 | QI2: 8th oct-24 | QJ2: 9th oct-24 | QK2: 10th oct-24 | QL2: 11th oct-24 | QM2: 12th oct-24 | QN2: 13th oct-24 | QO2: 14th oct-24 | QP2: 15th oct-24 | QQ2: 16th oct-24 | QR2: 17th oct-24 | QS2: 18th oct-24 | QT2: 19th oct-24 | QU2: 20th oct-24 | QV2: 21st oct-24 | QW2: 22nd oct-24 | QX2: 23rd oct-24 | QY2: 24th oct-24 | QZ2: 25th oct-24 | RA2: 26th oct-24 | RB2: 27th oct-24 | RC2: 28th oct-24 | RD2: 29th oct-24 | RE2: 30th oct-24 | RF2: 31st oct-24 | RG2: monthly total | RH2: 1st nov-2024 | RI2: 2nd nov-2024 | RJ2: 3rd nov-2024 | RK2: 4th nov-2024 | RL2: 5th nov-2024 | RM2: 6th nov-2024 | RN2: 7th nov-2024 | RO2: 8th nov-2024 | RP2: 9th nov-2024 | RQ2: 10th nov-2024 | RR2: 11th nov-2024 | RS2: 12th nov-2024 | RT2: 13th nov-2024 | RU2: 14th nov-2024 | RV2: 15th nov-2024 | RW2: 16th nov-2024 | RX2: 17th nov-2024 | RY2: 18th nov-2024 | RZ2: 19th nov-2024 | SA2: 20th nov-2024 | SB2: 21st nov-2024 | SC2: 22nd nov-2024 | SD2: 23rd nov-2024 | SE2: 24th nov-2024 | SF2: 25th nov-2024 | SG2: 26th nov-2024 | SH2: 27th nov-2024 | SI2: 28th nov-2024 | SJ2: 29th nov-2024 | SK2: 30th nov-2024 | SL2: 31st nov-2024 | SM2: monthly total | SN2: 1st dec- 2024 | SO2: 2nd dec- 2024 | SP2: 3rd dec- 2024 | SQ2: 4th dec- 2024 | SR2: 5th dec- 2024 | SS2: 6th dec- 2024 | ST2: 7th dec- 2024 | SU2: 8th dec- 2024 | SV2: 9th dec- 2024 | SW2: 10th dec- 2024 | SX2: 11th dec- 2024 | SY2: 12th dec- 2024 | SZ2: 13th dec- 2024 | TA2: 14th dec- 2024 | TB2: 15th dec- 2024 | TC2: 16th dec- 2024 | TD2: 17th dec- 2024 | TE2: 18th dec- 2024 | TF2: 19th dec- 2024 | TG2: 20th dec- 2024 | TH2: 21st dec- 2024 | TI2: 22nd dec- 2024 | TJ2: 23rd dec- 2024 | TK2: 24th dec- 2024 | TL2: 25th dec- 2024 | TM2: 26th dec- 2024 | TN2: 27th dec- 2024 | TO2: 28th dec- 2024 | TP2: 29th dec- 2024 | TQ2: 30th dec- 2024 | TR2: 31st dec- 2024 | TS2: monthly total | TT2: 1st jan-2025 | TU2: 2nd jan-2025 | TV2: 3rd jan-2025 | TW2: 4th jan-2025 | TX2: 5th jan-2025 | TY2: 6th jan-2025 | TZ2: 7th jan-2025 | UA2: 8th jan-2025 | UB2: 9th jan-2025 | UC2: 10th jan-2025 | UD2: 11th jan-2025 | UE2: 12th jan-2025 | UF2: 13th jan-2025 | UG2: 14th jan-2025 | UH2: 15th jan-2025 | UI2: 16th jan-2025 | UJ2: 17th jan-2025 | UK2: 18th jan-2025 | UL2: 19th jan-2025 | UM2: 20th jan-2025 | UN2: 21st jan-2025 | UO2: 22nd jan-2025 | UP2: 23rd jan-2025 | UQ2: 24th jan-2025 | UR2: 25th jan-2025 | US2: 26th jan-2025 | UT2: 27th jan-2025 | UU2: 28th jan-2025 | UV2: 29th jan-2025 | UW2: 30th jan-2025 | UX2: 31st jan-2025 | UY2: monthly total | UZ2: 1st feb2025 | VA2: 2nd feb2025 | VB2: 3rd feb2025 | VC2: 4th feb2025 | VD2: 5th feb2025 | VE2: 6th feb2025 | VF2: 7th feb2025 | VG2: 8th feb2025 | VH2: 9th feb2025 | VI2: 10th feb2025 | VJ2: 11th feb2025 | VK2: 12th feb2025 | VL2: 13th feb2025 | VM2: 14th feb2025 | VN2: 15th feb2025 | VO2: 16th feb2025 | VP2: 17th feb2025 | VQ2: 18th feb2025 | VR2: 19th feb2025 | VS2: 20th feb2025 | VT2: 21st feb2025 | VU2: 22nd feb2025 | VV2: 23rd feb2025 | VW2: 24th feb2025 | VX2: 25th feb2025 | VY2: 26th feb2025 | VZ2: 27th feb2025 | WA2: 28th feb2025 | WB2: monthly total | WC2: 1st mar 2025 | WD2: 2nd mar 2025 | WE2: 3rd mar 2025 | WF2: 4th mar 2025 | WG2: 5th mar 2025 | WH2: 6th mar 2025 | WI2: 7th mar 2025 | WJ2: 8th mar 2025 | WK2: 9th mar 2025 | WL2: 10th mar 2025 | WM2: 11th mar 2025 | WN2: 12th mar 2025 | WO2: 13th mar 2025 | WP2: 14th mar 2025 | WQ2: 15th mar 2025 | WR2: 16th mar 2025 | WS2: 17th mar 2025 | WT2: 18th mar 2025 | WU2: 19th mar 2025 | WV2: 20th mar 2025 | WW2: 21st mar 2025 | WX2: 22nd mar 2025 | WY2: 23rd mar 2025 | WZ2: 24th mar 2025 | XA2: 25th mar 2025 | XB2: 26th mar 2025 | XC2: 27th mar 2025 | XD2: 28th mar 2025 | XE2: 29th mar 2025 | XF2: 30th mar 2025 | XG2: 31st mar 2025 | XH2: monthly total | XI2: 1st-apr2025 | XJ2: 2nd -apr2025 | XK2: 3rd -apr2025 | XL2: 4th -apr2025 | XM2: 5th -apr2025 | XN2: 6th -apr2025 | XO2: 7th -apr2025 | XP2: 8th -apr2025 | XQ2: 9th -apr2025 | XR2: 10th -apr2025 | XS2: 11th -apr2025 | XT2: 12th -apr2025 | XU2: 13th -apr2025 | XV2: 14th -apr2025 | XW2: 15th -apr2025 | XX2: 16th -apr2025 | XY2: 17th -apr2025 | XZ2: 18th -apr2025 | YA2: 19th -apr2025 | YB2: 20th -apr2025 | YC2: 21st -apr2025 | YD2: 22nd -apr2025 | YE2: 23rd -apr2025 | YF2: 24th -apr2025 | YG2: 25th -apr2025 | YH2: 26th -apr2025 | YI2: 27th -apr2025 | YJ2: 28th -apr2025 | YK2: 29th -apr2025 | YL2: 30th -apr2025 | YM2: monthly total | YN2: 1st May-2025 | YO2: 2nd May-2025 | YP2: 3rd May-2025 | YQ2: 4th May-2025 | YR2: 5th May-2025 | YS2: 6th May-2025 | YT2: 7th May-2025 | YU2: 8th May-2025 | YV2: 9th May-2025 | YW2: 10th May-2025 | YX2: 11th May-2025 | YY2: 12th May-2025 | YZ2: 13th May-2025 | ZA2: 14th May-2025 | ZB2: 15th May-2025 | ZC2: 16th May-2025 | ZD2: 17th May-2025 | ZE2: 18th May-2025 | ZF2: 19th May-2025 | ZG2: 20th May-2025 | ZH2: 21st May-2025 | ZI2: 22nd May-2025 | ZJ2: 23rd May-2025 | ZK2: 24th May-2025 | ZL2: 25th May-2025 | ZM2: 26th May-2025 | ZN2: 27th May-2025 | ZO2: 28th May-2025 | ZP2: 29th May-2025 | ZQ2: 30th May-2025 | ZR2: 31st May-2025 | ZS2: monthly total | ZT2: 1st june | ZU2: 2nd june | ZV2: 3rd june | ZW2: 4th june | ZX2: 5th june | ZY2: 6th june | ZZ2: 7th june | AAA2: 8th june | AAB2: 9th june | AAC2: 10th june | AAD2: 11th june | AAE2: 12th june | AAF2: 13th june | AAG2: 14th june | AAH2: 15th june | AAI2: 16th june | AAJ2: 17th june | AAK2: 18th june | AAL2: 19th june | AAM2: 20th june | AAN2: 21st june | AAO2: 22nd june | AAP2: 23rd june | AAQ2: 24th june | AAR2: 25th june | AAS2: 26th june | AAT2: 27th june | AAU2: 28th june | AAV2: 29th june | AAW2: 30th june | AAX2: monthly total | AAY2: 1st july | AAZ2: 2nd july | ABA2: 3rd july | ABB2: 4th july | ABC2: 5th july | ABD2: 6th july | ABE2: 7th july | ABF2: 8th july | ABG2: 9th july | ABH2: 10th july | ABI2: 11th july | ABJ2: 12th july | ABK2: 13th july | ABL2: 14th july | ABM2: 15th july | ABN2: 16th july | ABO2: 17th july | ABP2: 18th july | ABQ2: 19th july | ABR2: 20th july | ABS2: 21st july | ABT2: 22nd july | ABU2: 23rd july | ABV2: 24th july | ABW2: 25th july | ABX2: 26th july | ABY2: 27th july | ABZ2: 28th july | ACA2: 29th july | ACB2: 30th july | ACC2: 31st july | ACD2: monthly total | ACE2: 1st aug | ACF2: 2nd aug | ACG2: 3rd aug | ACH2: 4th aug | ACI2: 5th aug | ACJ2: 6th aug | ACK2: 7th aug | ACL2: 8th aug | ACM2: 9th aug | ACN2: 10th aug | ACO2: 11th aug | ACP2: 12th aug | ACQ2: 13th aug | ACR2: 14th aug | ACS2: 15th aug | ACT2: 16th aug | ACU2: 17th aug | ACV2: 18th aug | ACW2: 19th aug | ACX2: 20th aug | ACY2: 21st aug | ACZ2: 22nd aug | ADA2: 23rd aug | ADB2: 24th aug | ADC2: 25th aug | ADD2: 26th aug | ADE2: 27th aug | ADF2: 28th aug | ADG2: 29th aug | ADH2: 30th aug | ADI2: 31st aug | ADJ2: monthly total | ADK2: 1st -sep25 | ADL2: 2nd -sep25 | ADM2: 3rd -sep25 | ADN2: 4th -sep25 | ADO2: 5th -sep25 | ADP2: 6th -sep25 | ADQ2: 7th -sep25 | ADR2: 8th -sep25 | ADS2: 9th -sep25 | ADT2: 10th -sep25 | ADU2: 11th -sep25 | ADV2: 12th -sep25 | ADW2: 13th -sep25 | ADX2: 14th -sep25 | ADY2: 15th -sep25 | ADZ2: 16th -sep25 | AEA2: 17th -sep25 | AEB2: 18th -sep25 | AEC2: 19th -sep25 | AED2: 20th -sep25 | AEE2: 21st -sep25 | AEF2: 22nd -sep25 | AEG2: 23rd -sep25 | AEH2: 24th -sep25 | AEI2: 25th -sep25 | AEJ2: 26th -sep25 | AEK2: 27th -sep25 | AEL2: 28th -sep25 | AEM2: 29th -sep25 | AEN2: 30th -sep25 | AEO2: monthly total | AEP2: 1st -oct25 | AEQ2: 2nd -oct25 | AER2: 3rd -oct25 | AES2: 4th -oct25 | AET2: 5th -oct25 | AEU2: 6th -oct25 | AEV2: 7th -oct25 | AEW2: 8th -oct25 | AEX2: 9th -oct25 | AEY2: 10th -oct25 | AEZ2: 11th -oct25 | AFA2: 12th -oct25 | AFB2: 13th -oct25 | AFC2: 14th -oct25 | AFD2: 15th -oct25 | AFE2: 16th -oct25 | AFF2: 17th -oct25 | AFG2: 18th -oct25 | AFH2: 19th -oct25 | AFI2: 20th -oct25 | AFJ2: 21st -oct25 | AFK2: 22nd -oct25 | AFL2: 23rd -oct25 | AFM2: 24th -oct25 | AFN2: 25th -oct25 | AFO2: 26th -oct25 | AFP2: 27th -oct25 | AFQ2: 28th -oct25 | AFR2: 29th -oct25 | AFS2: 30th -oct25 | AFT2: 31st -oct25 | AFU2: monthly total | AFV2: 1st -nov25 | AFW2: 2nd -nov25 | AFX2: 3rd -nov25 | AFY2: 4th -nov25 | AFZ2: 5th -nov25 | AGA2: 6th -nov25 | AGB2: 7th -nov25 | AGC2: 8th -nov25 | AGD2: 9th -nov25 | AGE2: 10th -nov25 | AGF2: 11th -nov25 | AGG2: 12th -nov25 | AGH2: 13th -nov25 | AGI2: 14th -nov25 | AGJ2: 15th -nov25 | AGK2: 16th -nov25 | AGL2: 17th -nov25 | AGM2: 18th -nov25 | AGN2: 19th -nov25 | AGO2: 20th -nov25 | AGP2: 21st -nov25 | AGQ2: 22nd -nov25 | AGR2: 23rd -nov25 | AGS2: 24th -nov25 | AGT2: 25th -nov25 | AGU2: 26th -nov25 | AGV2: 27th -nov25 | AGW2: 28th -nov25 | AGX2: 29th -nov25 | AGY2: 30th -nov25 | AGZ2: Total | AHA2: 1st -dce25 | AHB2: 2nd -dce25 | AHC2: 3rd -dce25 | AHD2: 4th -dce25 | AHE2: 5th -dce25 | AHF2: 6th -dce25 | AHG2: 7th -dce25 | AHH2: 8th -dce25 | AHI2: 9th -dce25 | AHJ2: 10th -dce25 | AHK2: 11th -dce25 | AHL2: 12th -dce25 | AHM2: 13th -dce25 | AHN2: 14th -dce25 | AHO2: 15th -dce25 | AHP2: 16th -dce25 | AHQ2: 17th -dce25 | AHR2: 18th -dce25 | AHS2: 19th -dce25 | AHT2: 20th -dce25 | AHU2: 21st -dce25 | AHV2: 22nd -dce25 | AHW2: 23rd -dce25 | AHX2: 24th -dce25 | AHY2: 25th -dce25 | AHZ2: 26th -dce25 | AIA2: 27th -dce25 | AIB2: 28th -dce25 | AIC2: 29th -dce25 | AID2: 30th -dce25 | AIE2: 31st -dce25 | AIF2: total | AIG2: 1st -jan26 | AIH2: 2nd -jan26 | AII2: 3rd -jan26 | AIJ2: 4th -jan26 | AIK2: 5th -jan26 | AIL2: 6th -jan26 | AIM2: 7th -jan26 | AIN2: 8th -jan26 | AIO2: 9th -jan26 | AIP2: 10th -jan26 | AIQ2: 11th -jan26 | AIR2: 12th -jan26 | AIS2: 13th -jan26 | AIT2: 14th -jan26 | AIU2: 15th -jan26 | AIV2: 16th -jan26 | AIW2: 17th -jan26 | AIX2: 18th -jan26 | AIY2: 19th -jan26 | AIZ2: 20th -jan26 | AJA2: 21st -jan26 | AJB2: 22nd -jan26 | AJC2: 23rd -jan26 | AJD2: 24th -jan26 | AJE2: 25th -jan26 | AJF2: 26th -jan26 | AJG2: 27th -jan26 | AJH2: 28th -jan26 | AJI2: 29th -jan26 | AJJ2: 30th -jan26 | AJK2: 31st -jan26 | AJL2: total | AJM2: 1st -feb2026 | AJN2: 2nd -feb2026 | AJO2: 3rd -feb2026 | AJP2: 4th -feb2026 | AJQ2: 5th -feb2026 | AJR2: 6th -feb2026 | AJS2: 7th -feb2026 | AJT2: 8th -feb2026 | AJU2: 9th -feb2026 | AJV2: 10th -feb2026 | AJW2: 11th -feb2026 | AJX2: 12th -feb2026 | AJY2: 13th -feb2026 | AJZ2: 14th -feb2026 | AKA2: 15th -feb2026 | AKB2: 16th -feb2026 | AKC2: 17th -feb2026 | AKD2: 18th -feb2026 | AKE2: 19th -feb2026 | AKF2: 20th -feb2026 | AKG2: 21st -feb2026 | AKH2: 22nd -feb2026 | AKI2: 23rd -feb2026 | AKJ2: 24th -feb2026 | AKK2: 25th -feb2026 | AKL2: 26th -feb2026 | AKM2: 27th -feb2026 | AKN2: 28th -feb2026 | AKO2: total | AKP2: 1st -mar2026 | AKQ2: 2nd -mar2026 | AKR2: 3rd -mar2026 | AKS2: 4th -mar2026 | AKT2: 5th -mar2026 | AKU2: 6th -mar2026 | AKV2: 7th -mar2026 | AKW2: 8th -mar2026 | AKX2: 9th -mar2026 | AKY2: 10th -mar2026 | AKZ2: 11th -mar2026 | ALA2: 12th -mar2026 | ALB2: 13th -mar2026 | ALC2: 14th -mar2026 | ALD2: 15th -mar2026 | ALE2: 16th -mar2026 | ALF2: 17th -mar2026 | ALG2: 18th -mar2026 | ALH2: 19th -mar2026 | ALI2: 20th -mar2026 | ALJ2: 21st -mar2026 | ALK2: 22nd -mar2026 | ALL2: 23rd -mar2026 | ALM2: 24th -mar2026 | ALN2: 25th -mar2026 | ALO2: 26th -mar2026 | ALP2: 27th -mar2026 | ALQ2: 28th -mar2026 | ALR2: 29th -mar2026 | ALS2: 30th -mar2026 | ALT2: 31st -mar2026 | ALU2: total | ALV2: 1st -apr206 | ALW2: 2nd -apr206 | ALX2: 3rd -apr206 | ALY2: 4th -apr206 | ALZ2: 5th -apr206 | AMA2: 6th -apr206 | AMB2: 7th -apr206 | AMC2: 8th -apr206 | AMD2: 9th -apr206 | AME2: 10th -apr206 | AMF2: 11th -apr206 | AMG2: 12th -apr206 | AMH2: 13th -apr206 | AMI2: 14th -apr206 | AMJ2: 15th -apr206 | AMK2: 16th -apr206 | AML2: 17th -apr206 | AMM2: 18th -apr206 | AMN2: 19th -apr206 | AMO2: 20th -apr206 | AMP2: 21st -apr206 | AMQ2: 22nd -apr206 | AMR2: 23rd -apr206 | AMS2: 24th -apr206 | AMT2: 25th -apr206 | AMU2: 26th -apr206 | AMV2: 27th -apr206 | AMW2: 28th -apr206 | AMX2: 29th -apr206 | AMY2: 30th -apr206 | AMZ2: total | ANA2: 1st May2026 | ANB2: 2nd May2026 | ANC2: 3rd May2026 | AND2: 4th May2026 | ANE2: 5th May2026 | ANF2: 6th May2026 | ANG2: 7th May2026 | ANH2: 8th May2026 | ANI2: 9th May2026 | ANJ2: 10th May2026 | ANK2: 11th May2026 | ANL2: 12th May2026 | ANM2: 13th May2026 | ANN2: 14th May2026 | ANO2: 15th May2026 | ANP2: 16th May2026 | ANQ2: 17th May2026 | ANR2: 18th May2026 | ANS2: 19th May2026 | ANT2: 20th May2026 | ANU2: 21st May2026 | ANV2: 22nd May2026 | ANW2: 23rd May2026 | ANX2: 24th May2026 | ANY2: 25th May2026 | ANZ2: 26th May2026 | AOA2: 27th May2026 | AOB2: 28th May2026 | AOC2: 29th May2026 | AOD2: 30th May2026
A3: EXPENSES | B3: GARBAGE | C3: 20000 | F3: 0 | H3: 0 | K3: 0 | O3: 0 | T3: 0 | X3: 20000 | AH3: =SUM(C3:AG3) | BP3: 20000 | BS3: 20000 | CS3: =SUM(BN3:CR3) | CT3: 20000 | DX3: =SUM(CT3:DW3) | DZ3: 20000 | FD3: =SUM(DY3:FC3) | FE3: 20000 | GI3: 20000 | GJ3: =SUM(FE3:GI3) | HN3: =SUM(GK3:HM3) | HO3: 20000 | IS3: 20000 | IT3: =SUM(HO3:IS3) | JX3: 20000 | JY3: =SUM(IU3:JX3) | LE3: =SUM(KA3:LD3) | LF3: 20000 | MJ3: =SUM(LF3:MI3) | MK3: 20000 | NP3: =SUM(ML3:NO3) | NQ3: 0 | NR3: 20000 | OU3: 20000 | OV3: =SUM(NR3:OU3) | QA3: =SUM(OW3:PZ3) | QB3: 20000 | RG3: =SUM(QC3:RF3) | RI3: 20000 | SM3: =SUM(RI3:SL3) | SN3: 0 | SQ3: 20000 | TS3: =SUM(SO3:TR3) | TU3: 20000 | UY3: =SUM(TU3:UX3) | VB3: 20000 | WA3: 20000 | WB3: =SUM(UZ3:WA3) | XH3: =SUM(WF3:XG3) | XI3: 20000 | YL3: 20000 | YM3: =SUM(XK3:YL3) | ZR3: 20000 | ZS3: =SUM(YN3:ZR3) | AAX3: =SUM(ZT3:AAW3) | AAY3: 20000 | ACD3: =SUM(AAY3:ACC3) | ACF3: 20000 | ADJ3: =SUM(ACE3:ADI3) | ADK3: 20000 | AEO3: =SUM(ADK3:AEN3) | AER3: 20000 | AFU3: =SUM(AEP3:AFT3) | AFV3: 0 | AFW3: 20000 | AGZ3: =SUM(AFV3:AGY3) | AHA3: 20000 | AIE3: 0 | AIF3: =SUM(AHA3:AIE3) | AJL3: =SUM(AIG3:AJK3) | AJQ3: 20000 | AKO3: =SUM(AJM3:AKN3) | AKU3: 20000 | ALU3: =SUM(AKS3:ALT3) | AMA3: 30000 | AMZ3: =SUM(ALV3:AMY3) | ANB3: 30000
B4: LIQUID SOAP | C4: 0 | G4: 3000 | H4: 0 | O4: 0 | V4: 3000 | X4: 3000 | AC4: 3000 | AE4: 20000 | AH4: =SUM(C4:AG4) | AM4: 3000 | BF4: 4000 | BG4: 20000 | BM4: =SUM(AI4:BL4) | CG4: 4000 | CJ4: 20000 | CS4: =SUM(BN4:CR4) | DL4: 4000 | DM4: 20000 | DX4: =SUM(CT4:DW4) | ET4: 0 | EU4: 3000 | FD4: =SUM(DY4:FC4) | FP4: 4000 | FS4: 7000 | GJ4: =SUM(FE4:GI4) | GW4: 4000 | GX4: 2000 | HA4: 4000 | HE4: 20000 | HI4: 0 | HN4: =SUM(GK4:HM4) | IO4: 34500 | IT4: =SUM(HO4:IS4) | JY4: =SUM(IU4:JX4) | KD4: 3000 | KG4: 25000 | LE4: =SUM(KA4:LD4) | LL4: 29500 | MJ4: =SUM(LF4:MI4) | MU4: 25000 | NP4: =SUM(ML4:NO4) | OD4: 4000 | OE4: 25000 | OG4: 4000 | OV4: =SUM(NR4:OU4) | PD4: 25000 | QA4: =SUM(OW4:PZ4) | QC4: 25000 | RF4: 25000 | RG4: =SUM(QC4:RF4) | SG4: 4000 | SM4: =SUM(RI4:SL4) | TS4: =SUM(SO4:TR4) | UY4: =SUM(TU4:UX4) | VA4: 3000 | VB4: 25000 | VR4: 4500 | VY4: 4500 | VZ4: 30000 | WB4: =SUM(UZ4:WA4) | WX4: 1000 | XH4: =SUM(WF4:XG4) | XS4: 4000 | XV4: 25000 | YM4: =SUM(XK4:YL4) | YU4: 4000 | YY4: 4000 | ZS4: =SUM(YN4:ZR4) | ZT4: 4000 | ZV4: 4000 | ZY4: 4000 | AAC4: 4000 | AAT4: 4000 | AAW4: 4000 | AAX4: =SUM(ZT4:AAW4) | AAY4: 25000 | ABR4: 25000 | ACD4: =SUM(AAY4:ACC4) | ACL4: 25000 | ADJ4: =SUM(ACE4:ADI4) | ADL4: 4000 | ADR4: 4000 | AEO4: =SUM(ADK4:AEN4) | AEU4: 4000 | AFC4: 4000 | AFH4: 20000 | AFU4: =SUM(AEP4:AFT4) | AGD4: 3500 | AGH4: 4000 | AGQ4: 25000 | AGR4: 3500 | AGZ4: =SUM(AFV4:AGY4) | AHT4: 4000 | AIC4: 4000 | AIF4: =SUM(AHA4:AIE4) | AIK4: 4000 | AIM4: 25000 | AJL4: =SUM(AIG4:AJK4) | AJO4: 3500 | AJV4: 3500 | AKG4: 25000 | AKO4: =SUM(AJM4:AKN4) | ALU4: =SUM(AKS4:ALT4) | AMZ4: =SUM(ALV4:AMY4) | ANH4: 4000
B5: CAR FUEL | C5: 100000 | E5: 100016 | G5: 100000 | H5: 0 | I5: 100000 | P5: 100000 | S5: 200000 | Y5: 100000 | AA5: 100000 | AC5: 100000 | AE5: 100000 | AH5: =SUM(C5:AG5) | AI5: 200000 | AN5: 100000 | AS5: 200000 | AU5: 100000 | AX5: 200000 | AZ5: 100000 | BE5: 200000 | BK5: 200000 | BM5: =SUM(AI5:BL5) | BR5: 100000 | BX5: 200000 | CA5: 100000 | CE5: 200000 | CI5: 100000 | CL5: 100000 | CN5: 100000 | CR5: 100000 | CS5: =SUM(BN5:CR5) | CU5: 100000 | CV5: 30000 | CW5: 100000 | CY5: 100000 | CZ5: 100000 | DB5: 100000 | DD5: 100000 | DE5: 125000 | DF5: 95000 | DH5: 100000 | DJ5: 100000 | DN5: 100000 | DP5: 100000 | DT5: 100000 | DV5: 103500 | DX5: =SUM(CT5:DW5) | EA5: 100000 | EE5: 100000 | EG5: 100000 | EJ5: 100000 | EZ5: 100000 | FD5: =SUM(DY5:FC5) | FE5: 100000 | FF5: 0 | FI5: 200000 | FP5: 200000 | FU5: 400000 | FZ5: 200000 | GE5: 100000 | GH5: 100000 | GJ5: =SUM(FE5:GI5) | GK5: 200000 | GL5: 100000 | GM5: 100000 | GO5: 200000 | GR5: 300000 | GX5: 300000 | GZ5: 100000 | HC5: 200000 | HH5: 100000 | HJ5: 100000 | HL5: 100000 | HN5: =SUM(GK5:HM5) | HO5: 200000 | HT5: 200000 | HX5: 100000 | HZ5: 200000 | IB5: 100000 | ID5: =160000+40000 | IH5: 200000 | IO5: 200000 | IQ5: 100000 | IT5: =SUM(HO5:IS5) | IU5: 3000 | IW5: 200000 | IX5: 100000 | JA5: 2000 | JB5: 200000 | JC5: 200000 | JE5: 233582 | JI5: 200000 | JJ5: 200000 | JM5: 150000 | JP5: 300000 | JQ5: 100000 | JT5: 200000 | JU5: 100000 | JW5: 200000 | JX5: 100000 | JY5: =SUM(IU5:JX5) | KC5: 200000 | KF5: 300000 | KM5: 200000 | KR5: 200000 | KZ5: 200000 | LB5: 100000 | LE5: =SUM(KA5:LD5) | LF5: 100000 | LH5: 200000 | LM5: 200000 | LS5: 200000 | LU5: 100000 | LY5: 200000 | MB5: 100000 | ME5: 200000 | MJ5: =SUM(LF5:MI5) | NF5: 100000 | NJ5: 200000 | NO5: 100000 | NP5: =SUM(ML5:NO5) | NQ5: 0 | NR5: 103000 | NV5: 300000 | OD5: 250000 | OI5: 100000 | OL5: 200000 | OP5: 100000 | OR5: 100000 | OV5: =SUM(NR5:OU5) | OW5: 200000 | PA5: 200000 | PD5: 100000 | PG5: 100000 | PK5: 100000 | PL5: 105000 | PO5: 200000 | PU5: 100000 | PV5: 100000 | PZ5: 100000 | QA5: =SUM(OW5:PZ5) | QC5: 200000 | QJ5: 100000 | QL5: 100000 | QN5: 200000 | QQ5: 100000 | QR5: 100000 | QU5: 100000 | QV5: 200000 | RA5: 103000 | RE5: 100000 | RG5: =SUM(QC5:RF5) | RK5: 200000 | RP5: 200000 | RT5: 150000 | RV5: 100000 | RZ5: 100000 | SA5: 300000 | SF5: 100000 | SH5: 100000 | SI5: 100000 | SM5: =SUM(RI5:SL5) | SP5: 100000 | SR5: 100000 | SU5: 100000 | SW5: 100000 | SY5: 100000 | SZ5: 0 | TF5: 102000 | TI5: 100000 | TQ5: 100000 | TR5: 100000 | TS5: =SUM(SO5:TR5) | TY5: 100000 | UA5: 100000 | UC5: 0 | UD5: 100000 | UE5: 100000 | UH5: 100000 | UN5: 300000 | UP5: 102500 | UT5: 200000 | UW5: 100000 | UY5: =SUM(TU5:UX5) | VB5: 200000 | VC5: 5000 | VF5: 100000 | VJ5: 100000 | VM5: 100000 | VQ5: 50000 | VR5: 303000 | VS5: 100000 | VT5: 0 | VX5: 100000 | VZ5: 100000 | WA5: 100000 | WB5: =SUM(UZ5:WA5) | WC5: 100000 | WF5: 200000 | WI5: =25.998*4550 | WN5: 200000 | WR5: 101000 | WU5: 383221 | WX5: 100000 | WZ5: 100000 | XA5: 300000 | XE5: 100000 | XF5: 50000 | XH5: =SUM(WF5:XG5) | XI5: 200000 | XL5: 100000 | XN5: 100000 | XT5: 200000 | XY5: 100000 | XZ5: 100000 | YE5: 100000 | YI5: 100000 | YJ5: 103000 | YL5: 200000 | YM5: =SUM(XK5:YL5) | YN5: 0 | YO5: 5000 | YR5: 200000 | YZ5: 200000 | ZA5: 100000 | ZH5: 100000 | ZJ5: 200000 | ZK5: 200000 | ZM5: 100000 | ZQ5: 100000 | ZS5: =SUM(YN5:ZR5) | ZV5: 100000 | ZY5: 170000 | AAA5: 100000 | AAC5: 100000 | AAJ5: 100000 | AAL5: 100000 | AAN5: 100000 | AAS5: 100000 | AAW5: 100000 | AAX5: =SUM(ZT5:AAW5) | ABD5: 100000 | ABF5: 100000 | ABH5: 100000 | ABM5: 100000 | ABN5: 100000 | ABO5: 100000 | ABT5: 329490 | ABY5: 0 | ABZ5: 100000 | ACB5: 100000 | ACD5: =SUM(AAY5:ACC5) | ACJ5: 300000 | ADJ5: =SUM(ACE5:ADI5) | ADW5: 100000 | ADX5: 200000 | ADZ5: 100000 | AED5: 150000 | AEF5: 100000 | AEI5: 100000 | AEN5: 200000 | AEO5: =SUM(ADK5:AEN5) | AET5: 100000 | AEW5: 100000 | AFB5: 100000 | AFH5: 100000 | AFK5: 100000 | AFO5: 100000 | AFP5: 100000 | AFT5: 100000 | AFU5: =SUM(AEP5:AFT5) | AFV5: 100000 | AFW5: 50000 | AFZ5: 100000 | AGC5: 220000 | AGD5: 100000 | AGF5: 100000 | AGL5: 100000 | AGN5: 100000 | AGQ5: 100000 | AGR5: 100000 | AGU5: 100000 | AGW5: 100000 | AGZ5: =SUM(AFV5:AGY5) | AHA5: 100000 | AHE5: 100000 | AHG5: 100000 | AHK5: 100000 | AHQ5: 50000 | AHU5: 200000 | AHZ5: 100000 | AIB5: 50000 | AID5: 200000 | AIF5: =SUM(AHA5:AIE5) | AIJ5: 50000 | AIO5: 100000 | AIQ5: 100000 | AIX5: 100000 | AJE5: 100000 | AJF5: 100000 | AJL5: =SUM(AIG5:AJK5) | AJM5: 100000 | AJY5: 100000 | AKA5: 100000 | AKG5: 100000 | AKH5: 100000 | AKM5: 50000 | AKN5: 100000 | AKO5: =SUM(AJM5:AKN5) | AKP5: 50000 | AKQ5: 100000 | AKV5: 100000 | AKZ5: 100000 | ALC5: 100000 | ALD5: 100000 | ALG5: 100000 | ALH5: 100000 | ALM5: 100000 | ALP5: 200000 | ALQ5: 100000 | ALR5: 150000 | ALU5: =SUM(AKS5:ALT5) | ALZ5: 100000 | AMC5: 100000 | AMG5: 100000 | AMH5: 100000 | AML5: 100000 | AMO5: 200000 | AMT5: 100000 | AMU5: 100000 | AMV5: 200000 | AMX5: 100000 | AMY5: 100000 | AMZ5: =SUM(ALV5:AMY5) | ANA5: 100000 | ANB5: 50000 | ANE5: 200000 | ANH5: 100000 | ANP5: 100000 | ANQ5: 100000 | ANS5: 50000 | ANT5: 412375 | ANX5: 400000 | AOA5: 0 | AOB5: 200000
B6: FOOD | E6: 1000 | L6: 5000 | U6: 22000 | W6: 5000 | Y6: 6000 | AH6: =SUM(C6:AG6) | AJ6: 0 | AO6: 16000 | BA6: 0 | BB6: 6000 | BG6: 5000 | BK6: 5000 | BM6: =SUM(AI6:BL6) | BS6: 2500 | CE6: 5000 | CG6: 10000 | CS6: =SUM(BN6:CR6) | CW6: 14000 | DG6: 3000 | DH6: 8000 | DO6: 6000 | DX6: =SUM(CT6:DW6) | EJ6: 10000 | EK6: 2500 | FD6: =SUM(DY6:FC6) | FE6: 7000 | FJ6: 8000 | FN6: 6000 | FO6: 5000 | FZ6: 2000 | GB6: 12500 | GC6: 2000 | GF6: 7000 | GG6: 3000 | GJ6: =SUM(FE6:GI6) | GM6: 5000 | GR6: 15000 | HK6: 6000 | HN6: =SUM(GK6:HM6) | HW6: 10000 | HX6: 10000 | IT6: =SUM(HO6:IS6) | JY6: =SUM(IU6:JX6) | KH6: 3000 | KN6: 7000 | LE6: =SUM(KA6:LD6) | LK6: 9000 | LY6: 39000 | ME6: 5000 | MJ6: =SUM(LF6:MI6) | NP6: =SUM(ML6:NO6) | OK6: 6000 | OV6: =SUM(NR6:OU6) | OZ6: 5000 | PG6: 6000 | PJ6: 6000 | PL6: 5000 | PM6: 0 | PN6: 8000 | PU6: 12000 | QA6: =SUM(OW6:PZ6) | QQ6: 10000 | QX6: 4000 | RE6: 3000 | RG6: =SUM(QC6:RF6) | RH6: 5000 | RM6: 3000 | RW6: 12000 | SA6: 6000 | SH6: 9000 | SM6: =SUM(RI6:SL6) | SN6: 6000 | SR6: 3000 | SX6: 9000 | TE6: 17000 | TS6: =SUM(SO6:TR6) | TT6: 5000 | TV6: 3000 | UA6: 3000 | UC6: 0 | UD6: 1500 | UH6: 6000 | UM6: 4000 | UO6: 9000 | UV6: 8000 | UW6: 6000 | UY6: =SUM(TU6:UX6) | UZ6: 0 | VJ6: 3000 | VR6: 23000 | VY6: 12000 | WB6: =SUM(UZ6:WA6) | WP6: 0 | WQ6: 10000 | XH6: =SUM(WF6:XG6) | XL6: 10000 | XM6: 20000 | XQ6: 3000 | XW6: 2000 | XX6: 13000 | YE6: 3000 | YL6: 12000 | YM6: =SUM(XK6:YL6) | YN6: 0 | YT6: 8000 | YY6: 4000 | ZB6: 8000 | ZI6: 7000 | ZP6: 7000 | ZS6: =SUM(YN6:ZR6) | AAE6: 7000 | AAT6: 20000 | AAX6: =SUM(ZT6:AAW6) | ABL6: 8000 | ABS6: 19000 | ACD6: =SUM(AAY6:ACC6) | ADJ6: =SUM(ACE6:ADI6) | ADZ6: 9000 | AEF6: 5000 | AEN6: 8000 | AEO6: =SUM(ADK6:AEN6) | AFU6: =SUM(AEP6:AFT6) | AGL6: 1000 | AGZ6: =SUM(AFV6:AGY6) | AHC6: 5000 | AIF6: =SUM(AHA6:AIE6) | AIK6: 10000 | AIM6: 4000 | AIS6: 14000 | AJA6: 1000 | AJL6: =SUM(AIG6:AJK6) | AKO6: =SUM(AJM6:AKN6) | ALU6: =SUM(AKS6:ALT6) | AMP6: 5000 | AMZ6: =SUM(ALV6:AMY6) | AND6: 10000 | ANS6: 12000
B7: BROOM | H7: 0 | X7: 4000 | AH7: =SUM(C7:AG7) | AJ7: 0 | AQ7: 0 | BH7: 4000 | BI7: 0 | BM7: =SUM(AI7:BL7) | BU7: 0 | CL7: 4000 | CS7: =SUM(BN7:CR7) | DN7: 4000 | DX7: =SUM(CT7:DW7) | EA7: 10000 | ES7: 4000 | FD7: =SUM(DY7:FC7) | GA7: 4000 | GJ7: =SUM(FE7:GI7) | HH7: 4000 | HN7: =SUM(GK7:HM7) | IT7: =SUM(HO7:IS7) | JO7: 4000 | JY7: =SUM(IU7:JX7) | KT7: 14000 | LE7: =SUM(KA7:LD7) | MJ7: =SUM(LF7:MI7) | NP7: =SUM(ML7:NO7) | OI7: 4000 | OV7: =SUM(NR7:OU7) | PQ7: 4000 | QA7: =SUM(OW7:PZ7) | QV7: 4000 | RG7: =SUM(QC7:RF7) | SB7: 4000 | SM7: =SUM(RI7:SL7) | TH7: 4000 | TS7: =SUM(SO7:TR7) | UN7: 4000 | UY7: =SUM(TU7:UX7) | UZ7: 0 | WB7: =SUM(UZ7:WA7) | WU7: 5000 | WW7: 4000 | XH7: =SUM(WF7:XG7) | YM7: =SUM(XK7:YL7) | ZS7: =SUM(YN7:ZR7) | ZU7: 4000 | AAO7: 0 | AAP7: 4000 | AAX7: =SUM(ZT7:AAW7) | ABO7: 4000 | ACD7: =SUM(AAY7:ACC7) | ACM7: 4000 | ADJ7: =SUM(ACE7:ADI7) | ADR7: 4000 | AEO7: =SUM(ADK7:AEN7) | AEY7: 4000 | AFU7: =SUM(AEP7:AFT7) | AFZ7: 4000 | AGZ7: =SUM(AFV7:AGY7) | AIF7: =SUM(AHA7:AIE7) | AIJ7: 4000 | AJB7: 4000 | AJL7: =SUM(AIG7:AJK7) | AJQ7: 4000 | AKO7: =SUM(AJM7:AKN7) | ALU7: =SUM(AKS7:ALT7) | AMR7: 4000 | AMZ7: =SUM(ALV7:AMY7)
B8: Bankin transport | E8: 33000 | H8: 0 | X8: 18000 | Z8: 19000 | AD8: 4000 | AE8: 33000 | AH8: =SUM(C8:AG8) | AO8: 7000 | AS8: 14000 | AU8: 6000 | AV8: 6000 | AW8: 10000 | BL8: 58000 | BM8: =SUM(AI8:BL8) | CA8: 2000 | CG8: 5000 | CS8: =SUM(BN8:CR8) | FD8: =SUM(DY8:FC8) | HE8: 6000 | HF8: 14000 | HN8: =SUM(GK8:HM8) | IJ8: 12000 | IT8: =SUM(HO8:IS8) | JE8: 10000 | JS8: 8000 | JY8: =SUM(IU8:JX8) | LE8: =SUM(KA8:LD8) | MJ8: =SUM(LF8:MI8) | NP8: =SUM(ML8:NO8) | NY8: 4000 | OE8: 13000 | OT8: 8000 | OV8: =SUM(NR8:OU8) | QA8: =SUM(OW8:PZ8) | QK8: 20000 | RG8: =SUM(QC8:RF8) | SM8: =SUM(RI8:SL8) | SO8: 6500 | SP8: 12500 | TS8: =SUM(SO8:TR8) | UR8: 4000 | UY8: =SUM(TU8:UX8) | WB8: =SUM(UZ8:WA8) | WT8: 10000 | XH8: =SUM(WF8:XG8) | XI8: 20000 | XR8: 12000 | YM8: =SUM(XK8:YL8) | YS8: 14000 | ZS8: =SUM(YN8:ZR8) | AAD8: 14000 | AAX8: =SUM(ZT8:AAW8) | AAZ8: 16000 | ABB8: 2000 | ABE8: 2000 | ABF8: 2000 | ABG8: 2000 | ABL8: 2000 | ABM8: 2000 | ABN8: 2000 | ABO8: 2000 | ABP8: 2000 | ABQ8: 2000 | ABS8: 2000 | ABU8: 2000 | ABV8: 2000 | ABW8: 2000 | ABX8: 2000 | ACA8: 2000 | ACB8: 2000 | ACC8: 2000 | ACD8: =SUM(AAY8:ACC8) | ACE8: 2000 | ACF8: 2000 | ACH8: 2000 | ACI8: 2000 | ACJ8: 2000 | ACK8: 2000 | ACL8: 2000 | ACQ8: 2000 | ACR8: 2000 | ACS8: 2000 | ACT8: 2000 | ACV8: 4000 | ACW8: 2000 | ACX8: 2000 | ACY8: 2000 | ACZ8: 2000 | ADA8: 2000 | ADC8: 2000 | ADD8: 2000 | ADE8: 2000 | ADF8: 2000 | ADG8: 2000 | ADH8: 2000 | ADJ8: =SUM(ACE8:ADI8) | ADK8: 4000 | ADM8: 2000 | ADN8: 2000 | ADO8: 2000 | ADP8: 2000 | ADR8: 4000 | ADS8: 0 | ADT8: 2000 | ADV8: 2000 | ADW8: 2000 | ADY8: 2000 | AEA8: 2000 | AEB8: 26000 | AEC8: 2000 | AEH8: 2000 | AEI8: 2000 | AEJ8: 2000 | AEK8: 2000 | AEM8: 2000 | AEN8: 2000 | AEO8: =SUM(ADK8:AEN8) | AEP8: 2000 | AEQ8: 2000 | AER8: 2000 | AES8: 2000 | AEU8: 2000 | AEV8: 2000 | AEW8: 2000 | AEX8: 2000 | AEY8: 2000 | AEZ8: 2000 | AFB8: 2000 | AFC8: 2000 | AFD8: 2000 | AFE8: 2000 | AFF8: 2000 | AFG8: 2000 | AFI8: 2000 | AFJ8: 2000 | AFK8: 2000 | AFL8: 2000 | AFM8: 2000 | AFN8: 2000 | AFP8: 2000 | AFQ8: 2000 | AFR8: 2000 | AFS8: 2000 | AFT8: 4000 | AFU8: =SUM(AEP8:AFT8) | AFW8: 7000 | AFY8: 4000 | AFZ8: 4000 | AGA8: 2000 | AGB8: 2000 | AGC8: 2000 | AGE8: 14000 | AGF8: 2000 | AGG8: 2000 | AGH8: 2000 | AGI8: 2000 | AGJ8: 2000 | AGL8: 2000 | AGM8: 2000 | AGN8: 2000 | AGO8: 2000 | AGT8: 2000 | AGU8: 2000 | AGV8: 4000 | AGW8: 2000 | AGX8: 12000 | AGZ8: =SUM(AFV8:AGY8) | AHA8: 2000 | AHB8: 2000 | AHC8: 2000 | AHD8: 2000 | AHE8: 2000 | AHF8: 2000 | AHG8: 18000 | AHH8: 16000 | AHI8: 2000 | AHJ8: 2000 | AHK8: 2000 | AHL8: 2000 | AHM8: 2000 | AHO8: 2000 | AHP8: 2000 | AHQ8: 2000 | AHR8: 2000 | AHS8: 2000 | AHV8: 2000 | AHW8: 2000 | AHX8: 2000 | AHZ8: 2000 | AIA8: 2000 | AIC8: 2000 | AID8: 2000 | AIE8: 2000 | AIF8: =SUM(AHA8:AIE8) | AIG8: 0 | AII8: 2000 | AIK8: 2000 | AIL8: 2000 | AIM8: 2000 | AIN8: 2000 | AIO8: 2000 | AIR8: 2000 | AIS8: 2000 | AIT8: 0 | AIY8: 2000 | AIZ8: 2000 | AJA8: 2000 | AJB8: 2000 | AJC8: 2000 | AJD8: 2000 | AJF8: 2000 | AJG8: 2000 | AJH8: 2000 | AJI8: 2000 | AJJ8: 2000 | AJK8: 2000 | AJL8: =SUM(AIG8:AJK8) | AJN8: 2000 | AJO8: 2000 | AJP8: 2000 | AJQ8: 2000 | AJR8: 2000 | AJS8: 10000 | AJT8: 0 | AJU8: 2000 | AJV8: 2000 | AJW8: 2000 | AJX8: 2000 | AJY8: 2000 | AJZ8: 10000 | AKB8: 2000 | AKC8: 2000 | AKD8: 2000 | AKE8: 2000 | AKF8: 2000 | AKG8: 10000 | AKI8: 2000 | AKJ8: 2000 | AKK8: 2000 | AKL8: 2000 | AKM8: 2000 | AKN8: 8000 | AKO8: =SUM(AJM8:AKN8) | ALL8: 2000 | ALO8: 0 | ALP8: 2000 | ALS8: 2000 | ALT8: 2000 | ALU8: =SUM(AKS8:ALT8) | ALV8: 2000 | ALW8: 2000 | ALX8: 2000 | ALY8: 2000 | AMA8: 2000 | AMB8: 2000 | AMC8: 2000 | AMD8: 2000 | AME8: 2000 | AMF8: 2000 | AMG8: 0 | AMH8: 2000 | AMI8: 2000 | AMJ8: 2000 | AMK8: 2000 | AML8: 2000 | AMP8: 2000 | AMQ8: 2000 | AMR8: 2000 | AMS8: 2000 | AMU8: 2000 | AMX8: 2000 | AMZ8: =SUM(ALV8:AMY8) | ANG8: 2000 | ANH8: 2000 | ANI8: 2000 | ANK8: 6000 | ANL8: 2000 | ANM8: 2000 | ANN8: 2000 | ANO8: 2000 | ANP8: 2000 | ANR8: 2000 | ANS8: 2000 | ANT8: 2000 | ANU8: 26000 | ANV8: 14000 | ANW8: 10000 | ANY8: 2000 | ANZ8: 2000 | AOB8: 2000 | AOC8: 2000
B9: AIRTIME | E9: 2000 | H9: 0 | I9: 2000 | M9: 2000 | P9: 2000 | S9: 2000 | W9: 2000 | AA9: 2000 | AC9: 2000 | AG9: 2000 | AH9: =SUM(C9:AG9) | AL9: 2000 | AP9: 2000 | AS9: 2000 | AV9: 2000 | AX9: 1000 | AY9: 2000 | BC9: 2000 | BE9: 1000 | BF9: 2000 | BJ9: 2000 | BL9: 1000 | BM9: =SUM(AI9:BL9) | BO9: 2000 | BQ9: 2000 | BS9: 1000 | BT9: 1000 | BU9: 0 | BV9: 2000 | BY9: 2000 | CB9: 2000 | CG9: 2000 | CM9: 2000 | CQ9: 2000 | CS9: =SUM(BN9:CR9) | CV9: 2000 | DF9: 2000 | DI9: 2000 | DM9: 2000 | DP9: 3000 | DT9: 2000 | DW9: 2000 | DX9: =SUM(CT9:DW9) | EB9: 2000 | EF9: 2000 | EI9: 2000 | EL9: 2000 | EN9: 2000 | EQ9: 2000 | ES9: 2000 | ET9: 0 | EU9: 2000 | EX9: 2000 | EZ9: 2000 | FB9: 2000 | FD9: =SUM(DY9:FC9) | FE9: 2000 | FH9: 2000 | FK9: 2000 | FN9: 2000 | FS9: 2000 | FU9: 2000 | FW9: 2000 | FY9: 2000 | GB9: 2000 | GD9: 2000 | GG9: 2000 | GJ9: =SUM(FE9:GI9) | GK9: 2000 | GN9: 2000 | GP9: 2000 | GS9: 2000 | GV9: 2000 | GX9: 2000 | GZ9: 2000 | HB9: 2000 | HE9: 2000 | HG9: 2000 | HJ9: 2000 | HL9: 2000 | HN9: =SUM(GK9:HM9) | HO9: 2000 | HR9: 2000 | HT9: 2000 | HV9: 2000 | HY9: 2000 | IA9: 2000 | IC9: 2000 | IE9: 2000 | IH9: 2000 | IJ9: 2000 | IL9: 2000 | IO9: 2000 | IQ9: 2000 | IS9: 2000 | IT9: =SUM(HO9:IS9) | IZ9: 2000 | JB9: 2000 | JE9: 2000 | JI9: 2000 | JK9: 2000 | JO9: 2000 | JQ9: 2000 | JT9: 2000 | JV9: 2000 | JY9: =SUM(IU9:JX9) | JZ9: 2000 | KB9: 2000 | KF9: 2000 | KI9: 2000 | KK9: 2000 | KM9: 2000 | KP9: 2000 | KR9: 2000 | KT9: 2000 | KW9: 2000 | LA9: 2000 | LD9: 2000 | LE9: =SUM(KA9:LD9) | LJ9: 2000 | LL9: 2000 | LN9: 0 | LO9: 2000 | LQ9: 2000 | LS9: 2000 | LV9: 2000 | LX9: 2000 | LZ9: 2000 | MC9: 2000 | ME9: 2000 | MG9: 2000 | MJ9: =SUM(LF9:MI9) | MK9: 2000 | MM9: 2000 | MO9: 2000 | MU9: 2000 | MX9: 2000 | NC9: 2000 | NF9: 2000 | NH9: 2000 | NJ9: 2000 | NM9: 2000 | NO9: 2000 | NP9: =SUM(ML9:NO9) | NV9: 2000 | NY9: 2000 | OB9: 2000 | OD9: 2000 | OF9: 2000 | OI9: 2000 | OK9: 2000 | OP9: 2000 | OR9: 2000 | OT9: 2000 | OV9: =SUM(NR9:OU9) | OX9: 2000 | OZ9: 2000 | PB9: 2000 | PE9: 2000 | PG9: 2000 | PI9: 2000 | PL9: 2000 | PN9: 2000 | PP9: 2000 | PW9: 2000 | PZ9: 2000 | QA9: =SUM(OW9:PZ9) | QC9: 2000 | QE9: 2000 | QH9: 2000 | QJ9: 2000 | QL9: 2000 | QO9: 2000 | QQ9: 2000 | QS9: 2000 | QV9: 2000 | QX9: 2000 | QZ9: 2000 | RC9: 2000 | RE9: 2000 | RG9: =SUM(QC9:RF9) | RH9: 2000 | RK9: 2000 | RM9: 2000 | RO9: 2000 | RR9: 5000 | RT9: 2000 | RV9: 2000 | RY9: 2000 | SA9: 2000 | SC9: 2000 | SF9: 2000 | SH9: 2000 | SJ9: 2000 | SM9: =SUM(RI9:SL9) | SO9: 2000 | SQ9: 2000 | SS9: 2000 | SV9: 2000 | SX9: 2000 | SZ9: 2000 | TA9: 0 | TC9: 2000 | TE9: 2000 | TJ9: 2000 | TL9: 2000 | TQ9: 2000 | TS9: =SUM(SO9:TR9) | TT9: 2000 | TV9: 2000 | TY9: 2000 | UA9: 2000 | UC9: 2000 | UF9: 2000 | UH9: 2000 | UJ9: 2000 | UM9: 2000 | UO9: 2000 | UQ9: 2000 | UT9: 2000 | UV9: 5000 | UX9: 2000 | UY9: =SUM(TU9:UX9) | VB9: 2000 | VD9: 2000 | VF9: 2000 | VK9: 2000 | VM9: 2000 | VR9: 2000 | VT9: 2000 | VW9: 2000 | VY9: 2000 | WA9: 2000 | WB9: =SUM(UZ9:WA9) | WE9: 2000 | WG9: 2000 | WL9: 2000 | WS9: 2000 | WU9: 2000 | WW9: 2000 | WY9: 0 | WZ9: 2000 | XB9: 2000 | XD9: 2000 | XH9: =SUM(WF9:XG9) | XJ9: 2000 | XL9: 2000 | XQ9: 2000 | XS9: 2000 | XV9: 2000 | XX9: 2000 | XZ9: 2000 | YB9: 2000 | YE9: 2000 | YG9: 2000 | YJ9: 2000 | YL9: 2000 | YM9: =SUM(XK9:YL9) | ZB9: 2000 | ZF9: 2000 | ZH9: 5000 | ZJ9: 2000 | ZM9: 2000 | ZN9: 0 | ZO9: 2000 | ZQ9: 2000 | ZS9: =SUM(YN9:ZR9) | ZU9: 2000 | ZW9: 2000 | AAB9: 2000 | AAD9: 2000 | AAF9: 2000 | AAI9: 2000 | AAM9: 2000 | AAO9: 0 | AAP9: 2000 | AAR9: 2000 | AAT9: 2000 | AAW9: 2000 | AAX9: =SUM(ZT9:AAW9) | ABB9: 2000 | ABE9: 2000 | ABI9: 2000 | ABL9: 2000 | ABS9: 20000 | ABW9: 2000 | ABY9: 0 | ABZ9: 2000 | ACB9: 2000 | ACD9: =SUM(AAY9:ACC9) | ACE9: 2000 | ACH9: 2000 | ACJ9: 2000 | ACS9: 2000 | ACV9: 2000 | ACX9: 2000 | ACZ9: 2000 | ADC9: 2000 | ADE9: 2000 | ADG9: 2000 | ADJ9: =SUM(ACE9:ADI9) | ADK9: 2000 | ADL9: 2000 | ADM9: 2000 | ADO9: 2000 | ADR9: 4000 | ADT9: 2000 | ADV9: 2000 | ADY9: 2000 | AEA9: 2000 | AEC9: 2000 | AEH9: 2000 | AEJ9: 2000 | AEK9: 15000 | AEM9: 2000 | AEO9: =SUM(ADK9:AEN9) | AEP9: 2000 | AEQ9: 5000 | AER9: 2000 | AEU9: 2000 | AEY9: 2000 | AFB9: 2000 | AFE9: 2000 | AFK9: 2000 | AFM9: 2000 | AFP9: 2000 | AFU9: =SUM(AEP9:AFT9) | AFZ9: 2000 | AGD9: 15000 | AGE9: 2000 | AGI9: 2000 | AGL9: 2000 | AGO9: 2000 | AGT9: 2000 | AGW9: 2000 | AGZ9: =SUM(AFV9:AGY9) | AHA9: 2000 | AHC9: 2000 | AHD9: 10000 | AHE9: 2000 | AHH9: 2000 | AHJ9: 2000 | AHK9: 2000 | AHO9: 2000 | AHQ9: 2000 | AHS9: 2000 | AHV9: 2000 | AHX9: 2000 | AHZ9: 22000 | AIC9: 2000 | AIE9: 2000 | AIF9: =SUM(AHA9:AIE9) | AIG9: 0 | AIK9: 2000 | AIM9: 2000 | AIO9: 2000 | AIR9: 2000 | AIS9: 20000 | AIT9: 2000 | AIU9: 0 | AIV9: 2000 | AIY9: 2000 | AIZ9: 2000 | AJB9: 2000 | AJF9: 2000 | AJH9: 2000 | AJJ9: 2000 | AJL9: =SUM(AIG9:AJK9) | AJN9: 2000 | AJP9: 2000 | AJR9: 2000 | AJW9: 2000 | AJY9: 2000 | AKB9: 2000 | AKD9: 2000 | AKI9: 2000 | AKK9: 2000 | AKM9: 2000 | AKO9: =SUM(AJM9:AKN9) | AKQ9: 2000 | AKS9: 2000 | AKT9: 2000 | AKU9: 2000 | AKV9: 10000 | AKX9: 2000 | AKY9: 2000 | AKZ9: 2000 | ALA9: 2000 | ALB9: 8000 | ALE9: 2000 | ALF9: 2000 | ALG9: 2000 | ALH9: 2000 | ALL9: 2000 | ALM9: 20000 | ALN9: 22000 | ALO9: 0 | ALP9: 2000 | ALS9: 2000 | ALU9: =SUM(AKS9:ALT9) | ALV9: 2000 | ALW9: 2000 | ALZ9: 2000 | AMA9: 2000 | AMD9: 2000 | AME9: 2000 | AMF9: 2000 | AMG9: 2000 | AMH9: 2000 | AMJ9: 2000 | AML9: 2000 | AMP9: 2000 | AMR9: 2000 | AMZ9: =SUM(ALV9:AMY9) | ANA9: 2000 | ANC9: 2000 | ANG9: 2000 | ANI9: 2000 | ANK9: 2000 | ANM9: 2000 | ANO9: 2000 | ANR9: 2000 | ANT9: 2000 | ANV9: 2000 | ANX9: 2000 | ANY9: 2000 | ANZ9: 2000 | AOB9: 2000 | AOC9: 2000
B10: price survey | D10: 2000 | H10: 0 | M10: 2000 | W10: 2000 | AB10: 2000 | AH10: =SUM(C10:AG10) | AK10: 2000 | AM10: 2000 | AN10: 2000 | AS10: 2000 | AT10: 0 | AU10: 2000 | AX10: 2000 | BA10: 0 | BB10: 2000 | BE10: 2000 | BG10: 2000 | BM10: =SUM(AI10:BL10) | BO10: 2000 | BX10: 2000 | CE10: 4000 | CJ10: 2000 | CO10: 2000 | CQ10: 2000 | CS10: =SUM(BN10:CR10) | CY10: 2000 | DN10: 2000 | DU10: 2000 | DX10: =SUM(CT10:DW10) | EB10: 2000 | EJ10: 2000 | FD10: =SUM(DY10:FC10) | FH10: 2000 | FO10: 2000 | FZ10: 2000 | GJ10: =SUM(FE10:GI10) | GL10: 2000 | GP10: 2000 | HA10: 2000 | HL10: 2000 | HN10: =SUM(GK10:HM10) | HQ10: 2000 | HU10: 2000 | HW10: 2000 | HZ10: 2000 | IF10: 2000 | II10: 2000 | IM10: 2000 | IO10: 2000 | IT10: =SUM(HO10:IS10) | IU10: 2000 | IW10: 2000 | IX10: 2000 | JB10: 2000 | JI10: 2000 | JK10: 2000 | JP10: 2000 | JW10: 2000 | JY10: =SUM(IU10:JX10) | JZ10: 2000 | KB10: 2000 | KE10: 2000 | KG10: 2000 | KI10: 2000 | KN10: 2000 | KP10: 2000 | KS10: 2000 | KU10: 2000 | KZ10: 4000 | LB10: 2000 | LD10: 2000 | LE10: =SUM(KA10:LD10) | LH10: 2000 | LL10: 2000 | LN10: 0 | LO10: 2000 | LS10: 2000 | LV10: 2000 | LX10: 2000 | LZ10: 2000 | MC10: 2000 | ME10: 2000 | MG10: 2000 | MJ10: =SUM(LF10:MI10) | MK10: 2000 | MM10: 2000 | MO10: 2000 | MV10: 2000 | NA10: 2000 | NC10: 2000 | NF10: 2000 | NH10: 2000 | NJ10: 2000 | NM10: 2000 | NO10: 2000 | NP10: =SUM(ML10:NO10) | NR10: 2000 | NT10: 0 | NU10: 2000 | NW10: 2000 | NY10: 2000 | OB10: 2000 | OD10: 2000 | OF10: 2000 | OI10: 2000 | OK10: 2000 | OM10: 2000 | OP10: 2000 | OR10: 2000 | OT10: 2000 | OV10: =SUM(NR10:OU10) | OX10: 2000 | OZ10: 2000 | PB10: 2000 | PE10: 2000 | PG10: 2000 | PI10: 2000 | PL10: 2000 | PN10: 2000 | PP10: 2000 | PS10: 2000 | PU10: 2000 | PW10: 2000 | PZ10: 2000 | QA10: =SUM(OW10:PZ10) | QC10: 2000 | QE10: 2000 | QH10: 2000 | QJ10: 2000 | QL10: 2000 | QO10: 2000 | QQ10: 2000 | QS10: 2000 | QV10: 2000 | QX10: 2000 | QZ10: 2000 | RC10: 2000 | RE10: 2000 | RG10: =SUM(QC10:RF10) | RH10: 2000 | RK10: 2000 | RM10: 2000 | RO10: 2000 | RR10: 2000 | RT10: 2000 | RV10: 2000 | RY10: 2000 | SA10: 2000 | SC10: 2000 | SF10: 2000 | SH10: 2000 | SM10: =SUM(RI10:SL10) | SO10: 2000 | SQ10: 2000 | SV10: 2000 | SX10: 2000 | SZ10: 2000 | TA10: 0 | TC10: 2000 | TJ10: 2000 | TL10: 2000 | TQ10: 2000 | TS10: =SUM(SO10:TR10) | TT10: 2000 | TV10: 2000 | TY10: 2000 | UA10: 2000 | UC10: 2000 | UF10: 2000 | UH10: 2000 | UJ10: 2000 | UM10: 2000 | UO10: 2000 | UQ10: 2000 | UT10: 2000 | UV10: 2000 | UX10: 2000 | UY10: =SUM(TU10:UX10) | VB10: 2000 | VD10: 2000 | VF10: 2000 | VI10: 2000 | VK10: 2000 | VM10: 2000 | VP10: 2000 | VR10: 2000 | VT10: 2000 | VW10: 2000 | VY10: 2000 | WA10: 2000 | WB10: =SUM(UZ10:WA10) | WE10: 2000 | WG10: 2000 | WL10: 2000 | WS10: 2000 | WU10: 2000 | WW10: 2000 | WY10: 0 | WZ10: 2000 | XB10: 2000 | XD10: 2000 | XH10: =SUM(WF10:XG10) | XJ10: 2000 | XL10: 2000 | XQ10: 2000 | XS10: 2000 | XV10: 2000 | XX10: 2000 | XZ10: 2000 | YB10: 2000 | YE10: 2000 | YG10: 2000 | YJ10: 2000 | YL10: 2000 | YM10: =SUM(XK10:YL10) | YO10: 2000 | YY10: 2000 | ZB10: 2000 | ZF10: 2000 | ZH10: 2000 | ZJ10: 2000 | ZM10: 2000 | ZO10: 2000 | ZQ10: 2000 | ZS10: =SUM(YN10:ZR10) | ZU10: 2000 | ZW10: 2000 | AAB10: 2000 | AAD10: 2000 | AAF10: 2000 | AAI10: 2000 | AAK10: 2000 | AAM10: 2000 | AAO10: 0 | AAP10: 2000 | AAR10: 2000 | AAT10: 2000 | AAW10: 2000 | AAX10: =SUM(ZT10:AAW10) | ABB10: 2000 | ABC10: 2000 | ABE10: 2000 | ABI10: 2000 | ABL10: 2000 | ABS10: 2000 | ABW10: 2000 | ABY10: 0 | ABZ10: 2000 | ACB10: 2000 | ACD10: =SUM(AAY10:ACC10) | ACE10: 2000 | ACH10: 2000 | ACJ10: 2000 | ACS10: 2000 | ACV10: 2000 | ACX10: 2000 | ACZ10: 2000 | ADC10: 2000 | ADE10: 2000 | ADG10: 2000 | ADJ10: =SUM(ACE10:ADI10) | ADK10: 2000 | ADM10: 2000 | ADO10: 2000 | ADR10: 2000 | ADT10: 2000 | ADV10: 2000 | ADY10: 2000 | AEA10: 2000 | AEC10: 2000 | AEH10: 2000 | AEJ10: 2000 | AEM10: 2000 | AEO10: =SUM(ADK10:AEN10) | AEP10: 2000 | AER10: 2000 | AEU10: 2000 | AEY10: 2000 | AFB10: 2000 | AFE10: 2000 | AFK10: 2000 | AFM10: 2000 | AFP10: 2000 | AFU10: =SUM(AEP10:AFT10) | AFZ10: 2000 | AGE10: 2000 | AGI10: 2000 | AGL10: 2000 | AGO10: 2000 | AGT10: 2000 | AGW10: 2000 | AGZ10: =SUM(AFV10:AGY10) | AHA10: 2000 | AHC10: 2000 | AHE10: 2000 | AHH10: 2000 | AHJ10: 2000 | AHK10: 2000 | AHO10: 2000 | AHQ10: 2000 | AHS10: 2000 | AHV10: 2000 | AHX10: 2000 | AHZ10: 2000 | AIC10: 2000 | AIE10: 2000 | AIF10: =SUM(AHA10:AIE10) | AIK10: 2000 | AIM10: 2000 | AIO10: 2000 | AIR10: 2000 | AIZ10: 2000 | AJB10: 2000 | AJH10: 2000 | AJJ10: 2000 | AJL10: =SUM(AIG10:AJK10) | AJN10: 2000 | AJR10: 2000 | AJW10: 2000 | AJY10: 2000 | AKB10: 2000 | AKD10: 2000 | AKI10: 2000 | AKK10: 2000 | AKM10: 2000 | AKO10: =SUM(AJM10:AKN10) | AKQ10: 2000 | AKS10: 2000 | AKU10: 2000 | AKX10: 2000 | AKZ10: 2000 | ALB10: 2000 | ALE10: 2000 | ALL10: 2000 | ALN10: 2000 | ALO10: 0 | ALP10: 2000 | ALS10: 2000 | ALU10: =SUM(AKS10:ALT10) | ALV10: 2000 | ALW10: 2000 | ALX10: 2000 | ALY10: 2000 | AMA10: 2000 | AME10: 2000 | AMH10: 2000 | AMJ10: 2000 | AMP10: 2000 | AMR10: 0 | AMZ10: =SUM(ALV10:AMY10) | ANG10: 2000 | ANM10: 2000 | ANO10: 2000 | ANR10: 2000 | ANT10: 2000 | ANV10: 2000 | ANY10: 2000 | AOB10: 2000
B11: Security | G11: 1200000 | H11: 0 | AH11: =SUM(C11:AG11) | AN11: 1200000 | BM11: =SUM(AI11:BL11) | BP11: 1200000 | CS11: =SUM(BN11:CR11) | DB11: 1200000 | DX11: =SUM(CT11:DW11) | EC11: 1200000 | FD11: =SUM(DY11:FC11) | FN11: 1200000 | GJ11: =SUM(FE11:GI11) | GU11: 1200000 | HN11: =SUM(GK11:HM11) | HV11: 1200000 | IT11: =SUM(HO11:IS11) | IZ11: 1200000 | JY11: =SUM(IU11:JX11) | KF11: 1200000 | LE11: =SUM(KA11:LD11) | LI11: 1200000 | LJ11: 2000 | MJ11: =SUM(LF11:MI11) | ML11: 1200000 | NP11: =SUM(ML11:NO11) | NS11: 1200000 | OV11: =SUM(NR11:OU11) | PE11: 1200000 | PS11: 2000 | QA11: =SUM(OW11:PZ11) | QD11: 1200000 | RG11: =SUM(QC11:RF11) | RN11: 1200000 | SM11: =SUM(RI11:SL11) | SS11: 1200000 | TS11: =SUM(SO11:TR11) | UG11: 1200000 | UY11: =SUM(TU11:UX11) | VC11: 1200000 | WB11: =SUM(UZ11:WA11) | WF11: 1200000 | XH11: =SUM(WF11:XG11) | XJ11: 1200000 | YM11: =SUM(XK11:YL11) | YS11: 1200000 | ZS11: =SUM(YN11:ZR11) | AAC11: 1200000 | AAX11: =SUM(ZT11:AAW11) | AAY11: 1200000 | ACD11: =SUM(AAY11:ACC11) | ADJ11: =SUM(ACE11:ADI11) | ADK11: 0 | AEO11: =SUM(ADK11:AEN11) | AFU11: =SUM(AEP11:AFT11) | AGZ11: =SUM(AFV11:AGY11) | AIF11: =SUM(AHA11:AIE11) | AJL11: =SUM(AIG11:AJK11) | AKO11: =SUM(AJM11:AKN11) | AKQ11: 2000 | AKS11: 2000 | AKU11: 2000 | AKX11: 2000 | AKZ11: 2000 | ALB11: 2000 | ALE11: 2000 | ALL11: 0 | ALU11: =SUM(AKS11:ALT11) | AMZ11: =SUM(ALV11:AMY11)
B12: Hose pipe and Rubber | G12: 12000 | H12: 0 | M12: 10000 | Q12: 14000 | W12: 12000 | AA12: 10000 | AB12: 10000 | AH12: =SUM(C12:AG12) | AJ12: 12000 | AN12: 18000 | AO12: 10000 | AP12: 350000 | AT12: 12000 | AU12: 12000 | AV12: 10000 | BE12: 100000 | BM12: =SUM(AI12:BL12) | BQ12: 40000 | CS12: =SUM(BN12:CR12) | CV12: 2650000 | CW12: 50000 | DX12: =SUM(CT12:DW12) | FD12: =SUM(DY12:FC12) | HN12: =SUM(GK12:HM12) | IT12: =SUM(HO12:IS12) | JY12: =SUM(IU12:JX12) | LE12: =SUM(KA12:LD12) | MJ12: =SUM(LF12:MI12) | NP12: =SUM(ML12:NO12) | OV12: =SUM(NR12:OU12) | QA12: =SUM(OW12:PZ12) | RG12: =SUM(QC12:RF12) | SM12: =SUM(RI12:SL12) | TS12: =SUM(SO12:TR12) | UY12: =SUM(TU12:UX12) | WB12: =SUM(UZ12:WA12) | XH12: =SUM(WF12:XG12) | YM12: =SUM(XK12:YL12) | ZS12: =SUM(YN12:ZR12) | AAX12: =SUM(ZT12:AAW12) | ACD12: =SUM(AAY12:ACC12) | ADJ12: =SUM(ACE12:ADI12) | AEO12: =SUM(ADK12:AEN12) | AFU12: =SUM(AEP12:AFT12) | AGZ12: =SUM(AFV12:AGY12) | AIF12: =SUM(AHA12:AIE12) | AJL12: =SUM(AIG12:AJK12) | AKO12: =SUM(AJM12:AKN12) | ALU12: =SUM(AKS12:ALT12) | AMZ12: =SUM(ALV12:AMY12)
B13: Salary | C13: 0 | D13: 2306000 | H13: 0 | AA13: 75000 | AH13: =SUM(C13:AG13) | AL13: 2525000 | BM13: =SUM(AI13:BL13) | BP13: =2657000+50000 | CS13: =SUM(BN13:CR13) | CW13: 0 | DX13: =SUM(CT13:DW13) | EB13: 2536000 | FD13: =SUM(DY13:FC13) | FH13: 2503000 | FJ13: 60000 | FN13: 200000 | GJ13: =SUM(FE13:GI13) | GO13: 2418500 | GQ13: 75000 | HN13: =SUM(GK13:HM13) | HR13: 2019000 | IT13: =SUM(HO13:IS13) | IW13: 2132500 | JY13: =SUM(IU13:JX13) | KB13: 2238200 | LE13: =SUM(KA13:LD13) | LH13: 2247000 | MJ13: =SUM(LF13:MI13) | MM13: 2235000 | NP13: =SUM(ML13:NO13) | NR13: 2241000 | OV13: =SUM(NR13:OU13) | OX13: 2237000 | QA13: =SUM(OW13:PZ13) | QC13: 2148000 | RG13: =SUM(QC13:RF13) | RI13: 2326000 | SM13: =SUM(RI13:SL13) | SQ13: 2308500 | TS13: =SUM(SO13:TR13) | TV13: 2073600 | TW13: 50000 | UY13: =SUM(TU13:UX13) | VB13: 2049000 | VG13: 225000 | WB13: =SUM(UZ13:WA13) | WE13: 2270000 | WN13: 36000 | XH13: =SUM(WF13:XG13) | XL13: 1991500 | YM13: =SUM(XK13:YL13) | YO13: 2044400 | ZS13: =SUM(YN13:ZR13) | ZV13: 2186000 | AAX13: =SUM(ZT13:AAW13) | ACD13: =SUM(AAY13:ACC13) | ACH13: 2147000 | ADJ13: =SUM(ACE13:ADI13) | ADM13: 2599900 | AEO13: =SUM(ADK13:AEN13) | AES13: 2240000 | AFU13: =SUM(AEP13:AFT13) | AFZ13: =2120800+45000 | AGC13: 40000 | AGZ13: =SUM(AFV13:AGY13) | AHC13: 2169000 | AIF13: =SUM(AHA13:AIE13) | AIM13: 2303000 | AJL13: =SUM(AIG13:AJK13) | AJP13: 2377500 | AKO13: =SUM(AJM13:AKN13) | AKS13: 2755800 | AKU13: 70000 | ALU13: =SUM(AKS13:ALT13) | ALX13: 2253000 | AMZ13: =SUM(ALV13:AMY13) | AND13: 2301000 | ANG13: 396000 | ANM13: 100000
B14: staff advance | J14: 50000 | AO14: 51900000 | AU14: =10000*5350 | BM14: =SUM(AI14:BL14) | CJ14: 50000 | CS14: =SUM(BN14:CR14) | DP14: 20000 | DX14: =SUM(CT14:DW14) | DY14: 100000 | FC14: 100000 | FD14: =SUM(DY14:FC14) | FS14: 50000 | FW14: 80000 | GC14: 100000 | GJ14: =SUM(FE14:GI14) | GZ14: 50000 | HJ14: 40000 | HN14: =SUM(GK14:HM14) | HO14: 216000 | IB14: 50000 | IH14: 15000 | II14: 80000 | IM14: 110000 | IQ14: 100000 | IT14: =SUM(HO14:IS14) | JI14: 50000 | JJ14: 100000 | JL14: 50000 | JM14: 120000 | JT14: 25000 | JY14: =SUM(IU14:JX14) | KN14: =60000+90000 | KO14: =40000+70000+80000 | KS14: 70000 | LE14: =SUM(KA14:LD14) | LN14: 0 | LO14: 50000 | LT14: =50000+100000 | LZ14: 100000 | MJ14: =SUM(LF14:MI14) | MQ14: 50000 | MX14: 60000 | ND14: 50000 | NH14: 70000 | NI14: 50000 | NJ14: 50000 | NP14: =SUM(ML14:NO14) | OC14: 50000 | OE14: =50000+50000 | OF14: 100000 | OG14: 70000 | OV14: =SUM(NR14:OU14) | PK14: 20000 | PM14: 0 | PN14: 80000 | PQ14: 50000 | QA14: =SUM(OW14:PZ14) | QQ14: 50000 | QT14: 90000 | RF14: 60000 | RG14: =SUM(QC14:RF14) | RV14: 270000 | SA14: 90000 | SM14: =SUM(RI14:SL14) | TE14: 60000 | TF14: 800000 | TH14: 50000 | TK14: 250000 | TP14: 50000 | TS14: =SUM(SO14:TR14) | UH14: =40000+70000 | UI14: 110000 | UM14: 120000 | UR14: =50000+40000 | UW14: 50000 | UY14: =SUM(TU14:UX14) | VP14: 50000 | VW14: 100000 | WB14: =SUM(UZ14:WA14) | WN14: 300000 | XD14: 50000 | XH14: =SUM(WF14:XG14) | XT14: 150000 | YA14: =70000+50000 | YE14: 500000 | YI14: 50000 | YM14: =SUM(XK14:YL14) | YV14: 45000 | ZB14: 150000 | ZH14: 60000 | ZJ14: 150000 | ZL14: 10000 | ZS14: =SUM(YN14:ZR14) | AAD14: 75000 | AAK14: 110000 | AAL14: =20000+50000 | AAX14: =SUM(ZT14:AAW14) | AAZ14: 2150000 | ABM14: 30000 | ABO14: =50000+30000 | ABP14: 50000 | ABS14: 120000 | ACD14: =SUM(AAY14:ACC14) | ACT14: 30000 | ACV14: 100000 | ADJ14: =SUM(ACE14:ADI14) | ADZ14: 30000 | AEA14: =85000+110000+70000+50000 | AEC14: 150000 | AED14: 0 | AEF14: 0 | AEH14: 60000 | AEO14: =SUM(ADK14:AEN14) | AEX14: 200000 | AFE14: 30000 | AFI14: 50000 | AFL14: 50000 | AFP14: 50000 | AFU14: =SUM(AEP14:AFT14) | AGH14: 50000 | AGJ14: 70000 | AGL14: 30000 | AGS14: 50000 | AGT14: 100000 | AGV14: 50000 | AGZ14: =SUM(AFV14:AGY14) | AHT14: =150000+50000 | AHU14: 20000 | AIF14: =SUM(AHA14:AIE14) | AIS14: 150000 | AIX14: 150000 | AIY14: 50000 | AIZ14: 50000 | AJL14: =SUM(AIG14:AJK14) | AKO14: =SUM(AJM14:AKN14) | ALF14: 50000 | ALG14: 150000 | ALJ14: 50000 | ALN14: 50000 | ALU14: =SUM(AKS14:ALT14) | AMO14: 50000 | AMP14: 70000 | AMR14: 100000 | AMZ14: =SUM(ALV14:AMY14) | ANT14: =60000+70000 | ANW14: =150000+50000+100000 | ANY14: 50000
B15: water bill | L15: 235000 | AL15: 168200 | BM15: =SUM(AI15:BL15) | BS15: 157700 | CS15: =SUM(BN15:CR15) | CY15: 207000 | DX15: =SUM(CT15:DW15) | EJ15: 153100 | FA15: 170800 | FD15: =SUM(DY15:FC15) | GR15: 213000 | HN15: =SUM(GK15:HM15) | HY15: 207000 | IT15: =SUM(HO15:IS15) | IY15: 172000 | JY15: =SUM(IU15:JX15) | KF15: 183000 | LA15: 183000 | LE15: =SUM(KA15:LD15) | MJ15: =SUM(LF15:MI15) | MS15: 194800 | NP15: =SUM(ML15:NO15) | OC15: 248600 | OV15: =SUM(NR15:OU15) | OX15: 242000 | PZ15: 272000 | QA15: =SUM(OW15:PZ15) | RE15: 175000 | RG15: =SUM(QC15:RF15) | SM15: =SUM(RI15:SL15) | SP15: 186500 | TS15: =SUM(SO15:TR15) | TU15: 198500 | UY15: =SUM(TU15:UX15) | VD15: 174100 | WB15: =SUM(UZ15:WA15) | WH15: 198500 | XH15: =SUM(WF15:XG15) | XJ15: 256500 | YM15: =SUM(XK15:YL15) | YV15: 358000 | ZQ15: 322000 | ZS15: =SUM(YN15:ZR15) | AAW15: 327000 | AAX15: =SUM(ZT15:AAW15) | ACB15: 292000 | ACD15: =SUM(AAY15:ACC15) | ADJ15: =SUM(ACE15:ADI15) | ADN15: 230000 | AEO15: =SUM(ADK15:AEN15) | AEP15: 206600 | AFQ15: 236000 | AFU15: =SUM(AEP15:AFT15) | AFY15: 93000 | AGV15: 170000 | AGZ15: =SUM(AFV15:AGY15) | AHV15: 152000 | AIF15: =SUM(AHA15:AIE15) | AJG15: 146000 | AJL15: =SUM(AIG15:AJK15) | AKI15: 158600 | AKO15: =SUM(AJM15:AKN15) | ALP15: 183000 | ALU15: =SUM(AKS15:ALT15) | AMW15: 241499 | AMZ15: =SUM(ALV15:AMY15) | ANZ15: 202000
B16: generator | X16: 93000 | AP16: 48500 | AY16: 98000 | BD16: 49000 | BM16: =SUM(AI16:BL16) | BN16: 99000 | CC16: 99000 | CM16: 99000 | CS16: =SUM(BN16:CR16) | DE16: 49500 | DJ16: 99800 | DS16: 99800 | DT16: 299400 | DU16: 199600 | DX16: =SUM(CT16:DW16) | ED16: 49900 | EF16: 99800 | EG16: 49900 | EH16: 266750 | EI16: 97000 | EJ16: 48500 | EW16: 48500 | FD16: =SUM(DY16:FC16) | FZ16: 97000 | GB16: 48500 | GC16: 48500 | GJ16: =SUM(FE16:GI16) | GR16: 97000 | HD16: 97000 | HE16: 97000 | HJ16: 48500 | HK16: 145500 | HN16: =SUM(GK16:HM16) | HT16: 97000 | IE16: 99000 | IM16: 346500 | IT16: =SUM(HO16:IS16) | JA16: 99800 | JN16: 99800 | JS16: 199600 | JY16: =SUM(IU16:JX16) | KH16: 97800 | KT16: 97800 | KX16: 97800 | KY16: 97800 | KZ16: 97800 | LE16: =SUM(KA16:LD16) | LL16: 194000 | LP16: 97000 | LV16: 97000 | LW16: 194000 | LX16: 145500 | MJ16: =SUM(LF16:MI16) | MO16: 97000 | MP16: 97000 | NC16: 47990 | NF16: 95980 | NK16: 191960 | NP16: =SUM(ML16:NO16) | NX16: 94980 | OF16: 47490 | OR16: 47490 | OS16: 94980 | OV16: =SUM(NR16:OU16) | PE16: 94980 | PG16: 189960 | PH16: 94980 | PS16: 71235 | PW16: 47490 | PZ16: 94980 | QA16: =SUM(OW16:PZ16) | QC16: 142470 | QJ16: 94980 | QU16: 91980 | QZ16: 91980 | RC16: 91980 | RG16: =SUM(QC16:RF16) | RN16: 91980 | RR16: 89400 | RS16: 44700 | RT16: 44700 | RW16: 178800 | RZ16: 312900 | SA16: 312900 | SB16: 223500 | SM16: =SUM(RI16:SL16) | SS16: 44700 | SZ16: 89400 | TA16: 0 | TF16: 89400 | TI16: 89400 | TP16: 89400 | TS16: =SUM(SO16:TR16) | TZ16: 44700 | UE16: 89400 | UL16: 44900 | UQ16: 89800 | UY16: =SUM(TU16:UX16) | VS16: 45500 | VW16: 45500 | VX16: 91000 | VY16: 318500 | WB16: =SUM(UZ16:WA16) | WI16: 91000 | WJ16: 364000 | WK16: 445000 | WL16: 250250 | WX16: 273000 | XA16: 182000 | XB16: 550800 | XD16: 91800 | XG16: 91800 | XH16: =SUM(WF16:XG16) | XI16: 91800 | XM16: 91800 | XN16: 183600 | XY16: 93000 | YK16: 93000 | YM16: =SUM(XK16:YL16) | YO16: 186000 | YP16: 93000 | YT16: 93000 | ZA16: 186000 | ZD16: 93000 | ZS16: =SUM(YN16:ZR16) | AAA16: 186000 | AAD16: 93000 | AAG16: 46500 | AAH16: 186000 | AAX16: =SUM(ZT16:AAW16) | ABA16: 93000 | ABF16: 186000 | ABT16: 93000 | ACD16: =SUM(AAY16:ACC16) | ACK16: 186000 | ACL16: 372000 | ACM16: 93000 | ADB16: 139500 | ADC16: 372000 | ADD16: 232500 | ADF16: 93000 | ADJ16: =SUM(ACE16:ADI16) | ADN16: 93000 | ADX16: 93000 | AEB16: 139500 | AEC16: 93000 | AEO16: =SUM(ADK16:AEN16) | AET16: 93000 | AEW16: 93000 | AFG16: 93000 | AFI16: 186000 | AFR16: 93000 | AFU16: =SUM(AEP16:AFT16) | AGE16: =93000+93000 | AGO16: 93000 | AGV16: 0 | AGW16: 90980 | AGZ16: =SUM(AFV16:AGY16) | AHL16: 91780 | AHW16: 91780 | AIF16: =SUM(AHA16:AIE16) | AIM16: 183560 | AIQ16: 91780 | AJJ16: 91980 | AJL16: =SUM(AIG16:AJK16) | AJV16: 91980 | AKA16: 91980 | AKO16: =SUM(AJM16:AKN16) | AKY16: 45990 | ALC16: =92980+185960 | ALD16: =185960+185960 | ALE16: 185960 | ALG16: 140970 | ALO16: 100000 | ALR16: 200000 | ALS16: 250000 | ALU16: =SUM(AKS16:ALT16) | AMI16: 311940 | AML16: 262450 | AMM16: 367430 | AMN16: 393675 | AMO16: 314940 | AMR16: 157470 | AMZ16: =SUM(ALV16:AMY16) | AND16: 168870 | ANE16: 281450 | ANJ16: 112580 | ANO16: =56290+20000 | ANP16: 354000 | ANQ16: 118000 | ANW16: 128980 | ANX16: 128980 | ANZ16: 128980
B17: shorteg | AC17: 1826000 | AN17: 5535576 | AO17: 20000 | BM17: =SUM(AI17:BL17) | CS17: =SUM(BN17:CR17) | EJ17: 35067 | EK17: 10000 | FD17: =SUM(DY17:FC17) | GG17: 600000 | GJ17: =SUM(FE17:GI17) | HN17: =SUM(GK17:HM17) | IT17: =SUM(HO17:IS17) | JY17: =SUM(IU17:JX17) | LE17: =SUM(KA17:LD17) | MJ17: =SUM(LF17:MI17) | NP17: =SUM(ML17:NO17) | OV17: =SUM(NR17:OU17) | OW17: 0 | QA17: =SUM(OW17:PZ17) | RG17: =SUM(QC17:RF17) | SM17: =SUM(RI17:SL17) | TS17: =SUM(SO17:TR17) | UY17: =SUM(TU17:UX17) | WB17: =SUM(UZ17:WA17) | XH17: =SUM(WF17:XG17) | XQ17: 30000 | YM17: =SUM(XK17:YL17) | ZS17: =SUM(YN17:ZR17) | AAX17: =SUM(ZT17:AAW17) | ACD17: =SUM(AAY17:ACC17) | ADJ17: =SUM(ACE17:ADI17) | AEO17: =SUM(ADK17:AEN17) | AFU17: =SUM(AEP17:AFT17) | AFV17: 2224432 | AGO17: 0 | AGZ17: =SUM(AFV17:AGY17) | AIF17: =SUM(AHA17:AIE17) | AJL17: =SUM(AIG17:AJK17) | AKO17: =SUM(AJM17:AKN17) | ALU17: =SUM(AKS17:ALT17) | ALZ17: 18000 | AMZ17: =SUM(ALV17:AMY17) | AND17: 12635 | ANS17: 224000
B18: Toiletpaper | CE18: 10000 | CL18: 50000 | CS18: =SUM(BN18:CR18) | CW18: 6000 | DO18: 2000 | DX18: =SUM(CT18:DW18) | EE18: 60000 | ET18: 0 | EU18: 10000 | FD18: =SUM(DY18:FC18) | FT18: 15000 | GJ18: =SUM(FE18:GI18) | HK18: 10000 | HN18: =SUM(GK18:HM18) | IT18: =SUM(HO18:IS18) | JY18: =SUM(IU18:JX18) | LE18: =SUM(KA18:LD18) | MJ18: =SUM(LF18:MI18) | NP18: =SUM(ML18:NO18) | OP18: 17000 | OV18: =SUM(NR18:OU18) | OW18: 0 | PG18: 50000 | QA18: =SUM(OW18:PZ18) | RG18: =SUM(QC18:RF18) | SM18: =SUM(RI18:SL18) | TS18: =SUM(SO18:TR18) | UI18: 10000 | UY18: =SUM(TU18:UX18) | WB18: =SUM(UZ18:WA18) | XH18: =SUM(WF18:XG18) | YM18: =SUM(XK18:YL18) | YV18: 25000 | ZS18: =SUM(YN18:ZR18) | AAX18: =SUM(ZT18:AAW18) | ACD18: =SUM(AAY18:ACC18) | ACY18: 10000 | ADJ18: =SUM(ACE18:ADI18) | AEO18: =SUM(ADK18:AEN18) | AFU18: =SUM(AEP18:AFT18) | AGZ18: =SUM(AFV18:AGY18) | AIF18: =SUM(AHA18:AIE18) | AJL18: =SUM(AIG18:AJK18) | AKO18: =SUM(AJM18:AKN18) | ALU18: =SUM(AKS18:ALT18) | AMZ18: =SUM(ALV18:AMY18) | ANK18: 20000
B19: Toilet repair | RJ19: 170000 | UU19: 15000 | WB19: =SUM(UZ19:WA19) | XH19: =SUM(WF19:XG19) | XS19: 30000 | YM19: =SUM(XK19:YL19) | YV19: 30000 | ZD19: 25000 | ZR19: 50000 | ZS19: =SUM(YN19:ZR19) | AAH19: 30000 | AAX19: =SUM(ZT19:AAW19) | ABP19: 145000 | ACD19: =SUM(AAY19:ACC19) | ACG19: 41000 | ACL19: 60000 | ACX19: 30000 | ADJ19: =SUM(ACE19:ADI19) | AEO19: =SUM(ADK19:AEN19) | AFO19: 2500 | AFU19: =SUM(AEP19:AFT19) | AGR19: 60000 | AGZ19: =SUM(AFV19:AGY19) | AIF19: =SUM(AHA19:AIE19) | AJL19: =SUM(AIG19:AJK19) | AKE19: 150000 | AKO19: =SUM(AJM19:AKN19) | AKR19: 25000 | AKS19: 65000 | ALU19: =SUM(AKS19:ALT19) | AMZ19: =SUM(ALV19:AMY19)
B20: Book | CE20: 11000 | CS20: =SUM(BN20:CR20) | FB20: 15300 | FD20: =SUM(DY20:FC20) | FJ20: 2000 | FV20: 11000 | GE20: 20000 | GJ20: =SUM(FE20:GI20) | HN20: =SUM(GK20:HM20) | IR20: 14000 | IT20: =SUM(HO20:IS20) | JY20: =SUM(IU20:JX20) | KB20: 2000 | LE20: =SUM(KA20:LD20) | LH20: 9800 | LR20: 9400 | MJ20: =SUM(LF20:MI20) | NP20: =SUM(ML20:NO20) | NU20: 144000 | OV20: =SUM(NR20:OU20) | OY20: 17800 | PP20: 8800 | QA20: =SUM(OW20:PZ20) | QQ20: 9000 | QZ20: 170000 | RA20: 16800 | RG20: =SUM(QC20:RF20) | RW20: =13200+9800 | SM20: =SUM(RI20:SL20) | TS20: =SUM(SO20:TR20) | UY20: =SUM(TU20:UX20) | VM20: 13800 | WB20: =SUM(UZ20:WA20) | WG20: 11400 | XH20: =SUM(WF20:XG20) | YM20: =SUM(XK20:YL20) | YZ20: 13500 | ZS20: =SUM(YN20:ZR20) | AAX20: =SUM(ZT20:AAW20) | ABG20: 18500 | ABI20: 9600 | ABP20: 16000 | ABU20: 8000 | ACD20: =SUM(AAY20:ACC20) | ADJ20: =SUM(ACE20:ADI20) | ADW20: 50000 | AEO20: =SUM(ADK20:AEN20) | AEU20: 5000 | AFU20: =SUM(AEP20:AFT20) | AGZ20: =SUM(AFV20:AGY20) | AHS20: 5500 | AIF20: =SUM(AHA20:AIE20) | AJL20: =SUM(AIG20:AJK20) | AJV20: 5000 | AKK20: 6500 | AKO20: =SUM(AJM20:AKN20) | AKV20: 24000 | ALU20: =SUM(AKS20:ALT20) | ALW20: 10000 | AMZ20: =SUM(ALV20:AMY20)
B21: bucket | CE21: 12000 | CS21: =SUM(BN21:CR21) | FD21: =SUM(DY21:FC21) | HN21: =SUM(GK21:HM21) | IT21: =SUM(HO21:IS21) | JY21: =SUM(IU21:JX21) | LE21: =SUM(KA21:LD21) | MJ21: =SUM(LF21:MI21) | NP21: =SUM(ML21:NO21) | OV21: =SUM(NR21:OU21) | QA21: =SUM(OW21:PZ21) | RG21: =SUM(QC21:RF21) | SM21: =SUM(RI21:SL21) | TS21: =SUM(SO21:TR21) | UY21: =SUM(TU21:UX21) | WB21: =SUM(UZ21:WA21) | XH21: =SUM(WF21:XG21) | YM21: =SUM(XK21:YL21) | ZS21: =SUM(YN21:ZR21) | AAX21: =SUM(ZT21:AAW21) | ACD21: =SUM(AAY21:ACC21) | ADJ21: =SUM(ACE21:ADI21) | AEO21: =SUM(ADK21:AEN21) | AFU21: =SUM(AEP21:AFT21) | AGZ21: =SUM(AFV21:AGY21) | AIF21: =SUM(AHA21:AIE21) | AJL21: =SUM(AIG21:AJK21) | AJV21: 25000 | AKO21: =SUM(AJM21:AKN21) | ALU21: =SUM(AKS21:ALT21) | AMZ21: =SUM(ALV21:AMY21) | ANF21: 26000
B22: cleaning | CD22: 50000 | CS22: =SUM(BN22:CR22) | FD22: =SUM(DY22:FC22) | GA22: 1000 | GE22: 20000 | GJ22: =SUM(FE22:GI22) | GP22: 20000 | GT22: 8500 | GZ22: 90000 | HD22: 11000 | HJ22: 160000 | HN22: =SUM(GK22:HM22) | IB22: 15000 | ID22: 200000 | IT22: =SUM(HO22:IS22) | JY22: =SUM(IU22:JX22) | KE22: 60000 | KQ22: 15000 | KS22: 30000 | KT22: 20000 | LE22: =SUM(KA22:LD22) | MJ22: =SUM(LF22:MI22) | NP22: =SUM(ML22:NO22) | OP22: 54000 | OT22: 170000 | OV22: =SUM(NR22:OU22) | QA22: =SUM(OW22:PZ22) | QB22: 0 | RG22: =SUM(QC22:RF22) | SM22: =SUM(RI22:SL22) | TS22: =SUM(SO22:TR22) | UY22: =SUM(TU22:UX22) | WB22: =SUM(UZ22:WA22) | WC22: 5000 | WD22: 5000 | WE22: 5000 | WI22: 22000 | XB22: 25000 | XH22: =SUM(WF22:XG22) | YM22: =SUM(XK22:YL22) | YQ22: 5000 | YR22: 5000 | YS22: 5000 | ZJ22: 10000 | ZS22: =SUM(YN22:ZR22) | AAF22: 40000 | AAX22: =SUM(ZT22:AAW22) | ACD22: =SUM(AAY22:ACC22) | ACT22: 7000 | ADJ22: =SUM(ACE22:ADI22) | AEO22: =SUM(ADK22:AEN22) | AFU22: =SUM(AEP22:AFT22) | AGZ22: =SUM(AFV22:AGY22) | AIF22: =SUM(AHA22:AIE22) | AIJ22: 30000 | AJB22: 60000 | AJL22: =SUM(AIG22:AJK22) | AKO22: =SUM(AJM22:AKN22) | ALS22: 60000 | ALU22: =SUM(AKS22:ALT22) | AMT22: 58000 | AMV22: 2000 | AMZ22: =SUM(ALV22:AMY22)
B23: URA | BW23: 400000 | CS23: =SUM(BN23:CR23) | FD23: =SUM(DY23:FC23) | HN23: =SUM(GK23:HM23) | IT23: =SUM(HO23:IS23) | JY23: =SUM(IU23:JX23) | LE23: =SUM(KA23:LD23) | MJ23: =SUM(LF23:MI23) | NP23: =SUM(ML23:NO23) | OV23: =SUM(NR23:OU23) | QA23: =SUM(OW23:PZ23) | RG23: =SUM(QC23:RF23) | SM23: =SUM(RI23:SL23) | TS23: =SUM(SO23:TR23) | UY23: =SUM(TU23:UX23) | WB23: =SUM(UZ23:WA23) | XH23: =SUM(WF23:XG23) | YM23: =SUM(XK23:YL23) | ZS23: =SUM(YN23:ZR23) | AAX23: =SUM(ZT23:AAW23) | ACD23: =SUM(AAY23:ACC23) | ADJ23: =SUM(ACE23:ADI23) | AEO23: =SUM(ADK23:AEN23) | AFU23: =SUM(AEP23:AFT23) | AGZ23: =SUM(AFV23:AGY23) | AIF23: =SUM(AHA23:AIE23) | AJL23: =SUM(AIG23:AJK23) | AKO23: =SUM(AJM23:AKN23) | ALU23: =SUM(AKS23:ALT23) | AMZ23: =SUM(ALV23:AMY23)
B24: slashing | CK24: 20000 | CR24: 0 | CS24: =SUM(BN24:CR24) | DA24: 20000 | DU24: 20000 | DX24: =SUM(CT24:DW24) | EN24: 20000 | FD24: =SUM(DY24:FC24) | FO24: 20000 | GJ24: =SUM(FE24:GI24) | HB24: 20000 | HN24: =SUM(GK24:HM24) | HO24: 20000 | II24: 20000 | IT24: =SUM(HO24:IS24) | JJ24: 20000 | JY24: =SUM(IU24:JX24) | KM24: 20000 | LE24: =SUM(KA24:LD24) | LX24: 20000 | MJ24: =SUM(LF24:MI24) | NF24: 20000 | NP24: =SUM(ML24:NO24) | OD24: 20000 | OU24: 20000 | OV24: =SUM(NR24:OU24) | PT24: 20000 | QA24: =SUM(OW24:PZ24) | QM24: 20000 | RG24: =SUM(QC24:RF24) | RK24: 20000 | SK24: 20000 | SM24: =SUM(RI24:SL24) | TS24: =SUM(SO24:TR24) | UT24: 20000 | UY24: =SUM(TU24:UX24) | WB24: =SUM(UZ24:WA24) | XH24: =SUM(WF24:XG24) | XJ24: 20000 | YF24: 20000 | YM24: =SUM(XK24:YL24) | ZC24: 20000 | ZR24: 20000 | ZS24: =SUM(YN24:ZR24) | AAX24: =SUM(ZT24:AAW24) | ACD24: =SUM(AAY24:ACC24) | ADE24: 20000 | ADJ24: =SUM(ACE24:ADI24) | AEO24: =SUM(ADK24:AEN24) | AFL24: 20000 | AFU24: =SUM(AEP24:AFT24) | AGJ24: 20000 | AGZ24: =SUM(AFV24:AGY24) | AID24: 20000 | AIF24: =SUM(AHA24:AIE24) | AJD24: 20000 | AJL24: =SUM(AIG24:AJK24) | AKL24: 20000 | AKO24: =SUM(AJM24:AKN24) | ALM24: 20000 | ALU24: =SUM(AKS24:ALT24) | AMQ24: 20000 | AMZ24: =SUM(ALV24:AMY24) | ANN24: 20000
B25: ummeme | DU25: 290000 | DX25: =SUM(CT25:DW25) | EI25: 40000 | FD25: =SUM(DY25:FC25) | HN25: =SUM(GK25:HM25) | IT25: =SUM(HO25:IS25) | JY25: =SUM(IU25:JX25) | LE25: =SUM(KA25:LD25) | MJ25: =SUM(LF25:MI25) | NP25: =SUM(ML25:NO25) | OV25: =SUM(NR25:OU25) | QA25: =SUM(OW25:PZ25) | RG25: =SUM(QC25:RF25) | SM25: =SUM(RI25:SL25) | TQ25: 20000 | TS25: =SUM(SO25:TR25) | UY25: =SUM(TU25:UX25) | WB25: =SUM(UZ25:WA25) | XH25: =SUM(WF25:XG25) | YM25: =SUM(XK25:YL25) | ZS25: =SUM(YN25:ZR25) | AAH25: 10000 | AAX25: =SUM(ZT25:AAW25) | ACD25: =SUM(AAY25:ACC25) | ADJ25: =SUM(ACE25:ADI25) | AEO25: =SUM(ADK25:AEN25) | AFU25: =SUM(AEP25:AFT25) | AGZ25: =SUM(AFV25:AGY25) | AIF25: =SUM(AHA25:AIE25) | AJL25: =SUM(AIG25:AJK25) | AKO25: =SUM(AJM25:AKN25) | ALU25: =SUM(AKS25:ALT25) | AMZ25: =SUM(ALV25:AMY25)
B26: padlock | EJ26: 100000 | FD26: =SUM(DY26:FC26) | GC26: 20000 | GF26: 15000 | GJ26: =SUM(FE26:GI26) | HL26: 30000 | HN26: =SUM(GK26:HM26) | IT26: =SUM(HO26:IS26) | JY26: =SUM(IU26:JX26) | LE26: =SUM(KA26:LD26) | MG26: 25000 | MJ26: =SUM(LF26:MI26) | NP26: =SUM(ML26:NO26) | OV26: =SUM(NR26:OU26) | PL26: 10000 | PM26: 0 | PN26: 5000 | QA26: =SUM(OW26:PZ26) | QY26: 7000 | RG26: =SUM(QC26:RF26) | SM26: =SUM(RI26:SL26) | TS26: =SUM(SO26:TR26) | TU26: 6000 | UG26: 5000 | UY26: =SUM(TU26:UX26) | WB26: =SUM(UZ26:WA26) | WL26: 5000 | WU26: 10000 | XH26: =SUM(WF26:XG26) | YF26: 60000 | YM26: =SUM(XK26:YL26) | ZS26: =SUM(YN26:ZR26) | AAB26: 25000 | AAX26: =SUM(ZT26:AAW26) | ACD26: =SUM(AAY26:ACC26) | ACL26: 25000 | ADC26: 10000 | ADJ26: =SUM(ACE26:ADI26) | ADY26: 5000 | AEO26: =SUM(ADK26:AEN26) | AFH26: 30000 | AFU26: =SUM(AEP26:AFT26) | AGZ26: =SUM(AFV26:AGY26) | AHM26: 20000 | AIF26: =SUM(AHA26:AIE26) | AIS26: 21000 | AIW26: 30000 | AJC26: 10000 | AJL26: =SUM(AIG26:AJK26) | AJO26: 10000 | AKO26: =SUM(AJM26:AKN26) | ALU26: =SUM(AKS26:ALT26) | ALW26: 5000 | AMD26: 65000 | AMO26: 5000 | AMU26: 15000 | AMZ26: =SUM(ALV26:AMY26)
B27: credit sales | FV27: 314474 | FY27: 151000 | GA27: 232000 | GD27: 250000 | GJ27: =SUM(FE27:GI27) | HD27: =392026+9506000 | HE27: 378300 | HG27: =50000+388291 | HL27: =52900+266750 | HM27: =428110+100000 | HN27: =SUM(GK27:HM27) | HO27: 50000 | HP27: =100000+126100 | HQ27: 295000 | HR27: 630000 | HS27: 630327 | HU27: =50*4850 | HW27: 238050 | HY27: 145500 | IG27: 198000 | IJ27: 200000 | IK27: 148500 | IT27: =SUM(HO27:IS27) | IU27: =40000+95000 | IV27: 418052 | IX27: 249500 | JA27: =140000+22000 | JG27: 300000 | JH27: 0 | JP27: 385000 | JX27: 26750 | JY27: =SUM(IU27:JX27) | KE27: 760000 | KF27: 365136 | KG27: =530000+760000 | KI27: =106000+1086000 | KM27: =337654+76000+30000 | KN27: 181000 | KO27: 4890000 | KP27: 813000 | KQ27: 586800 | KT27: 2117370 | KU27: =1760400+274818 | KV27: =1000*4890 | KX27: =69000+224000 | LC27: =321000+105000+66000 | LE27: =SUM(KA27:LD27) | LJ27: =107000+44000 | LS27: 410000 | LY27: =112000+69000 | LZ27: 129000 | ME27: 397793 | MG27: 215000 | MH27: 151000 | MJ27: =SUM(LF27:MI27) | MK27: =856000+210000 | MU27: 296626 | MV27: 24000 | MW27: 50000 | MZ27: 100000 | NA27: 1276000 | NB27: 305504 | NH27: =11000+15000 | NL27: =107000+44000 | NN27: =856000+210000+15000+20000 | NP27: =SUM(ML27:NO27) | NU27: 200000 | OI27: =388516+112000+69000 | OM27: =6000+214000+66000+105000 | OQ27: =856000+6000 | OT27: =220000+642000+6000 | OV27: =SUM(NR27:OU27) | OX27: 448000 | OY27: 400000 | OZ27: 294117 | PB27: =856000+105000+220000+8000 | PC27: 100000 | PD27: =107000+44000 | PE27: 321000 | PF27: =6000+856000 | PO27: 725000 | PQ27: 112000 | PT27: 374400 | PV27: =107000+44000 | PW27: 0 | PX27: 199648 | QA27: =SUM(OW27:PZ27) | QO27: 100000 | RB27: 200000 | RE27: 346811 | RG27: =SUM(QC27:RF27) | RI27: =110000+23000 | RJ27: =44000+107000 | RL27: 336141 | SB27: 50000 | SF27: 1356540 | SM27: =SUM(RI27:SL27) | SO27: 983400 | SP27: 8805900 | TS27: =SUM(SO27:TR27) | UM27: 40000 | UR27: 20000 | UY27: =SUM(TU27:UX27) | VY27: 107778 | WB27: =SUM(UZ27:WA27) | WG27: 13500 | XA27: 598507 | XH27: =SUM(WF27:XG27) | YI27: 510000 | YM27: =SUM(XK27:YL27) | YP27: 900000 | ZS27: =SUM(YN27:ZR27) | AAL27: 525000 | AAX27: =SUM(ZT27:AAW27) | ACD27: =SUM(AAY27:ACC27) | ADJ27: =SUM(ACE27:ADI27) | AEO27: =SUM(ADK27:AEN27) | AFU27: =SUM(AEP27:AFT27) | AGP27: 130000 | AGZ27: =SUM(AFV27:AGY27) | AHR27: 220000 | AIF27: =SUM(AHA27:AIE27) | AJL27: =SUM(AIG27:AJK27) | AKO27: =SUM(AJM27:AKN27) | ALE27: 400000 | ALU27: =SUM(AKS27:ALT27) | AMZ27: =SUM(ALV27:AMY27)
B28: Rtt | ACF28: 0 | ADJ28: =SUM(ACE28:ADI28) | AEO28: =SUM(ADK28:AEN28) | AFU28: =SUM(AEP28:AFT28) | AGZ28: =SUM(AFV28:AGY28) | AIF28: =SUM(AHA28:AIE28) | AJL28: =SUM(AIG28:AJK28) | AKO28: =SUM(AJM28:AKN28) | ALU28: =SUM(AKS28:ALT28) | AMZ28: =SUM(ALV28:AMY28)
B29: cash withdrow from bussines | AIS29: 6500000 | AIX29: 290000 | AKO29: =SUM(AJM29:AKN29) | AKP29: 5000000 | ALU29: =SUM(AKS29:ALT29) | AMH29: 639300 | AMZ29: =SUM(ALV29:AMY29)
B30: other transport | AEP30: 14000 | AER30: 14000 | AFU30: =SUM(AEP30:AFT30) | AGZ30: =SUM(AFV30:AGY30) | AHF30: 54439 | AHL30: 50000 | AIF30: =SUM(AHA30:AIE30) | AIJ30: 150000 | AIL30: 10000 | AJI30: 5000 | AJK30: 8000 | AJL30: =SUM(AIG30:AJK30) | AKO30: =SUM(AJM30:AKN30) | ALU30: =SUM(AKS30:ALT30) | AMZ30: =SUM(ALV30:AMY30)
B31: others | H31: 0 | I31: 11000 | J31: 5000 | K31: 0 | N31: 271000 | R31: 20000 | S31: 200000 | U31: 0 | V31: 50000 | W31: 20000 | AD31: 4000 | AE31: 5000 | AG31: 150000 | AH31: =SUM(C31:AG31) | AJ31: 11500 | AO31: 290000 | AQ31: 0 | AR31: 7000 | AT31: 21000 | AW31: 20000 | AX31: 300000 | BC31: 114000 | BE31: 24000 | BG31: 10000 | BH31: 100000 | BL31: 20000 | BM31: =SUM(AI31:BL31) | BS31: 2000 | BU31: 0 | BV31: 10000 | BZ31: 300 | CA31: 15000 | CK31: 1000 | CL31: 279000 | CN31: 1000 | CO31: 13000 | CP31: 60000 | CQ31: 355000 | CR31: 28846 | CS31: =SUM(BN31:CR31) | CW31: 120000 | CY31: 10000 | CZ31: 263000 | DF31: 500 | DH31: 24440 | DI31: 6000 | DK31: 15000 | DM31: 100000 | DP31: 2000 | DT31: 10000 | DX31: =SUM(CT31:DW31) | DY31: 50000 | EC31: 1000 | EF31: 30000 | EG31: 372334 | EI31: 2000 | EL31: 267235 | EO31: 0 | EP31: 182942 | ET31: 0 | EU31: 397021 | FC31: 238572 | FD31: =SUM(DY31:FC31) | FJ31: 363265 | FN31: 40000 | FP31: 20000 | FQ31: 20000 | FY31: 0 | GC31: 20000 | GH31: 1000 | GI31: 2000 | GJ31: =SUM(FE31:GI31) | GP31: 20000 | GR31: 1000 | GZ31: 2000 | HD31: 1200000 | HE31: 20000 | HH31: 400000 | HN31: =SUM(GK31:HM31) | IA31: 1000 | IB31: 532000 | IJ31: 4500 | IO31: 3120 | IQ31: 440000 | IT31: =SUM(HO31:IS31) | JB31: 100000 | JC31: 260000 | JN31: 2000 | JO31: 2000 | JS31: 700000 | JT31: 20000 | JW31: 7000 | JX31: 1000 | JY31: =SUM(IU31:JX31) | KI31: 287000 | KJ31: 50000 | KR31: 2000 | KW31: 485000 | LB31: 138000 | LE31: =SUM(KA31:LD31) | LF31: 23000 | LH31: 32000 | LK31: =50000+44000 | LP31: 2000 | LQ31: 2000 | LS31: =210000+330000+535000 | LU31: 160000 | LV31: =179014+336000 | LX31: 5000 | MC31: 3000 | ME31: 190000 | MG31: 15000 | MJ31: =SUM(LF31:MI31) | MK31: 3000 | MN31: 1000 | MP31: 4000 | MR31: 8000 | MT31: 4000 | MV31: 65000 | MX31: 8000 | NA31: 5000 | NF31: 20000 | NH31: 5000 | NI31: 2000 | NJ31: 5000 | NN31: 20000 | NO31: 1000 | NP31: =SUM(ML31:NO31) | NX31: 200000 | NY31: 636000 | NZ31: 5000 | OA31: 376263 | OD31: 1000 | OP31: 20000 | OV31: =SUM(NR31:OU31) | PE31: 4500 | PF31: 490000 | PL31: 50000 | PO31: 57500 | PT31: 150000 | PU31: 1000 | QA31: =SUM(OW31:PZ31) | QH31: 6000 | QN31: 1000 | QW31: 45990 | QZ31: 1550000 | RA31: =112000+46000 | RE31: 60000 | RG31: =SUM(QC31:RF31) | RJ31: 2000 | RK31: 20000 | RM31: 55000 | SA31: 1500000 | SB31: 1129800 | SI31: 1000 | SM31: =SUM(RI31:SL31) | SR31: 10000 | SZ31: 20000 | TA31: 0 | TC31: 2000 | TD31: 3500 | TE31: 5000 | TF31: 1500 | TJ31: 4000 | TO31: 1000 | TR31: 1500000 | TS31: =SUM(SO31:TR31) | TT31: 5000000 | UA31: 10000 | UB31: 1000 | UF31: 2000 | UG31: 103000 | UM31: 53000 | UO31: 10000 | UP31: 15000 | UU31: 10000 | UY31: =SUM(TU31:UX31) | VB31: 35000 | VE31: 12000 | VF31: 60000 | VH31: 10000 | VK31: 1000 | VQ31: 3000 | VX31: 5000 | VY31: 5000 | VZ31: 5000 | WA31: 5000 | WB31: =SUM(UZ31:WA31) | WD31: 15000 | WG31: 300000 | WH31: 10000 | WJ31: 54000 | WO31: 0 | WP31: 55000 | WS31: 25000 | WU31: 130000 | WV31: 200000 | WW31: 55000 | XA31: 1000 | XD31: 55000 | XE31: 340000 | XH31: =SUM(WF31:XG31) | XM31: 2560 | XO31: 14000 | XR31: 5000 | XV31: 20000 | YD31: 120000 | YE31: 1000 | YM31: =SUM(XK31:YL31) | YQ31: 0 | YW31: 32000 | ZD31: 10000 | ZF31: 99000 | ZO31: 20000 | ZQ31: 15000 | ZS31: =SUM(YN31:ZR31) | ZW31: 1255000 | ZX31: 96000 | ZY31: 220000 | AAH31: 39920 | AAK31: 1000 | AAL31: 25000 | AAV31: 10000 | AAX31: =SUM(ZT31:AAW31) | ABI31: 1000 | ABL31: 10000 | ABN31: 10000 | ACD31: =SUM(AAY31:ACC31) | ACF31: 0 | ACK31: 2500 | ACP31: 150000 | ADF31: 2000 | ADJ31: =SUM(ACE31:ADI31) | ADM31: 2000 | ADS31: 1000 | AEB31: 1000 | AEI31: 1108000 | AEM31: 200000 | AEO31: =SUM(ADK31:AEN31) | AFH31: 50000 | AFK31: 8000 | AFL31: 16000 | AFU31: =SUM(AEP31:AFT31) | AGG31: 30000 | AGH31: 60000 | AGO31: 30000 | AGZ31: =SUM(AFV31:AGY31) | AHC31: 52000 | AHF31: 400000 | AHQ31: 144000 | AHW31: 10000 | AIA31: 15000 | AIF31: =SUM(AHA31:AIE31) | AIN31: 3600000 | AJA31: 20000 | AJJ31: 5000 | AJL31: =SUM(AIG31:AJK31) | AKF31: 10000 | AKG31: 25000 | AKM31: 255000 | AKO31: =SUM(AJM31:AKN31) | AKS31: 15000 | AKV31: 40000 | AKY31: 5000 | ALE31: 1000 | ALH31: 310000 | ALL31: 16000 | ALM31: 1000 | ALQ31: 487500 | ALU31: =SUM(AKS31:ALT31) | AMC31: 45000 | AMD31: 1000 | AMH31: 150000 | AML31: 17000 | AMT31: 25000 | AMZ31: =SUM(ALV31:AMY31) | ANB31: 3000 | AND31: 130000 | ANE31: 200000 | ANF31: 6000 | ANI31: 170000 | ANM31: 30000 | ANP31: 5000 | ANR31: 25000 | ANY31: 1000
B32: TOTAL EXPENSES | C32: =SUM(C3:C13) | D32: =SUM(D3:D13) | E32: =SUM(E3:E13) | F32: =SUM(F3:F13) | G32: =SUM(G3:G13) | H32: =SUM(H3:H13) | I32: =SUM(I3:I31) | J32: =SUM(J3:J31) | K32: =SUM(K3:K31) | L32: =SUM(L3:L31) | M32: =SUM(M3:M31) | N32: =SUM(N3:N31) | O32: =SUM(O3:O31) | P32: =SUM(P3:P31) | ... AG32: =SUM(AG3:AG31) | AH32: =SUM(C32:AG32) | AI32: =SUM(AI4:AI31) | AJ32: =SUM(AJ4:AJ31) | AK32: =SUM(AK4:AK31) | AL32: =SUM(AL4:AL31) | AM32: =SUM(AM4:AM31) | AN32: =SUM(AN4:AN31) | AO32: =SUM(AO4:AO31) | AP32: =SUM(AP4:AP31) | ... BL32: =SUM(BL4:BL31) | BM32: =SUM(AI32:BL32) | BN32: =SUM(BN4:BN31) | BO32: =SUM(BO4:BO31) | BP32: =SUM(BP3:BP31) | BQ32: =SUM(BQ3:BQ31) | BR32: =SUM(BR3:BR31) | BS32: =SUM(BS3:BS31) | BT32: =SUM(BT3:BT31) | BU32: =SUM(BU3:BU31) | BV32: =SUM(BV3:BV31) | BW32: =SUM(BW3:BW31) | ... CJ32: =SUM(CJ3:CJ31) | CL32: =SUM(CL3:CL31) | CM32: =SUM(CM3:CM31) | CN32: =SUM(CN3:CN31) | CO32: =SUM(CO3:CO31) | CP32: =SUM(CP3:CP31) | CQ32: =SUM(CQ3:CQ31) | CR32: =SUM(CR3:CR31) | CS32: =SUM(BN32:CR32) | CT32: =SUM(CT3:CT31) | CU32: =SUM(CU3:CU31) | CV32: =SUM(CV3:CV31) | CW32: =SUM(CW3:CW31) | CX32: =SUM(CX3:CX31) | CY32: =SUM(CY3:CY31) | CZ32: =SUM(CZ3:CZ31) | DA32: =SUM(DA3:DA31) | ... DW32: =SUM(DW3:DW31) | DX32: =SUM(CT32:DW32) | DY32: =SUM(DY3:DY31) | DZ32: =SUM(DZ3:DZ31) | EA32: =SUM(EA3:EA31) | EB32: =SUM(EB3:EB31) | EC32: =SUM(EC3:EC31) | ED32: =SUM(ED3:ED31) | EE32: =SUM(EE3:EE31) | EF32: =SUM(EF3:EF31) | ... FC32: =SUM(FC3:FC31) | FE32: =SUM(FE3:FE31) | FF32: =SUM(FF3:FF31) | FG32: =SUM(FG3:FG31) | FH32: =SUM(FH3:FH31) | FI32: =SUM(FI3:FI31) | FJ32: =SUM(FJ3:FJ31) | FK32: =SUM(FK3:FK31) | FL32: =SUM(FL3:FL31) | ... GI32: =SUM(GI3:GI31) | GJ32: =SUM(FE32:GI32) | GK32: =SUM(GK3:GK31) | GL32: =SUM(GL3:GL31) | GM32: =SUM(GM3:GM31) | GN32: =SUM(GN3:GN31) | GO32: =SUM(GO3:GO31) | GP32: =SUM(GP3:GP31) | GQ32: =SUM(GQ3:GQ31) | GR32: =SUM(GR3:GR31) | ... ADI32: =SUM(ADI3:ADI31) | ADJ32: =SUM(ACE32:ADI32) | ADK32: =SUM(ADK3:ADK31) | ADL32: =SUM(ADL3:ADL31) | ADM32: =SUM(ADM3:ADM31) | ADN32: =SUM(ADN3:ADN31) | ADO32: =SUM(ADO3:ADO31) | ADP32: =SUM(ADP3:ADP31) | ADQ32: =SUM(ADQ3:ADQ31) | ADR32: =SUM(ADR3:ADR31) | ... AEN32: =SUM(AEN3:AEN31) | AEO32: =SUM(ADK32:AEN32) | AEP32: =SUM(AEP3:AEP31) | AEQ32: =SUM(AEQ3:AEQ31) | AER32: =SUM(AER3:AER31) | AES32: =SUM(AES3:AES31) | AET32: =SUM(AET3:AET31) | AEU32: =SUM(AEU3:AEU31) | AEV32: =SUM(AEV3:AEV31) | AEW32: =SUM(AEW3:AEW31) | ... AFT32: =SUM(AFT3:AFT31) | AFU32: =SUM(AEP32:AFT32) | AFV32: =SUM(AFV3:AFV31) | AFW32: =SUM(AFW3:AFW31) | AFX32: =SUM(AFX3:AFX31) | AFY32: =SUM(AFY3:AFY31) | AFZ32: =SUM(AFZ3:AFZ31) | AGA32: =SUM(AGA3:AGA31) | AGB32: =SUM(AGB3:AGB31) | AGC32: =SUM(AGC3:AGC31) | ... AKN32: =SUM(AKN3:AKN31) | AKO32: =SUM(AJM32:AKN32) | AKP32: =SUM(AKP3:AKP31) | AKQ32: =SUM(AKQ3:AKQ31) | AKR32: =SUM(AKR3:AKR31) | AKS32: =SUM(AKS3:AKS31) | AKT32: =SUM(AKT3:AKT31) | AKU32: =SUM(AKU3:AKU31) | AKV32: =SUM(AKV3:AKV31) | AKW32: =SUM(AKW3:AKW31) | ... ALT32: =SUM(ALT3:ALT31) | ALU32: =SUM(AKS32:ALT32) | ALV32: =SUM(ALV3:ALV31) | ALW32: =SUM(ALW3:ALW31) | ALX32: =SUM(ALX3:ALX31) | ALY32: =SUM(ALY3:ALY31) | ALZ32: =SUM(ALZ3:ALZ31) | AMA32: =SUM(AMA3:AMA31) | AMB32: =SUM(AMB3:AMB31) | AMC32: =SUM(AMC3:AMC31) | ... AMY32: =SUM(AMY3:AMY31) | AMZ32: =SUM(ALV32:AMY32) | ANA32: =SUM(ANA3:ANA31) | ANB32: =SUM(ANB3:ANB31) | ANC32: =SUM(ANC3:ANC31) | AND32: =SUM(AND3:AND31) | ANE32: =SUM(ANE3:ANE31) | ANF32: =SUM(ANF3:ANF31) | ANG32: =SUM(ANG3:ANG31) | ANH32: =SUM(ANH3:ANH31) | ... AOD32: =SUM(AOD3:AOD31)
CK33: =SUM(CK3:CK32) | AFV33: stolen
AFV34: 2224432
BP36: 1200000 | HR36: =224000+69000+2000 | AIM36: cash withdrow 3600000 buy dollar 1000 bank stanbic
BP37: 2707000 | AIM37: cash withdrow 6500000 for shifan school fee
BP38: 20000 | ADW38: 17th | ADX38: 85000 | ADY38: blasio
BP39: =SUM(BP36:BP38) | ADX39: 110000 | ADY39: baker
EG40: 100000 | ADX40: 70000 | ADY40: ricky
EG41: 10000 | ADX41: 50000 | ADY41: latif
EG42: 100000
EG43: 2000
EG44: 35067 | UU44: 35000
EG45: 48500
EG46: 151900
EG47: 1200 | QY47: 7
EG48: =SUM(EG40:EG47)

Sheet METER
A3: ITEMS | B3: PARTICULARS | D3: 44204 | E3: 44965 | F3: 44993 | G3: 45024 | H3: 45054 | I3: 45085 | J3: 45115 | K3: 45146 | L3: 45177 | M3: 45207 | N3: 45238 | O3: 45268 | P3: 13/8/23 | Q3: 14/8/23 | R3: 15/8/23 | S3: 16/8/23 | T3: 17/8/23 | U3: 18/8/23 | V3: 19/8/23 | W3: 20/8/23 | X3: 21/8/23 | Y3: 22/8/23 | Z3: 23/8/23 | AA3: 24/8/23 | AB3: 25/8/23 | AC3: 26/8/23 | AD3: 27/8/23 | AE3: 28/8/23 | AF3: 29/8/23 | AG3: 30/8/23 | AH3: 31/8/23 | AI3: MONTHLY TOTAL | AJ3: 45170 | AK3: =AJ3+1 | AL3: =AK3+1 | AM3: =AL3+1 | AN3: =AM3+1 | AO3: =AN3+1 | AP3: =AO3+1 | AQ3: =AP3+1 | AR3: =AQ3+1 | ... BM3: =BL3+1 | BN3: Monthly Total | BO3: =AJ3+30 | BP3: =AK3+30 | BQ3: =AL3+30 | BR3: =AM3+30 | BS3: =AN3+30 | BT3: =AO3+30 | BU3: =AP3+30 | BV3: =AQ3+30 | ... CR3: =BM3+30 | CS3: =BO3+30 | CT3: Monthly Total | CU3: =BP3+30 | CV3: =BQ3+30 | CW3: =BR3+30 | CX3: =BS3+30 | CY3: =BT3+30 | CZ3: =BU3+30 | DA3: =BV3+30 | DB3: =BW3+30 | ... DX3: =CS3+30 | DY3: MONTHLY TOTAL | DZ3: 45261 | EA3: =DZ3+1 | EB3: =EA3+1 | EC3: =EB3+1 | ED3: =EC3+1 | EE3: =ED3+1 | EF3: =EE3+1 | EG3: =EF3+1 | EH3: =EG3+1 | ... FD3: =FC3+1 | FE3: MONTHLY TOTAL | FF3: =FD3+1 | FG3: =FF3+1 | FH3: =FG3+1 | FI3: =FH3+1 | FJ3: =FI3+1 | FK3: =FJ3+1 | FL3: =FK3+1 | FM3: =FL3+1 | FN3: =FM3+1 | ... GJ3: =GI3+1 | GK3: MONTHLY TOTAL | GL3: =GJ3+1 | GM3: =GL3+1 | GN3: =GM3+1 | GO3: =GN3+1 | GP3: =GO3+1 | GQ3: =GP3+1 | GR3: =GQ3+1 | GS3: =GR3+1 | GT3: =GS3+1 | ... HN3: =HM3+1 | HO3: MONTHLY TOTAL | HP3: =HN3+1 | HQ3: =HP3+1 | HR3: =HQ3+1 | HS3: =HR3+1 | HT3: =HS3+1 | HU3: =HT3+1 | HV3: =HU3+1 | HW3: =HV3+1 | HX3: =HW3+1 | ... IT3: =IS3+1 | IU3: MONTHLY TOTAL | IV3: 45383 | IW3: =IV3+1 | IX3: =IW3+1 | IY3: =IX3+1 | IZ3: =IY3+1 | JA3: =IZ3+1 | JB3: =JA3+1 | JC3: =JB3+1 | JD3: =JC3+1 | ... JY3: =JX3+1 | JZ3: MONTHLY TOTAL | KA3: =JY3+1 | KB3: =KA3+1 | KC3: =KB3+1 | KD3: =KC3+1 | KE3: =KD3+1 | KF3: =KE3+1 | KG3: =KF3+1 | KH3: =KG3+1 | KI3: =KH3+1 | ... LE3: =LD3+1 | LF3: MONTHLY TOTAL | LG3: 1st june | LH3: 2nd june | LI3: 3rd june | LJ3: 4th june | LK3: 5th june | LL3: 6th june | LM3: 7th june | LN3: 8th june | LO3: 9th june | LP3: 10th june | LQ3: 11th june | LR3: 12th june | LS3: 13th june | LT3: 14th june | LU3: 15th june | LV3: 16th june | LW3: 17th june | LX3: 18th june | LY3: 19th june | LZ3: 20th june | MA3: 21st june | MB3: 22nd june | MC3: 23rd june | MD3: 24th june | ME3: 25th june | MF3: 26th june | MG3: 27th june | MH3: 28th june | MI3: 29th june | MJ3: 30th june | MK3: MONTHLY TOTAL | ML3: 1st july | MM3: 2nd july | MN3: 3rd july | MO3: 4th july | MP3: 5th july | MQ3: 6th july | MR3: 7th july | MS3: 8th july | MT3: 9th july | MU3: 10th july | MV3: 11th july | MW3: 12th july | MX3: 13th july | MY3: 14th july | MZ3: 15th july | NA3: 16th july | NB3: 17th july | NC3: 18th july | ND3: 19th july | NE3: 20th july | NF3: 21st july | NG3: 22nd july | NH3: 23rd july | NI3: 24th july | NJ3: 25th july | NK3: 26th july | NL3: 27th july | NM3: 28th july | NN3: 29th july | NO3: 30th july | NP3: 31st july | NQ3: MONTHLY TOTAL | NR3: 1st aug | NS3: 2nd aug | NT3: 3rd aug | NU3: 4th aug | NV3: 5th aug | NW3: 6th aug | NX3: 7th aug | NY3: 8th aug | NZ3: 9th aug | OA3: 10th aug | OB3: 11th aug | OC3: 12th aug | OD3: 13th aug | OE3: 14th aug | OF3: 15th aug | OG3: 16th aug | OH3: 17th aug | OI3: 18th aug | OJ3: 19th aug | OK3: 20th aug | OL3: 21st aug | OM3: 22nd aug | ON3: 23rd aug | OO3: 24th aug | OP3: 25th aug | OQ3: 26th aug | OR3: 27th aug | OS3: 28th aug | OT3: 29th aug | OU3: 30th aug | OV3: 31st aug | OW3: MONTHLY TOTAL | OX3: 1st sep | OY3: 2nd sep | OZ3: 3rd sep | PA3: 4th sep | PB3: 5th sep | PC3: 6th sep | PD3: 7th sep | PE3: 8th sep | PF3: 9th sep | PG3: 10th sep | PH3: 11th sep | PI3: 12th sep | PJ3: 13th sep | PK3: 14th sep | PL3: 15th sep | PM3: 16th sep | PN3: 17th sep | PO3: 18th sep | PP3: 19th sep | PQ3: 20th sep | PR3: 21st sep | PS3: 22nd sep | PT3: 23rd sep | PU3: 24th sep | PV3: 25th sep | PW3: 26th sep | PX3: 27th sep | PY3: 28th sep | PZ3: 29th sep | QA3: 30th sep | QB3: MONTHLY TOTAL | QC3: 1st 0ct 24 | QD3: 2nd 0ct 24 | QE3: 3rd 0ct 24 | QF3: 4th 0ct 24 | QG3: 5th 0ct 24 | QH3: 6th 0ct 24 | QI3: 7th 0ct 24 | QJ3: 8th 0ct 24 | QK3: 9th 0ct 24 | QL3: 10th 0ct 24 | QM3: 11th 0ct 24 | QN3: 12th 0ct 24 | QO3: 13th 0ct 24 | QP3: 14th 0ct 24 | QQ3: 15th 0ct 24 | QR3: 16th 0ct 24 | QS3: 17th 0ct 24 | QT3: 18th 0ct 24 | QU3: 19th 0ct 24 | QV3: 20th 0ct 24 | QW3: 21st 0ct 24 | QX3: 22nd 0ct 24 | QY3: 23rd 0ct 24 | QZ3: 24th 0ct 24 | RA3: 25th 0ct 24 | RB3: 26th 0ct 24 | RC3: 27th 0ct 24 | RD3: 28th 0ct 24 | RE3: 29th 0ct 24 | RF3: 30th 0ct 24 | RG3: 31st 0ct 24 | RH3: MONTHLY TOTAL | RI3: 1st Nov-2024 | RJ3: 2nd Nov-2024 | RK3: 3rd Nov-2024 | RL3: 4th Nov-2024 | RM3: 5th Nov-2024 | RN3: 6th Nov-2024 | RO3: 7th Nov-2024 | RP3: 8th Nov-2024 | RQ3: 9th Nov-2024 | RR3: 10th Nov-2024 | RS3: 11th Nov-2024 | RT3: 12th Nov-2024 | RU3: 13th Nov-2024 | RV3: 14th Nov-2024 | RW3: 15th Nov-2024 | RX3: 16th Nov-2024 | RY3: 17th Nov-2024 | RZ3: 18th Nov-2024 | SA3: 19th Nov-2024 | SB3: 20th Nov-2024 | SC3: 21st Nov-2024 | SD3: 22nd Nov-2024 | SE3: 23rd Nov-2024 | SF3: 24th Nov-2024 | SG3: 25th Nov-2024 | SH3: 26th Nov-2024 | SI3: 27th Nov-2024 | SJ3: 28th Nov-2024 | SK3: 29th Nov-2024 | SL3: 30th Nov-2024 | SM3: MONTHLY TOTAL | SN3: 1st dec-2024 | SO3: 2nd dec-2024 | SP3: 3rd dec-2024 | SQ3: 4th dec-2024 | SR3: 5th dec-2024 | SS3: 6th dec-2024 | ST3: 7th dec-2024 | SU3: 8th dec-2024 | SV3: 9th dec-2024 | SW3: 10th dec-2024 | SX3: 11th dec-2024 | SY3: 12th dec-2024 | SZ3: 13th dec-2024 | TA3: 14th dec-2024 | TB3: 15th dec-2024 | TC3: 16th dec-2024 | TD3: 17th dec-2024 | TE3: 18th dec-2024 | TF3: 19th dec-2024 | TG3: 20th dec-2024 | TH3: 21st dec-2024 | TI3: 22nd dec-2024 | TJ3: 23rd dec-2024 | TK3: 24th dec-2024 | TL3: 25th dec-2024 | TM3: 26th dec-2024 | TN3: 27th dec-2024 | TO3: 28th dec-2024 | TP3: 29th dec-2024 | TQ3: 30th dec-2024 | TR3: 31st dec-2024 | TS3: MONTHLY TOTAL | TT3: 1st jan-2025 | TU3: 2nd jan -2025 | TV3: 3rd jan -2025 | TW3: 4th jan -2025 | TX3: 5th jan -2025 | TY3: 6th jan -2025 | TZ3: 7th jan -2025 | UA3: 8th jan -2025 | UB3: 9th jan -2025 | UC3: 10th jan -2025 | UD3: 11th jan -2025 | UE3: 12th jan -2025 | UF3: 13th jan -2025 | UG3: 14th jan -2025 | UH3: 15th jan -2025 | UI3: 16th jan -2025 | UJ3: 17th jan -2025 | UK3: 18th jan -2025 | UL3: 19th jan -2025 | UM3: 20th jan -2025 | UN3: 21st jan -2025 | UO3: 22nd jan -2025 | UP3: 23rd jan -2025 | UQ3: 24th jan -2025 | UR3: 25th jan -2025 | US3: 26th jan -2025 | UT3: 27th jan -2025 | UU3: 28th jan -2025 | UV3: 29th jan -2025 | UW3: 30th jan -2025 | UX3: 31st jan -2025 | UY3: MONTHLY TOTAL | UZ3: 1st feb2025 | VA3: 2nd feb2025 | VB3: 3rd feb2025 | VC3: 4th feb2025 | VD3: 5th feb2025 | VE3: 6th feb2025 | VF3: 7th feb2025 | VG3: 8th feb2025 | VH3: 9th feb2025 | VI3: 10th feb2025 | VJ3: 11th feb2025 | VK3: 12th feb2025 | VL3: 13th feb2025 | VM3: 14th feb2025 | VN3: 15th feb2025 | VO3: 16th feb2025 | VP3: 17th feb2025 | VQ3: 18th feb2025 | VR3: 19th feb2025 | VS3: 20th feb2025 | VT3: 21st feb2025 | VU3: 22nd feb2025 | VV3: 23rd feb2025 | VW3: 24th feb2025 | VX3: 25th feb2025 | VY3: 26th feb2025 | VZ3: 27th feb2025 | WA3: 28th feb2025 | WB3: MONTHLY TOTAL | WC3: 1st mar2025 | WD3: 2nd mar2025 | WE3: 3rd mar2025 | WF3: 4th mar2025 | WG3: 5th mar2025 | WH3: 6th mar2025 | WI3: 7th mar2025 | WJ3: 8th mar2025 | WK3: 9th mar2025 | WL3: 10th mar2025 | WM3: 11th mar2025 | WN3: 12th mar2025 | WO3: 13th mar2025 | WP3: 14th mar2025 | WQ3: 15th mar2025 | WR3: 16th mar2025 | WS3: 17th mar2025 | WT3: 18th mar2025 | WU3: 19th mar2025 | WV3: 20th mar2025 | WW3: 21st mar2025 | WX3: 22nd mar2025 | WY3: 23rd mar2025 | WZ3: 24th mar2025 | XA3: 25th mar2025 | XB3: 26th mar2025 | XC3: 27th mar2025 | XD3: 28th mar2025 | XE3: 29th mar2025 | XF3: 30th mar2025 | XG3: 31st mar2025 | XH3: MONTHLY TOTAL | XI3: 1st -apr2025 | XJ3: 2nd -apr2025 | XK3: 3rd -apr2025 | XL3: 4th -apr2025 | XM3: 5th -apr2025 | XN3: 6th -apr2025 | XO3: 7th -apr2025 | XP3: 8th -apr2025 | XQ3: 9th -apr2025 | XR3: 10th -apr2025 | XS3: 11th -apr2025 | XT3: 12th -apr2025 | XU3: 13th -apr2025 | XV3: 14th -apr2025 | XW3: 15th -apr2025 | XX3: 16th -apr2025 | XY3: 17th -apr2025 | XZ3: 18th -apr2025 | YA3: 19th -apr2025 | YB3: 20th -apr2025 | YC3: 21st -apr2025 | YD3: 22nd -apr2025 | YE3: 23rd -apr2025 | YF3: 24th -apr2025 | YG3: 25th -apr2025 | YH3: 26th -apr2025 | YI3: 27th -apr2025 | YJ3: 28th -apr2025 | YK3: 29th -apr2025 | YL3: 30th -apr2025 | YM3: MONTHLY TOTAL | YN3: 1st May-2025 | YO3: 2nd May-2025 | YP3: 3rd May-2025 | YQ3: 4th May-2025 | YR3: 5th May-2025 | YS3: 6th May-2025 | YT3: 7th May-2025 | YU3: 8th May-2025 | YV3: 9th May-2025 | YW3: 10th May-2025 | YX3: 11th May-2025 | YY3: 12th May-2025 | YZ3: 13th May-2025 | ZA3: 14th May-2025 | ZB3: 15th May-2025 | ZC3: 16th May-2025 | ZD3: 17th May-2025 | ZE3: 18th May-2025 | ZF3: 19th May-2025 | ZG3: 20th May-2025 | ZH3: 21st May-2025 | ZI3: 22nd May-2025 | ZJ3: 23rd May-2025 | ZK3: 24th May-2025 | ZL3: 25th May-2025 | ZM3: 26th May-2025 | ZN3: 27th May-2025 | ZO3: 28th May-2025 | ZP3: 29th May-2025 | ZQ3: 30th May-2025 | ZR3: 31st May-2025 | ZS3: MONTHLY TOTAL | ZT3: 1st june | ZU3: 2nd june | ZV3: 3rd june | ZW3: 4th june | ZX3: 5th june | ZY3: 6th june | ZZ3: 7th june | AAA3: 8th june | AAB3: 9th june | AAC3: 10th june | AAD3: 11th june | AAE3: 12th june | AAF3: 13th june | AAG3: 14th june | AAH3: 15th june | AAI3: 16th june | AAJ3: 17th june | AAK3: 18th june | AAL3: 19th june | AAM3: 20th june | AAN3: 21st june | AAO3: 22nd june | AAP3: 23rd june | AAQ3: 24th june | AAR3: 25th june | AAS3: 26th june | AAT3: 27th june | AAU3: 28th june | AAV3: 29th june | AAW3: 30th june | AAX3: MONTHLY TOTAL | AAY3: 1st -july | AAZ3: 2nd -july | ABA3: 3rd -july | ABB3: 4th -july | ABC3: 5th -july | ABD3: 6th -july | ABE3: 7th -july | ABF3: 8th -july | ABG3: 9th -july | ABH3: 10th -july | ABI3: 11th -july | ABJ3: 12th -july | ABK3: 13th -july | ABL3: 14th -july | ABM3: 15th -july | ABN3: 16th -july | ABO3: 17th -july | ABP3: 18th -july | ABQ3: 19th -july | ABR3: 20th -july | ABS3: 21st -july | ABT3: 22nd -july | ABU3: 23rd -july | ABV3: 24th -july | ABW3: 25th -july | ABX3: 26th -july | ABY3: 27th -july | ABZ3: 28th -july | ACA3: 29th -july | ACB3: 30th -july | ACC3: 31st -july | ACD3: MONTHLY TOTAL | ACE3: 1st -aug25 | ACF3: 2nd -aug | ACG3: 3rd -aug | ACH3: 4th -aug | ACI3: 5th -aug | ACJ3: 6th -aug | ACK3: 7th -aug | ACL3: 8th -aug | ACM3: 9th -aug | ACN3: 10th -aug | ACO3: 11th -aug | ACP3: 12th -aug | ACQ3: 13th -aug | ACR3: 14th -aug | ACS3: 15th -aug | ACT3: 16th -aug | ACU3: 17th -aug | ACV3: 18th -aug | ACW3: 19th -aug | ACX3: 20th -aug | ACY3: 21st -aug | ACZ3: 22nd -aug | ADA3: 23rd -aug | ADB3: 24th -aug | ADC3: 25th -aug | ADD3: 26th -aug | ADE3: 27th -aug | ADF3: 28th -aug | ADG3: 29th -aug | ADH3: 30th -aug | ADI3: 31st -aug | ADJ3: MONTHLY TOTAL | ADK3: 1st -sep 25 | ADL3: 2nd -sep 25 | ADM3: 3rd -sep 25 | ADN3: 4th -sep 25 | ADO3: 5th -sep 25 | ADP3: 6th -sep 25 | ADQ3: 7th -sep 25 | ADR3: 8th -sep 25 | ADS3: 9th -sep 25 | ADT3: 10th -sep 25 | ADU3: 11th -sep 25 | ADV3: 12th -sep 25 | ADW3: 13th -sep 25 | ADX3: 14th -sep 25 | ADY3: 15th -sep 25 | ADZ3: 16th -sep 25 | AEA3: 17th -sep 25 | AEB3: 18th -sep 25 | AEC3: 19th -sep 25 | AED3: 20th -sep 25 | AEE3: 21st -sep 25 | AEF3: 22nd -sep 25 | AEG3: 23rd -sep 25 | AEH3: 24th -sep 25 | AEI3: 25th -sep 25 | AEJ3: 26th -sep 25 | AEK3: 27th -sep 25 | AEL3: 28th -sep 25 | AEM3: 29th -sep 25 | AEN3: 30th -sep 25 | AEO3: MONTHLY TOTAL | AEP3: 1st -oct25 | AEQ3: 2nd -oct25 | AER3: 3rd -oct25 | AES3: 4th -oct25 | AET3: 5th -oct25 | AEU3: 6th -oct25 | AEV3: 7th -oct25 | AEW3: 8th -oct25 | AEX3: 9th -oct25 | AEY3: 10th -oct25 | AEZ3: 11th -oct25 | AFA3: 12th -oct25 | AFB3: 13th -oct25 | AFC3: 14th -oct25 | AFD3: 15th -oct25 | AFE3: 16th -oct25 | AFF3: 17th -oct25 | AFG3: 18th -oct25 | AFH3: 19th -oct25 | AFI3: 20th -oct25 | AFJ3: 21st -oct25 | AFK3: 22nd -oct25 | AFL3: 23rd -oct25 | AFM3: 24th -oct25 | AFN3: 25th -oct25 | AFO3: 26th -oct25 | AFP3: 27th -oct25 | AFQ3: 28th -oct25 | AFR3: 29th -oct25 | AFS3: 30th -oct25 | AFT3: 31st -oct25 | AFU3: MONTHLY TOTAL | AFV3: 1st -nov25 | AFW3: 2nd -nov25 | AFX3: 3rd -nov25 | AFY3: 4th -nov25 | AFZ3: 5th -nov25 | AGA3: 6th -nov25 | AGB3: 7th -nov25 | AGC3: 8th -nov25 | AGD3: 9th -nov25 | AGE3: 10th -nov25 | AGF3: 11th -nov25 | AGG3: 12th -nov25 | AGH3: 13th -nov25 | AGI3: 14th -nov25 | AGJ3: 15th -nov25 | AGK3: 16th -nov25 | AGL3: 17th -nov25 | AGM3: 18th -nov25 | AGN3: 19th -nov25 | AGO3: 20th -nov25 | AGP3: 21st -nov25 | AGQ3: 22nd -nov25 | AGR3: 23rd -nov25 | AGS3: 24th -nov25 | AGT3: 25th -nov25 | AGU3: 26th -nov25 | AGV3: 27th -nov25 | AGW3: 28th -nov25 | AGX3: 29th -nov25 | AGY3: 30th -nov25 | AGZ3: MONTHLY TOTAL | AHA3: 1st -dec25 | AHB3: 2nd -dec25 | AHC3: 3rd -dec25 | AHD3: 4th -dec25 | AHE3: 5th -dec25 | AHF3: 6th -dec25 | AHG3: 7th -dec25 | AHH3: 8th -dec25 | AHI3: 9th -dec25 | AHJ3: 10th -dec25 | AHK3: 11th -dec25 | AHL3: 12th -dec25 | AHM3: 13th -dec25 | AHN3: 14th -dec25 | AHO3: 15th -dec25 | AHP3: 16th -dec25 | AHQ3: 17th -dec25 | AHR3: 18th -dec25 | AHS3: 19th -dec25 | AHT3: 20th -dec25 | AHU3: 21st -dec25 | AHV3: 22nd -dec25 | AHW3: 23rd -dec25 | AHX3: 24th -dec25 | AHY3: 25th -dec25 | AHZ3: 26th -dec25 | AIA3: 27th -dec25 | AIB3: 28th -dec25 | AIC3: 29th -dec25 | AID3: 30th -dec25 | AIE3: 31st -dec25 | AIF3: MONTHLY TOTAL | AIG3: 1st - jan26 | AIH3: 2nd - jan26 | AII3: 3rd - jan26 | AIJ3: 4th - jan26 | AIK3: 5th - jan26 | AIL3: 6th - jan26 | AIM3: 7th - jan26 | AIN3: 8th - jan26 | AIO3: 9th - jan26 | AIP3: 10th - jan26 | AIQ3: 11th - jan26 | AIR3: 12th - jan26 | AIS3: 13th - jan26 | AIT3: 14th - jan26 | AIU3: 15th - jan26 | AIV3: 16th - jan26 | AIW3: 17th - jan26 | AIX3: 18th - jan26 | AIY3: 19th - jan26 | AIZ3: 20th - jan26 | AJA3: 21st - jan26 | AJB3: 22nd - jan26 | AJC3: 23rd - jan26 | AJD3: 24th - jan26 | AJE3: 25th - jan26 | AJF3: 26th - jan26 | AJG3: 27th - jan26 | AJH3: 28th - jan26 | AJI3: 29th - jan26 | AJJ3: 30th - jan26 | AJK3: 31st - jan26 | AJL3: MONTHLY TOTAL | AJM3: 1st -feb2026 | AJN3: 2nd -feb2026 | AJO3: 3rd -feb2026 | AJP3: 4th -feb2026 | AJQ3: 5th -feb2026 | AJR3: 6th -feb2026 | AJS3: 7th -feb2026 | AJT3: 8th -feb2026 | AJU3: 9th -feb2026 | AJV3: 10th -feb2026 | AJW3: 11th -feb2026 | AJX3: 12th -feb2026 | AJY3: 13th -feb2026 | AJZ3: 14th -feb2026 | AKA3: 15th -feb2026 | AKB3: 16th -feb2026 | AKC3: 17th -feb2026 | AKD3: 18th -feb2026 | AKE3: 19th -feb2026 | AKF3: 20th -feb2026 | AKG3: 21st -feb2026 | AKH3: 22nd -feb2026 | AKI3: 23rd -feb2026 | AKJ3: 24th -feb2026 | AKK3: 25th -feb2026 | AKL3: 26th -feb2026 | AKM3: 27th -feb2026 | AKN3: 28th -feb2026 | AKO3: MONTHLY TOTAL | AKP3: 1st -mar2026 | AKQ3: 2nd -mar2026 | AKR3: 3rd -mar2026 | AKS3: 4th -mar2026 | AKT3: 5th -mar2026 | AKU3: 6th -mar2026 | AKV3: 7th -mar2026 | AKW3: 8th -mar2026 | AKX3: 9th -mar2026 | AKY3: 10th -mar2026 | AKZ3: 11th -mar2026 | ALA3: 12th -mar2026 | ALB3: 13th -mar2026 | ALC3: 14th -mar2026 | ALD3: 15th -mar2026 | ALE3: 16th -mar2026 | ALF3: 17th -mar2026 | ALG3: 18th -mar2026 | ALH3: 19th -mar2026 | ALI3: 20th -mar2026 | ALJ3: 21st -mar2026 | ALK3: 22nd -mar2026 | ALL3: 23rd -mar2026 | ALM3: 24th -mar2026 | ALN3: 25th -mar2026 | ALO3: 26th -mar2026 | ALP3: 27th -mar2026 | ALQ3: 28th -mar2026 | ALR3: 29th -mar2026 | ALS3: 30th -mar2026 | ALT3: 31st -mar2026 | ALU3: MONTHLY TOTAL | ALV3: 1st -apr2026 | ALW3: 2nd -apr2026 | ALX3: 3rd -apr2026 | ALY3: 4th -apr2026 | ALZ3: 5th -apr2026 | AMA3: 6th -apr2026 | AMB3: 7th -apr2026 | AMC3: 8th -apr2026 | AMD3: 9th -apr2026 | AME3: 10th -apr2026 | AMF3: 11th -apr2026 | AMG3: 12th -apr2026 | AMH3: 13th -apr2026 | AMI3: 14th -apr2026 | AMJ3: 15th -apr2026 | AMK3: 16th -apr2026 | AML3: 17th -apr2026 | AMM3: 18th -apr2026 | AMN3: 19th -apr2026 | AMO3: 20th -apr2026 | AMP3: 21st -apr2026 | AMQ3: 22nd -apr2026 | AMR3: 23rd -apr2026 | AMS3: 24th -apr2026 | AMT3: 25th -apr2026 | AMU3: 26th -apr2026 | AMV3: 27th -apr2026 | AMW3: 28th -apr2026 | AMX3: 29th -apr2026 | AMY3: 30th -apr2026 | AMZ3: MONTHLY TOTAL | ANA3: 1st -May2026 | ANB3: 2nd -May2026 | ANC3: 3rd -May2026 | AND3: 4th -May2026 | ANE3: 5th -May2026 | ANF3: 6th -May2026 | ANG3: 7th -May2026 | ANH3: 8th -May2026 | ANI3: 9th -May2026 | ANJ3: 10th -May2026 | ANK3: 11th -May2026 | ANL3: 12th -May2026 | ANM3: 13th -May2026 | ANN3: 14th -May2026 | ANO3: 15th -May2026 | ANP3: 16th -May2026 | ANQ3: 17th -May2026 | ANR3: 18th -May2026 | ANS3: 19th -May2026 | ANT3: 20th -May2026 | ANU3: 21st -May2026 | ANV3: 22nd -May2026 | ANW3: 23rd -May2026 | ANX3: 24th -May2026 | ANY3: 25th -May2026 | ANZ3: 26th -May2026 | AOA3: 27th -May2026 | AOB3: 28th -May2026 | AOC3: 29th -May2026 | AOD3: 30th -May2026 | AOE3: 31st -May2026 | AOF3: 10th -June2026
A4: PMS | B4: PMS 1 | C4: OPENING | D4: 906274.01 | E4: =D5 | F4: =E5 | G4: =F5 | H4: =G5 | I4: =H5 | J4: =I5 | K4: =J5 | L4: =K5 | ... AH4: =AG5 | AJ4: =AH5 | AK4: =AJ5 | AL4: =AK5 | AM4: =AL5 | AN4: =AM5 | AO4: =AN5 | AP4: =AO5 | AQ4: =AP5 | AR4: =AQ5 | ... BM4: =BL5 | BO4: =BM5 | BP4: =BO5 | BQ4: =BP5 | BR4: =BQ5 | BS4: =BR5 | BT4: =BS5 | BU4: =BT5 | BV4: =BU5 | BW4: =BV5 | ... CS4: =CR5 | CU4: =CS5 | CV4: =CU5 | CW4: =CV5 | CX4: =CW5 | CY4: =CX5 | CZ4: =CY5 | DA4: =CZ5 | DB4: =DA5 | DC4: =DB5 | ... DX4: =DW5 | DZ4: =DX5 | EA4: =DZ5 | EB4: =EA5 | EC4: =EB5 | ED4: =EC5 | EE4: =ED5 | EF4: =EE5 | EG4: =EF5 | EH4: =EG5 | ... FD4: =FC5 | FF4: =FD5 | FG4: =FF5 | FH4: =FG5 | FI4: =FH5 | FJ4: =FI5 | FK4: =FJ5 | FL4: =FK5 | FM4: =FL5 | FN4: =FM5 | ... GJ4: =GI5 | GK4: MONTHLY TOTAL | GL4: =GJ5 | GM4: =GL5 | GN4: =GM5 | GO4: =GN5 | GP4: =GO5 | GQ4: =GP5 | GR4: =GQ5 | GS4: =GR5 | GT4: =GS5 | ... HN4: =HM5 | HO4: MONTHLY TOTAL | HP4: =HN5 | HQ4: =HP5 | HR4: =HQ5 | HS4: =HR5 | HT4: =HS5 | HU4: =HT5 | HV4: =HU5 | HW4: =HV5 | HX4: =HW5 | ... IT4: =IS5 | IU4: MONTHLY TOTAL | IV4: =IT5 | IW4: =IV5 | IX4: =IW5 | IY4: =IX5 | IZ4: =IY5 | JA4: =IZ5 | JB4: =JA5 | JC4: =JB5 | JD4: =JC5 | ... JY4: =JX5 | KA4: =JY5 | KB4: =KA5 | KC4: =KB5 | KD4: =KC5 | KE4: =KD5 | KF4: =KE5 | KG4: =KF5 | KH4: =KG5 | KI4: =KH5 | ... LE4: =LD5 | LG4: =LE5 | LH4: =LG5 | LI4: =LH5 | LJ4: =LI5 | LK4: =LJ5 | LL4: =LK5 | LM4: =LL5 | LN4: =LM5 | LO4: =LN5 | ... MJ4: =MI5 | ML4: =MJ5 | MM4: =ML5 | MN4: =MM5 | MO4: =MN5 | MP4: =MO5 | MQ4: =MP5 | MR4: =MQ5 | MS4: =MR5 | MT4: =MS5 | ... NP4: =NO5 | NR4: =NP5 | NS4: =NR5 | NT4: =NS5 | NU4: =NT5 | NV4: =NU5 | NW4: =NV5 | NX4: =NW5 | NY4: =NX5 | NZ4: =NY5 | ... OV4: =OU5 | OX4: =OV5 | OY4: =OX5 | OZ4: =OY5 | PA4: =OZ5 | PB4: =PA5 | PC4: =PB5 | PD4: =PC5 | PE4: =PD5 | PF4: =PE5 | ... QA4: =PZ5 | QC4: =QA5 | QD4: =QC5 | QE4: =QD5 | QF4: =QE5 | QG4: =QF5 | QH4: =QG5 | QI4: =QH5 | QJ4: =QI5 | QK4: =QJ5 | ... RG4: =RF5 | RI4: =RG5 | RJ4: =RI5 | RK4: =RJ5 | RL4: =RK5 | RM4: =RL5 | RN4: =RM5 | RO4: =RN5 | RP4: =RO5 | RQ4: =RP5 | ... SL4: =SK5 | SN4: =SL5 | SO4: =SN5 | SP4: =SO5 | SQ4: =SP5 | SR4: =SQ5 | SS4: =SR5 | ST4: =SS5 | SU4: =ST5 | SV4: =SU5 | ... TR4: =TQ5 | TT4: =TR5 | TU4: =TT5 | TV4: =TU5 | TW4: =TV5 | TX4: =TW5 | TY4: =TX5 | TZ4: =TY5 | UA4: =TZ5 | UB4: =UA5 | ... UX4: =UW5 | UZ4: =UX5 | VA4: =UZ5 | VB4: =VA5 | VC4: =VB5 | VD4: =VC5 | VE4: =VD5 | VF4: =VE5 | VG4: =VF5 | VH4: =VG5 | ... WA4: =VZ5 | WC4: =WA5 | WD4: =WC5 | WE4: =WD5 | WF4: =WE5 | WG4: =WF5 | WH4: =WG5 | WI4: =WH5 | WJ4: =WI5 | WK4: =WJ5 | ... XG4: =XF5 | XI4: =XG5 | XJ4: =XI5 | XK4: =XJ5 | XL4: =XK5 | XM4: =XL5 | XN4: =XM5 | XO4: =XN5 | XP4: =XO5 | XQ4: =XP5 | ... YL4: =YK5 | YN4: =YL5 | YO4: =YN5 | YP4: =YO5 | YQ4: =YP5 | YR4: =YQ5 | YS4: =YR5 | YT4: =YS5 | YU4: =YT5 | YV4: =YU5 | ... ZR4: =ZQ5 | ZT4: =ZR5 | ZU4: =ZT5 | ZV4: =ZU5 | ZW4: =ZV5 | ZX4: =ZW5 | ZY4: =ZX5 | ZZ4: =ZY5 | AAA4: =ZZ5 | AAB4: =AAA5 | ... AAW4: =AAV5 | AAY4: =AAW5 | AAZ4: =AAY5 | ABA4: =AAZ5 | ABB4: =ABA5 | ABC4: =ABB5 | ABD4: =ABC5 | ABE4: =ABD5 | ABF4: =ABE5 | ABG4: =ABF5 | ... ACC4: =ACB5 | ACE4: =ACC5 | ACF4: =ACE5 | ACG4: =ACF5 | ACH4: =ACG5 | ACI4: =ACH5 | ACJ4: =ACI5 | ACK4: =ACJ5 | ACL4: =ACK5 | ACM4: =ACL5 | ... ADI4: =ADH5 | ADK4: =ADI5 | ADL4: =ADK5 | ADM4: =ADL5 | ADN4: =ADM5 | ADO4: =ADN5 | ADP4: =ADO5 | ADQ4: =ADP5 | ADR4: =ADQ5 | ADS4: =ADR5 | ... AEN4: =AEM5 | AEP4: =AEN5 | AEQ4: =AEP5 | AER4: =AEQ5 | AES4: =AER5 | AET4: =AES5 | AEU4: =AET5 | AEV4: =AEU5 | AEW4: =AEV5 | AEX4: =AEW5 | ... AFT4: =AFS5 | AFV4: =AFT5 | AFW4: =AFV5 | AFX4: =AFW5 | AFY4: =AFX5 | AFZ4: =AFY5 | AGA4: =AFZ5 | AGB4: =AGA5 | AGC4: =AGB5 | AGD4: =AGC5 | ... AGY4: =AGX5 | AHA4: =AGY5 | AHB4: =AHA5 | AHC4: =AHB5 | AHD4: =AHC5 | AHE4: =AHD5 | AHF4: =AHE5 | AHG4: =AHF5 | AHH4: =AHG5 | AHI4: =AHH5 | ... AIE4: =AID5 | AIG4: =AIE5 | AIH4: =AIG5 | AII4: =AIH5 | AIJ4: =AII5 | AIK4: =AIJ5 | AIL4: =AIK5 | AIM4: =AIL5 | AIN4: =AIM5 | AIO4: =AIN5 | ... AJK4: =AJJ5 | AJM4: =AJK5 | AJN4: =AJM5 | AJO4: =AJN5 | AJP4: =AJO5 | AJQ4: =AJP5 | AJR4: =AJQ5 | AJS4: =AJR5 | AJT4: =AJS5 | AJU4: =AJT5 | ... AKN4: =AKM5 | AKP4: =AKN5 | AKQ4: =AKP5 | AKR4: =AKQ5 | AKS4: =AKR5 | AKT4: =AKS5 | AKU4: =AKT5 | AKV4: =AKU5 | AKW4: =AKV5 | AKX4: =AKW5 | ... ALT4: =ALS5 | ALV4: =ALT5 | ALW4: =ALV5 | ALX4: =ALW5 | ALY4: =ALX5 | ALZ4: =ALY5 | AMA4: =ALZ5 | AMB4: =AMA5 | AMC4: =AMB5 | AMD4: =AMC5 | ... AMY4: =AMX5 | ANA4: =AMY5 | ANB4: =ANA5 | ANC4: =ANB5 | AND4: =ANC5 | ANE4: =AND5 | ANF4: =ANE5 | ANG4: =ANF5 | ANH4: =ANG5 | ANI4: =ANH5 | ... AOC4: =AOB5 | AOD4: 1692332.2 | AOE4: 1692332.2 | AOF4: 1696506.2
C5: CLOSING | D5: 907256.36 | E5: 908068.85 | F5: 909104.49 | G5: 910384.29 | H5: 911385.74 | I5: 912644.04 | J5: 913712.84 | K5: 914547.71 | L5: 915395.77 | M5: 916317 | N5: 917302.66 | O5: 918492.76 | P5: 919546.2 | Q5: 920620.88 | R5: 921685.27 | S5: 922665.67 | T5: 923703.77 | U5: 924812.21 | V5: 925977.47 | W5: 926937.64 | X5: 927664.69 | Y5: 928482.13 | Z5: 929366.72 | AA5: 930211.63 | AB5: 931558.71 | AC5: 932696.74 | AD5: 933746.19 | AE5: 934597 | AF5: 935497.54 | AG5: 936535.77 | AH5: 937530.79 | AJ5: 938749.92 | AK5: 939940.94 | AL5: 940865.65 | AM5: 941852.24 | AN5: 942823.64 | AO5: 943615.39 | AP5: 944808.95 | AQ5: 945946.39 | AR5: 947032.88 | AS5: 947889.36 | AT5: 948715.19 | AU5: 949408.5 | AV5: 950396.3 | AW5: 951221.41 | AX5: 952193.76 | AY5: 953175.65 | AZ5: 953900.06 | BA5: 954963.07 | BB5: 955684.43 | BC5: 956578.8 | BD5: 957498.78 | BE5: 958472.99 | BF5: 959458.24 | BG5: 960386.24 | BH5: 961264.4 | BI5: 961985.71 | BJ5: 962928.18 | BK5: 963729.86 | BL5: 964598.4 | BM5: 965561.07 | BO5: 966414.9 | BP5: 967216.62 | BQ5: 968053.16 | BR5: 968888.33 | BS5: 969744.6 | BT5: 970547.94 | BU5: 971309.6 | BV5: 972151.97 | BW5: 973006.65 | BX5: 973806.62 | BY5: 974519.41 | BZ5: 975328.4 | CA5: 976268.45 | CB5: 977141.72 | CC5: 977953.8 | CD5: 978778.31 | CE5: 979609 | CF5: 980441.91 | CG5: 981197.13 | CH5: 982081.87 | CI5: 982774.49 | CJ5: 983699.74 | CK5: 984413.02 | CL5: 985173.34 | CM5: 985999.33 | CN5: 986811.3 | CO5: 987728.1 | CP5: 988561.5 | CQ5: 989356.23 | CR5: 990199.64 | CS5: 990943.46 | CU5: 991763.45 | CV5: 992570 | CW5: 993461.73 | CX5: 994413.55 | CY5: 995545.69 | CZ5: 996445.19 | DA5: 997250.35 | DB5: 997900.3 | DC5: 998724.3 | DD5: 999632.38 | DE5: 1000484.1 | DF5: 1001218.2 | DG5: 1002006.1 | DH5: 1002903.4 | DI5: 1003651.4 | DJ5: 1004201.9 | DK5: 1004779.6 | DL5: 1005571.5 | DM5: 1006285.3 | DN5: 1007109.3 | DO5: 1007750.4 | DP5: 1008548.1 | DQ5: 1009432.6 | DR5: 1010248.9 | DS5: 1011114.8 | DT5: 1011886.4 | DU5: 1012487.2 | DV5: 1013147 | DW5: 1013670.7 | DX5: 1014373.5 | DZ5: 1015286.6 | EA5: 1015993.6 | EB5: 1016633 | EC5: 1017254.9 | ED5: 1017940.7 | EE5: 1018636.5 | EF5: 1019346.8 | EG5: 1020246.4 | EH5: 1021152.9 | EI5: 1021981.7 | EJ5: 1022719.1 | EK5: 1023452.3 | EL5: 1024253.6 | EM5: 1025036 | EN5: 1025877.4 | EO5: 1026927 | EP5: 1027799.2 | EQ5: 1028704.4 | ER5: 1029392 | ES5: 1030225.2 | ET5: 1031150.3 | EU5: 1032270.3 | EV5: 1033341.5 | EW5: 1034436.3 | EX5: 1035202 | EY5: 1035857.1 | EZ5: 1036542.1 | FA5: 1037187.4 | FB5: 1038025.2 | FC5: 1038820.4 | FD5: 1039685.8 | FF5: 1040471.8 | FG5: 1041268.4 | FH5: 1041960.1 | FI5: 1042907.4 | FJ5: 1043692 | FK5: 1044553.1 | FL5: 1045334.8 | FM5: 1046130.5 | FN5: 1046883 | FO5: 1047657.1 | FP5: 1048497.3 | FQ5: 1049375.5 | FR5: 1050201.9 | FS5: 1050855.6 | FT5: 1051523.9 | FU5: 1052298.1 | FV5: 1052866.5 | FW5: 1053619.4 | FX5: 1054374.4 | FY5: 1055272.1 | FZ5: 1056022.8 | GA5: 1056686.4 | GB5: 1057540.6 | GC5: 1058279.8 | GD5: 1059208.8 | GE5: 1060048.9 | GF5: 1060633.4 | GG5: 1061350.9 | GH5: 1062225 | GI5: 1062933.3 | GJ5: 1063622.9 | GL5: 1064470.5 | GM5: 1065333.6 | GN5: 1066493.4 | GO5: 1067357.7 | GP5: 1068212.6 | GQ5: 1069183.5 | GR5: 1070099.1 | GS5: 1070819.1 | GT5: 1071860.2 | GU5: 1072555.7 | GV5: 1073303 | GW5: 1074294.9 | GX5: 1075239.6 | GY5: 1076027.1 | GZ5: 1076861.8 | HA5: 1077642.8 | HB5: 1078578.4 | HC5: 1079419.3 | HD5: 1080168.9 | HE5: 1080963.8 | HF5: 1081845.6 | HG5: 1082533.4 | HH5: 1083135 | HI5: 1083935.6 | HJ5: 1084604.1 | HK5: 1085550.8 | HL5: 1086216.5 | HM5: 1087072.9 | HN5: 1087999.9 | HP5: 1088958.3 | HQ5: 1089891.2 | HR5: 1090865.3 | HS5: 1091850.1 | HT5: 1092757.5 | HU5: 1093542.5 | HV5: 1094532.8 | HW5: 1095466.6 | HX5: 1096218.4 | HY5: 1097041.9 | HZ5: 1097858.6 | IA5: 1098508.7 | IB5: 1099263.2 | IC5: 1099863 | ID5: 1100659.8 | IE5: 1101431.1 | IF5: 1102136.2 | IG5: 1102947 | IH5: 1103765 | II5: 1104565.3 | IJ5: 1105217.1 | IK5: 1106084.6 | IL5: 1106812.3 | IM5: 1107615.3 | IN5: 1108498.8 | IO5: 1109221.9 | IP5: 1110050.5 | IQ5: 1110924 | IR5: 1111642.2 | IS5: 1112550.6 | IT5: 1113166.8 | IV5: 1113854.4 | IW5: 1114684.3 | IX5: 1115334.8 | IY5: 1115999.4 | IZ5: 1116784.8 | JA5: 1117750.3 | JB5: 1118519.7 | JC5: 1119326.3 | JD5: 1120046.3 | JE5: 1120713.9 | JF5: 1121295.3 | JG5: 1122093.1 | JH5: 1122866.1 | JI5: 1123422.4 | JJ5: 1124277.7 | JK5: 1124904 | JL5: 1125543.8 | JM5: 1126076.8 | JN5: 1126772.8 | JO5: 1127383.3 | JP5: 1128083.9 | JQ5: 1128891.7 | JR5: 1129548.8 | JS5: 1130314.4 | JT5: 1131001 | JU5: 1131783.2 | JV5: 1132805.5 | JW5: 1133628.8 | JX5: 1134444.8 | JY5: 1135056.7 | KA5: 1135957 | KB5: 1136654.5 | KC5: 1137375.6 | KD5: 1138282.5 | KE5: 1139070.5 | KF5: 1139844.6 | KG5: 1140620.5 | KH5: 1141220.2 | KI5: 1141917.7 | KJ5: 1142739.2 | KK5: 1143631.5 | KL5: 1144320.9 | KM5: 1145191.3 | KN5: 1145868.3 | KO5: 1146452.5 | KP5: 1147303.2 | KQ5: 1148055.3 | KR5: 1148915.6 | KS5: 1149693.1 | KT5: 1150529.5 | KU5: 1151155.9 | KV5: 1151855 | KW5: 1152639.5 | KX5: 1153464.1 | KY5: 1154279.7 | KZ5: 1155010.3 | LA5: 1155724.1 | LB5: 1156535.4 | LC5: 1157259.8 | LD5: 1158024.1 | LE5: 1158992 | LG5: 1159784.4 | LH5: 1160364.9 | LI5: 1161248.7 | LJ5: 1162145.9 | LK5: 1162876.8 | LL5: 1163637.4 | LM5: 1164406.9 | LN5: 1165439.5 | LO5: 1166463.1 | LP5: 1167341.9 | LQ5: 1168165.3 | LR5: 1168962.4 | LS5: 1169906.9 | LT5: 1170668.9 | LU5: 1171691.4 | LV5: 1172506.5 | LW5: 1173335.5 | LX5: 1174088.6 | LY5: 1174841.2 | LZ5: 1175577.9 | MA5: 1176399.3 | MB5: 1177123 | MC5: 1177921.7 | MD5: 1178945.2 | ME5: 1179649.1 | MF5: 1180494.2 | MG5: 1181070.9 | MH5: 1181947.4 | MI5: 1182762.3 | MJ5: 1183692.2 | ML5: 1184703.3 | MM5: 1185513.9 | MN5: 1186268.2 | MO5: 1186915.1 | MP5: 1187869.6 | MQ5: 1188770.8 | MR5: 1189546.6 | MS5: 1190400.8 | MT5: 1191200.2 | MU5: 1191923.7 | MV5: 1192703.2 | MW5: 1193429.5 | MX5: 1194323.7 | MY5: 1195022.9 | MZ5: 1195785.8 | NA5: 1196536.2 | NB5: 1197228.8 | NC5: 1198071.9 | ND5: 1198870.4 | NE5: 1199777.5 | NF5: 1200622.7 | NG5: 1201406 | NH5: 1202087.1 | NI5: 1202752 | NJ5: 1203555.2 | NK5: 1204310.5 | NL5: 1205358.3 | NM5: 1205998.7 | NN5: 1206942.7 | NO5: 1207754.9 | NP5: 1208405.6 | NR5: 1209225.6 | NS5: 1210007.5 | NT5: 1210931.9 | NU5: 1211766 | NV5: 1212528.6 | NW5: 1213450 | NX5: 1214213.9 | NY5: 1215050.4 | NZ5: 1215970.4 | OA5: 1216910.3 | OB5: 1217508.7 | OC5: 1218349.7 | OD5: 1219155.3 | OE5: 1220009.5 | OF5: 1220729.9 | OG5: 1221501.9 | OH5: 1222466.5 | OI5: 1223269.7 | OJ5: 1224060.8 | OK5: 1224798.4 | OL5: 1225497 | OM5: 1226345.8 | ON5: 1227074.1 | OO5: 1227967.3 | OP5: 1228550 | OQ5: 1229261.1 | OR5: 1230047.3 | OS5: 1230704.5 | OT5: 1231529.4 | OU5: 1232313.5 | OV5: 1233154.5 | OX5: 1233865.3 | OY5: 1234672.6 | OZ5: 1235408.9 | PA5: 1236157.9 | PB5: 1236827.2 | PC5: 1237607.3 | PD5: 1238300.3 | PE5: 1239057.1 | PF5: 1240000.3 | PG5: 1240859 | PH5: 1241560.4 | PI5: 1242236.3 | PJ5: 1243133.8 | PK5: 1243925.3 | PL5: 1244549 | PM5: 1245454.9 | PN5: 1246331.3 | PO5: 1247000.3 | PP5: 1247549.2 | PQ5: 1248268.1 | PR5: 1248880 | PS5: 1249497.1 | PT5: 1250214.5 | PU5: 1250943 | PV5: 1251623.1 | PW5: 1252194.2 | PX5: 1252915.3 | PY5: 1253595 | PZ5: 1253947.1 | QA5: 1254683.6 | QC5: 1255375.1 | QD5: 1255971.4 | QE5: 1256654.8 | QF5: 1257471 | QG5: 1258315 | QH5: 1258980.7 | QI5: 1259907.8 | QJ5: 1260625 | QK5: 1261369.9 | QL5: 1262063.1 | QM5: 1262985.3 | QN5: 1263852.8 | QO5: 1264640.8 | QP5: 1265550.1 | QQ5: 1266235.9 | QR5: 1266871.7 | QS5: 1267623.9 | QT5: 1268521.7 | QU5: 1269212.3 | QV5: 1270014.2 | QW5: 1270658.9 | QX5: 1271340.8 | QY5: 1272058 | QZ5: 1272718.8 | RA5: 1273533.9 | RB5: 1274327.3 | RC5: 1274947.4 | RD5: 1275628.7 | RE5: 1276246.6 | RF5: 1276794 | RG5: 1277512.4 | RI5: 1278303.1 | RJ5: 1279124 | RK5: 1279829.9 | RL5: 1280602.8 | RM5: 1281259.4 | RN5: 1281853.7 | RO5: 1282393.6 | RP5: 1283191.6 | RQ5: 1283844.1 | RR5: 1284639.1 | RS5: 1285336.9 | RT5: 1285988.6 | RU5: 1286675.6 | RV5: 1287192.9 | RW5: 1287834.6 | RX5: 1288546.7 | RY5: 1289170 | RZ5: 1289784.7 | SA5: 1290602 | SB5: 1291283.3 | SC5: 1291876.3 | SD5: 1292653.5 | SE5: 1293472.1 | SF5: 1294163.6 | SG5: 1294981.9 | SH5: 1295633.9 | SI5: 1296390.2 | SJ5: 1297111.3 | SK5: 1297818.2 | SL5: 1298686.3 | SN5: 1299350.8 | SO5: 1300230.1 | SP5: 1300920.4 | SQ5: 1301689 | SR5: 1302337.1 | SS5: 1303089.1 | ST5: 1304173.8 | SU5: 1304926.5 | SV5: 1305695.8 | SW5: 1306365.2 | SX5: 1307127.8 | SY5: 1307873.4 | SZ5: 1308749.9 | TA5: 1309575.5 | TB5: 1310259.8 | TC5: 1311034.3 | TD5: 1311861.4 | TE5: 1312676.1 | TF5: 1313483.4 | TG5: 1314309.3 | TH5: 1315269.6 | TI5: 1316228.1 | TJ5: 1317170.8 | TK5: 1318032 | TL5: 1318707 | TM5: 1319283.5 | TN5: 1319912.2 | TO5: 1320706.7 | TP5: 1321225.9 | TQ5: 1321839.3 | TR5: 1322665.5 | TT5: 1323334.8 | TU5: 1324006.7 | TV5: 1324676.9 | TW5: 1325347.7 | TX5: 1325977.8 | TY5: 1326741.3 | TZ5: 1327531.8 | UA5: 1328215.7 | UB5: 1328861.3 | UC5: 1329520.2 | UD5: 1330290.3 | UE5: 1330903 | UF5: 1331630.4 | UG5: 1332449.8 | UH5: 1333280.8 | UI5: 1334095.7 | UJ5: 1334924.5 | UK5: 1335639.9 | UL5: 1336268 | UM5: 1337003.7 | UN5: 1337646.7 | UO5: 1338441.2 | UP5: 1339194.5 | UQ5: 1340118.6 | UR5: 1340800.7 | US5: 1341451.5 | UT5: 1342182.4 | UU5: 1342900.8 | UV5: 1343606.2 | UW5: 1344387.1 | UX5: 1345274.7 | UZ5: 1346036.6 | VA5: 1346776.7 | VB5: 1347697.2 | VC5: 1348404 | VD5: 1349113.7 | VE5: 1349840 | VF5: 1350607.5 | VG5: 1351328.6 | VH5: 1352018.5 | VI5: 1352826.8 | VJ5: 1353455.9 | VK5: 1354080.2 | VL5: 1354896.1 | VM5: 1355913.6 | VN5: 1356532.7 | VO5: 1357296.1 | VP5: 1358106.9 | VQ5: 1358838.5 | VR5: 1359521.3 | VS5: 1360277.2 | VT5: 1360955.3 | VU5: 1361720.8 | VV5: 1362360.1 | VW5: 1363138.5 | VX5: 1363869.8 | VY5: 1364535 | VZ5: 1365348.4 | WA5: 1366017 | WC5: 1366691.9 | WD5: 1367289.3 | WE5: 1367981.4 | WF5: 1368591.6 | WG5: 1369087 | WH5: 1369829.9 | WI5: 1370582.8 | WJ5: 1371279.6 | WK5: 1371959.4 | WL5: 1372625.4 | WM5: 1373269.9 | WN5: 1373863.8 | WO5: 1374513.3 | WP5: 1375166.3 | WQ5: 1375859.2 | WR5: 1376563.7 | WS5: 1377205.9 | WT5: 1377836.1 | WU5: 1378432 | WV5: 1379137 | WW5: 1379784.6 | WX5: 1380529.2 | WY5: 1381189 | WZ5: 1382032.9 | XA5: 1382725.9 | XB5: 1383408.9 | XC5: 1384075.7 | XD5: 1384843.6 | XE5: 1385633.4 | XF5: 1386289.7 | XG5: 1386795.7 | XI5: 1387560.4 | XJ5: 1388268.5 | XK5: 1389031.7 | XL5: 1389832.8 | XM5: 1390554.7 | XN5: 1391234.6 | XO5: 1392056.8 | XP5: 1392724.4 | XQ5: 1393399.3 | XR5: 1394136.6 | XS5: 1395019.6 | XT5: 1395750 | XU5: 1396514.5 | XV5: 1397208.5 | XW5: 1397904.7 | XX5: 1398685.4 | XY5: 1399426.3 | XZ5: 1400144.6 | YA5: 1400915.8 | YB5: 1401563.1 | YC5: 1402214.7 | YD5: 1402830.9 | YE5: 1403451.9 | YF5: 1404256 | YG5: 1405060.8 | YH5: 1405830.3 | YI5: 1406494.3 | YJ5: 1407093.9 | YK5: 1407764.3 | YL5: 1408376.4 | YN5: 1409097 | YO5: 1409944.9 | YP5: 1410539.4 | YQ5: 1411331 | YR5: 1412145 | YS5: 1412838 | YT5: 1413481.7 | YU5: 1413481.7 | YV5: 1413885.6 | YW5: 1414572.9 | YX5: 1415085.3 | YY5: 1415862.8 | YZ5: 1416462.5 | ZA5: 1417130.5 | ZB5: 1417850.1 | ZC5: 1418469.6 | ZD5: 1419278 | ZE5: 1419922.6 | ZF5: 1420691.4 | ZG5: 1421345.1 | ZH5: 1422006.3 | ZI5: 1422734.9 | ZJ5: 1423707.5 | ZK5: 1424685.2 | ZL5: 1425657.5 | ZM5: 1426507.5 | ZN5: 1427290.4 | ZO5: 1428210.3 | ZP5: 1428996.1 | ZQ5: 1429777.1 | ZR5: 1430522.2 | ZT5: 1431254.5 | ZU5: 1432056.6 | ZV5: 1432857.3 | ZW5: 1433645.8 | ZX5: 1434568.2 | ZY5: 1435292.1 | ZZ5: 1436011.9 | AAA5: 1436597.4 | AAB5: 1437267.6 | AAC5: 1438049 | AAD5: 1438778.5 | AAE5: 1439455.1 | AAF5: 1440306.5 | AAG5: 1441114.9 | AAH5: 1441999.7 | AAI5: 1442701.8 | AAJ5: 1443425.7 | AAK5: 1444241.9 | AAL5: 1445053.5 | AAM5: 1445805 | AAN5: 1446582.1 | AAO5: 1447273 | AAP5: 1448070.3 | AAQ5: 1448768.9 | AAR5: 1449614.7 | AAS5: 1450357.6 | AAT5: 1451128.6 | AAU5: 1452077.1 | AAV5: 1452826.5 | AAW5: 1453525.4 | AAY5: 1454357.2 | AAZ5: 1455080.1 | ABA5: 1455873.6 | ABB5: 1456715.3 | ABC5: 1457662.5 | ABD5: 1458603 | ABE5: 1459407.9 | ABF5: 1460371 | ABG5: 1461189 | ABH5: 1462018.7 | ABI5: 1462726.2 | ABJ5: 1463087.5 | ABK5: 1463829.9 | ABL5: 1464533.1 | ABM5: 1465249.2 | ABN5: 1465950.4 | ABO5: 1466715.9 | ABP5: 1467604.6 | ABQ5: 1468366.3 | ABR5: 1469064 | ABS5: 1469717.7 | ABT5: 1470415.3 | ABU5: 1471218 | ABV5: 1472105.7 | ABW5: 1472978.1 | ABX5: 1473759.7 | ABY5: 1474514.5 | ABZ5: 1475337.1 | ACA5: 1476051.8 | ACB5: 1476775.7 | ACC5: 1477572 | ACE5: 1478348.7 | ACF5: 1479494.9 | ACG5: 1480379.8 | ACH5: 1481297.4 | ACI5: 1482206.2 | ACJ5: 1482843.6 | ACK5: 1483651.1 | ACL5: 1484515 | ACM5: 1485401 | ACN5: 1486074.8 | ACO5: 1486970.3 | ACP5: 1487644.3 | ACQ5: 1488244.5 | ACR5: 1489031.5 | ACS5: 1489991 | ACT5: 1490653.8 | ACU5: 1491301.7 | ACV5: 1492071.4 | ACW5: 1492549 | ACX5: 1493209.7 | ACY5: 1493954.3 | ACZ5: 1494903.3 | ADA5: 1495642.2 | ADB5: 1496393.8 | ADC5: 1496982.7 | ADD5: 1497752.9 | ADE5: 1498435.2 | ADF5: 1498987.7 | ADG5: 1499783.4 | ADH5: 1500481.2 | ADI5: 1501146.6 | ADK5: 1501902.5 | ADL5: 1502490.3 | ADM5: 1503031.2 | ADN5: 1503799.3 | ADO5: 1504637.2 | ADP5: 1505361.8 | ADQ5: 1506052.3 | ADR5: 1506811.2 | ADS5: 1507386.2 | ADT5: 1507915.9 | ADU5: 1508537.6 | ADV5: 1509220.3 | ADW5: 1509927.2 | ADX5: 1510551.7 | ADY5: 1511329.4 | ADZ5: 1511896.9 | AEA5: 1512444.3 | AEB5: 1513003.4 | AEC5: 1513711.7 | AED5: 1514251.5 | AEE5: 1514888.8 | AEF5: 1515462.3 | AEG5: 1516069.3 | AEH5: 1516691.5 | AEI5: 1517343.2 | AEJ5: 1517989.4 | AEK5: 1518628.5 | AEL5: 1519209.7 | AEM5: 1520095.4 | AEN5: 1520612.8 | AEP5: 1521078.9 | AEQ5: 1521638 | AER5: 1522269.1 | AES5: 1522961.7 | AET5: 1523614.5 | AEU5: 1524430 | AEV5: 1525041.8 | AEW5: 1525692 | AEX5: 1526443.1 | AEY5: 1527280.4 | AEZ5: 1527969.3 | AFA5: 1528785.3 | AFB5: 1529414.3 | AFC5: 1529987 | AFD5: 1530597.9 | AFE5: 1531239.3 | AFF5: 1531883.5 | AFG5: 1532629.6 | AFH5: 1533149.8 | AFI5: 1533815.6 | AFJ5: 1534532.3 | AFK5: 1535045.6 | AFL5: 1535618.2 | AFM5: 1536275.4 | AFN5: 1537112.3 | AFO5: 1537768.4 | AFP5: 1538333.9 | AFQ5: 1538963.7 | AFR5: 1539534.1 | AFS5: 1540108.6 | AFT5: 1540753.2 | AFV5: 1541493.4 | AFW5: 1542152.8 | AFX5: 1542839 | AFY5: 1543473.5 | AFZ5: 1544231.9 | AGA5: 1544926 | AGB5: 1545676.1 | AGC5: 1546239.7 | AGD5: 1547040 | AGE5: 1547722.2 | AGF5: 1548410.8 | AGG5: 1548888 | AGH5: 1549532 | AGI5: 1550223.1 | AGJ5: 1550815.9 | AGK5: 1551441.2 | AGL5: 1552275.1 | AGM5: 1552912.7 | AGN5: 1553488 | AGO5: 1554175.8 | AGP5: 1554928.1 | AGQ5: 1555578 | AGR5: 1556220.6 | AGS5: 1556606.6 | AGT5: 1557305.6 | AGU5: 1557974.8 | AGV5: 1558728.4 | AGW5: 1559639.6 | AGX5: 1560462.8 | AGY5: 1561177.3 | AHA5: 1561844.2 | AHB5: 1562422.8 | AHC5: 1563014.6 | AHD5: 1563781.6 | AHE5: 1564571.6 | AHF5: 1565265.2 | AHG5: 1565901 | AHH5: 1566610.1 | AHI5: 1567212.9 | AHJ5: 1567946.3 | AHK5: 1568751.4 | AHL5: 1569570 | AHM5: 1570509.2 | AHN5: 1571306.9 | AHO5: 1571979.7 | AHP5: 1572663.3 | AHQ5: 1573177.7 | AHR5: 1574060.8 | AHS5: 1575003 | AHT5: 1575729.8 | AHU5: 1576434.1 | AHV5: 1577177.6 | AHW5: 1578046.1 | AHX5: 1579070.3 | AHY5: 1579771.1 | AHZ5: 1580446.2 | AIA5: 1581083.4 | AIB5: 1581636.9 | AIC5: 1582228.2 | AID5: 1582863.7 | AIE5: 1583823.6 | AIG5: 1584351.5 | AIH5: 1584950.4 | AII5: 1585624.5 | AIJ5: 1586234 | AIK5: 1587002.7 | AIL5: 1587739.6 | AIM5: 1588450.8 | AIN5: 1589155.4 | AIO5: 1589942.9 | AIP5: 1590889.8 | AIQ5: 1591627.6 | AIR5: 1592257.9 | AIS5: 1593047.5 | AIT5: 1593789.3 | AIU5: 1594074.1 | AIV5: 1594824.1 | AIW5: 1595178.1 | AIX5: 1595609.7 | AIY5: 1596233.3 | AIZ5: 1596855.9 | AJA5: 1597576.5 | AJB5: 1598104.2 | AJC5: 1598931.4 | AJD5: 1599658.7 | AJE5: 1600384.1 | AJF5: 1600998.1 | AJG5: 1602093.1 | AJH5: 1602941.7 | AJI5: 1603632.3 | AJJ5: 1604322.3 | AJK5: 1605051.1 | AJM5: 1605645.7 | AJN5: 1606257.3 | AJO5: 1607036.6 | AJP5: 1607864.7 | AJQ5: 1608354.7 | AJR5: 1608935.3 | AJS5: 1609775 | AJT5: 1610411.2 | AJU5: 1611179.7 | AJV5: 1611940.2 | AJW5: 1612553.9 | AJX5: 1613280.3 | AJY5: 1614009.5 | AJZ5: 1614633.4 | AKA5: 1615155.4 | AKB5: 1615803 | AKC5: 1616486.8 | AKD5: 1617132 | AKE5: 1617648.2 | AKF5: 1618195.9 | AKG5: 1618916.7 | AKH5: 1619477.5 | AKI5: 1620200.4 | AKJ5: 1620741.7 | AKK5: 1621380.8 | AKL5: 1622032.3 | AKM5: 1622720 | AKN5: 1623242.9 | AKP5: 1623762.7 | AKQ5: 1624312.3 | AKR5: 1624997 | AKS5: 1625686 | AKT5: 1626236.9 | AKU5: 1626831 | AKV5: 1627533.4 | AKW5: 1628186.8 | AKX5: 1628659.3 | AKY5: 1629313.9 | AKZ5: 1629970 | ALA5: 1630536.3 | ALB5: 1631255.4 | ALC5: 1632018.3 | ALD5: 1632750.6 | ALE5: 1633654.5 | ALF5: 1634331.2 | ALG5: 1634933.3 | ALH5: 1635726.5 | ALI5: 1636390.1 | ALJ5: 1637136.7 | ALK5: 1637668.6 | ALL5: 1638317.9 | ALM5: 1639130.5 | ALN5: 1639834 | ALO5: 1640522.5 | ALP5: 1641299.4 | ALQ5: 1642180.1 | ALR5: 1643084.7 | ALS5: 1643986.5 | ALT5: 1644822.8 | ALV5: 1645682.8 | ALW5: 1646382 | ALX5: 1647065.9 | ALY5: 1647846.6 | ALZ5: 1648235.5 | AMA5: 1648787.7 | AMB5: 1649730.4 | AMC5: 1650418.8 | AMD5: 1651320.5 | AME5: 1652314.4 | AMF5: 1653112.8 | AMG5: 1654053.4 | AMH5: 1654898.9 | AMI5: 1655525.2 | AMJ5: 1656324 | AMK5: 1657024.6 | AML5: 1657886.7 | AMM5: 1658829.1 | AMN5: 1659710 | AMO5: 1660801 | AMP5: 1661783 | AMQ5: 1662834.3 | AMR5: 1664055.1 | AMS5: 1665405.4 | AMT5: 1666845.4 | AMU5: 1668029.5 | AMV5: 1668724.6 | AMW5: 1669280.6 | AMX5: 1670024.4 | AMY5: 1670874.7 | ANA5: 1671562.1 | ANB5: 1672385.7 | ANC5: 1672970.1 | AND5: 1674020.8 | ANE5: 1674757.8 | ANF5: 1675665.8 | ANG5: 1676506.3 | ANH5: 1677349.9 | ANI5: 1678231.4 | ANJ5: 1678983.6 | ANK5: 1679888.6 | ANL5: 1680728.9 | ANM5: 1681577.4 | ANN5: 1682504.6 | ANO5: 1683599.1 | ANP5: 1684396.2 | ANQ5: 1684829.4 | ANR5: 1685359.3 | ANS5: 1685898.8 | ANT5: 1686382.9 | ANU5: 1686951.8 | ANV5: 1687823.2 | ANW5: 1688431.8 | ANX5: 1689052.2 | ANY5: 1689718.5 | ANZ5: 1690493.4 | AOA5: 1691134.9 | AOB5: 1691705.7 | AOC5: 1692332.2 | AOD5: 1693160.1 | AOE5: 1693160.1 | AOF5: 674346.47
C6: PMS 1 SALES | D6: =D5-D4 | E6: =E5-E4 | F6: =F5-F4 | G6: =G5-G4 | H6: =H5-H4 | I6: =I5-I4 | J6: =J5-J4 | K6: =K5-K4 | ... AH6: =AH5-AH4 | AI6: =SUM(D6:AH6) | AJ6: =AJ5-AJ4 | AK6: =AK5-AK4 | AL6: =AL5-AL4 | AM6: =AM5-AM4 | AN6: =AN5-AN4 | AO6: =AO5-AO4 | AP6: =AP5-AP4 | AQ6: =AQ5-AQ4 | ... BM6: =BM5-BM4 | BN6: =SUM(AJ6:BM6) | BO6: =BO5-BO4 | BP6: =BP5-BP4 | BQ6: =BQ5-BQ4 | BR6: =BR5-BR4 | BS6: =BS5-BS4 | BT6: =BT5-BT4 | BU6: =BU5-BU4 | BV6: =BV5-BV4 | ... CS6: =CS5-CS4 | CT6: =SUM(BO6:CS6) | CU6: =CU5-CU4 | CV6: =CV5-CV4 | CW6: =CW5-CW4 | CX6: =CX5-CX4 | CY6: =CY5-CY4 | CZ6: =CZ5-CZ4 | DA6: =DA5-DA4 | DB6: =DB5-DB4 | ... DX6: =DX5-DX4 | DY6: =SUM(CU6:DX6) | DZ6: =DZ5-DZ4 | EA6: =EA5-EA4 | EB6: =EB5-EB4 | EC6: =EC5-EC4 | ED6: =ED5-ED4 | EE6: =EE5-EE4 | EF6: =EF5-EF4 | EG6: =EG5-EG4 | ... FD6: =FD5-FD4 | FE6: =SUM(DZ6:FD6) | FF6: =FF5-FF4 | FG6: =FG5-FG4 | FH6: =FH5-FH4 | FI6: =FI5-FI4 | FJ6: =FJ5-FJ4 | FK6: =FK5-FK4 | FL6: =FL5-FL4 | FM6: =FM5-FM4 | ... GJ6: =GJ5-GJ4 | GL6: =GL5-GL4 | GM6: =GM5-GM4 | GN6: =GN5-GN4 | GO6: =GO5-GO4 | GP6: =GP5-GP4 | GQ6: =GQ5-GQ4 | GR6: =GR5-GR4 | GS6: =GS5-GS4 | ... HN6: =HN5-HN4 | HP6: =HP5-HP4 | HQ6: =HQ5-HQ4 | HR6: =HR5-HR4 | HS6: =HS5-HS4 | HT6: =HT5-HT4 | HU6: =HU5-HU4 | HV6: =HV5-HV4 | HW6: =HW5-HW4 | ... IT6: =IT5-IT4 | IV6: =IV5-IV4 | IW6: =IW5-IW4 | IX6: =IX5-IX4 | IY6: =IY5-IY4 | IZ6: =IZ5-IZ4 | JA6: =JA5-JA4 | JB6: =JB5-JB4 | JC6: =JC5-JC4 | ... JY6: =JY5-JY4 | JZ6: =SUM(IV6:JY6) | KA6: =KA5-KA4 | KB6: =KB5-KB4 | KC6: =KC5-KC4 | KD6: =KD5-KD4 | KE6: =KE5-KE4 | KF6: =KF5-KF4 | KG6: =KG5-KG4 | KH6: =KH5-KH4 | ... LE6: =LE5-LE4 | LF6: =SUM(KA6:LE6) | LG6: =LG5-LG4 | LH6: =LH5-LH4 | LI6: =LI5-LI4 | LJ6: =LJ5-LJ4 | LK6: =LK5-LK4 | LL6: =LL5-LL4 | LM6: =LM5-LM4 | LN6: =LN5-LN4 | ... MJ6: =MJ5-MJ4 | MK6: =SUM(LF6:MJ6) | ML6: =ML5-ML4 | MM6: =MM5-MM4 | MN6: =MN5-MN4 | MO6: =MO5-MO4 | MP6: =MP5-MP4 | MQ6: =MQ5-MQ4 | MR6: =MR5-MR4 | MS6: =MS5-MS4 | ... NP6: =NP5-NP4 | NQ6: =SUM(ML6:NP6) | NR6: =NR5-NR4 | NS6: =NS5-NS4 | NT6: =NT5-NT4 | NU6: =NU5-NU4 | NV6: =NV5-NV4 | NW6: =NW5-NW4 | NX6: =NX5-NX4 | NY6: =NY5-NY4 | ... OV6: =OV5-OV4 | OW6: =SUM(NR6:OV6) | OX6: =OX5-OX4 | OY6: =OY5-OY4 | OZ6: =OZ5-OZ4 | PA6: =PA5-PA4 | PB6: =PB5-PB4 | PC6: =PC5-PC4 | PD6: =PD5-PD4 | PE6: =PE5-PE4 | ... QA6: =QA5-QA4 | QB6: =SUM(OX6:QA6) | QC6: =QC5-QC4 | QD6: =QD5-QD4 | QE6: =QE5-QE4 | QF6: =QF5-QF4 | QG6: =QG5-QG4 | QH6: =QH5-QH4 | QI6: =QI5-QI4 | QJ6: =QJ5-QJ4 | ... RG6: =RG5-RG4 | RH6: =SUM(QC6:RG6) | RI6: =RI5-RI4 | RJ6: =RJ5-RJ4 | RK6: =RK5-RK4 | RL6: =RL5-RL4 | RM6: =RM5-RM4 | RN6: =RN5-RN4 | RO6: =RO5-RO4 | RP6: =RP5-RP4 | ... SL6: =SL5-SL4 | SM6: =SUM(RI6:SL6) | SN6: =SN5-SN4 | SO6: =SO5-SO4 | SP6: =SP5-SP4 | SQ6: =SQ5-SQ4 | SR6: =SR5-SR4 | SS6: =SS5-SS4 | ST6: =ST5-ST4 | SU6: =SU5-SU4 | ... TR6: =TR5-TR4 | TS6: =SUM(SO6:TR6) | TT6: =TT5-TT4 | TU6: =TU5-TU4 | TV6: =TV5-TV4 | TW6: =TW5-TW4 | TX6: =TX5-TX4 | TY6: =TY5-TY4 | TZ6: =TZ5-TZ4 | UA6: =UA5-UA4 | ... UX6: =UX5-UX4 | UY6: =SUM(TT6:UX6) | UZ6: =UZ5-UZ4 | VA6: =VA5-VA4 | VB6: =VB5-VB4 | VC6: =VC5-VC4 | VD6: =VD5-VD4 | VE6: =VE5-VE4 | VF6: =VF5-VF4 | VG6: =VG5-VG4 | ... WA6: =WA5-WA4 | WB6: =SUM(UZ6:WA6) | WC6: =WC5-WC4 | WD6: =WD5-WD4 | WE6: =WE5-WE4 | WF6: =WF5-WF4 | WG6: =WG5-WG4 | WH6: =WH5-WH4 | WI6: =WI5-WI4 | WJ6: =WJ5-WJ4 | ... XG6: =XG5-XG4 | XH6: =SUM(WC6:XG6) | XI6: =XI5-XI4 | XJ6: =XJ5-XJ4 | XK6: =XK5-XK4 | XL6: =XL5-XL4 | XM6: =XM5-XM4 | XN6: =XN5-XN4 | XO6: =XO5-XO4 | XP6: =XP5-XP4 | ... YL6: =YL5-YL4 | YM6: =SUM(XH6:YL6) | YN6: =YN5-YN4 | YO6: =YO5-YO4 | YP6: =YP5-YP4 | YQ6: =YQ5-YQ4 | YR6: =YR5-YR4 | YS6: =YS5-YS4 | YT6: =YT5-YT4 | YU6: =YU5-YU4 | ... ZR6: =ZR5-ZR4 | ZS6: =SUM(YN6:ZR6) | ZT6: =ZT5-ZT4 | ZU6: =ZU5-ZU4 | ZV6: =ZV5-ZV4 | ZW6: =ZW5-ZW4 | ZX6: =ZX5-ZX4 | ZY6: =ZY5-ZY4 | ZZ6: =ZZ5-ZZ4 | AAA6: =AAA5-AAA4 | ... AAW6: =AAW5-AAW4 | AAX6: =SUM(ZT6:AAW6) | AAY6: =AAY5-AAY4 | AAZ6: =AAZ5-AAZ4 | ABA6: =ABA5-ABA4 | ABB6: =ABB5-ABB4 | ABC6: =ABC5-ABC4 | ABD6: =ABD5-ABD4 | ABE6: =ABE5-ABE4 | ABF6: =ABF5-ABF4 | ... ACC6: =ACC5-ACC4 | ACD6: =SUM(AAY6:ACC6) | ACE6: =ACE5-ACE4 | ACF6: =ACF5-ACF4 | ACG6: =ACG5-ACG4 | ACH6: =ACH5-ACH4 | ACI6: =ACI5-ACI4 | ACJ6: =ACJ5-ACJ4 | ACK6: =ACK5-ACK4 | ACL6: =ACL5-ACL4 | ... ADI6: =ADI5-ADI4 | ADJ6: =SUM(ACE6:ADI6) | ADK6: =ADK5-ADK4 | ADL6: =ADL5-ADL4 | ADM6: =ADM5-ADM4 | ADN6: =ADN5-ADN4 | ADO6: =ADO5-ADO4 | ADP6: =ADP5-ADP4 | ADQ6: =ADQ5-ADQ4 | ADR6: =ADR5-ADR4 | ... AEN6: =AEN5-AEN4 | AEO6: =SUM(ADK6:AEN6) | AEP6: =AEP5-AEP4 | AEQ6: =AEQ5-AEQ4 | AER6: =AER5-AER4 | AES6: =AES5-AES4 | AET6: =AET5-AET4 | AEU6: =AEU5-AEU4 | AEV6: =AEV5-AEV4 | AEW6: =AEW5-AEW4 | ... AFT6: =AFT5-AFT4 | AFU6: =SUM(AEP6:AFT6) | AFV6: =AFV5-AFV4 | AFW6: =AFW5-AFW4 | AFX6: =AFX5-AFX4 | AFY6: =AFY5-AFY4 | AFZ6: =AFZ5-AFZ4 | AGA6: =AGA5-AGA4 | AGB6: =AGB5-AGB4 | AGC6: =AGC5-AGC4 | ... AGY6: =AGY5-AGY4 | AGZ6: =SUM(AFV6:AGY6) | AHA6: =AHA5-AHA4 | AHB6: =AHB5-AHB4 | AHC6: =AHC5-AHC4 | AHD6: =AHD5-AHD4 | AHE6: =AHE5-AHE4 | AHF6: =AHF5-AHF4 | AHG6: =AHG5-AHG4 | AHH6: =AHH5-AHH4 | ... AIE6: =AIE5-AIE4 | AIF6: =SUM(AHA6:AIE6) | AIG6: =AIG5-AIG4 | AIH6: =AIH5-AIH4 | AII6: =AII5-AII4 | AIJ6: =AIJ5-AIJ4 | AIK6: =AIK5-AIK4 | AIL6: =AIL5-AIL4 | AIM6: =AIM5-AIM4 | AIN6: =AIN5-AIN4 | ... AJK6: =AJK5-AJK4 | AJL6: =SUM(AIG6:AJK6) | AJM6: =AJM5-AJM4 | AJN6: =AJN5-AJN4 | AJO6: =AJO5-AJO4 | AJP6: =AJP5-AJP4 | AJQ6: =AJQ5-AJQ4 | AJR6: =AJR5-AJR4 | AJS6: =AJS5-AJS4 | AJT6: =AJT5-AJT4 | ... AKN6: =AKN5-AKN4 | AKO6: =SUM(AJM6:AKN6) | AKP6: =AKP5-AKP4 | AKQ6: =AKQ5-AKQ4 | AKR6: =AKR5-AKR4 | AKS6: =AKS5-AKS4 | AKT6: =AKT5-AKT4 | AKU6: =AKU5-AKU4 | AKV6: =AKV5-AKV4 | AKW6: =AKW5-AKW4 | ... ALT6: =ALT5-ALT4 | ALU6: =SUM(AKP6:ALT6) | ALV6: =ALV5-ALV4 | ALW6: =ALW5-ALW4 | ALX6: =ALX5-ALX4 | ALY6: =ALY5-ALY4 | ALZ6: =ALZ5-ALZ4 | AMA6: =AMA5-AMA4 | AMB6: =AMB5-AMB4 | AMC6: =AMC5-AMC4 | ... AMY6: =AMY5-AMY4 | AMZ6: =SUM(ALV6:AMY6) | ANA6: =ANA5-ANA4 | ANB6: =ANB5-ANB4 | ANC6: =ANC5-ANC4 | AND6: =AND5-AND4 | ANE6: =ANE5-ANE4 | ANF6: =ANF5-ANF4 | ANG6: =ANG5-ANG4 | ANH6: =ANH5-ANH4 | ... AOF6: =AOF5-AOF4
B7: PMS 2 | C7: OPENING | D7: 350641.91 | E7: =D8 | F7: =E8 | G7: =F8 | H7: =G8 | I7: =H8 | J7: =I8 | K7: =J8 | L7: =K8 | ... AH7: =AG8 | AJ7: =AH8 | AK7: =AJ8 | AL7: =AK8 | AM7: =AL8 | AN7: =AM8 | AO7: =AN8 | AP7: =AO8 | AQ7: =AP8 | AR7: =AQ8 | ... BM7: =BL8 | BO7: =BM8 | BP7: =BO8 | BQ7: =BP8 | BR7: =BQ8 | BS7: =BR8 | BT7: =BS8 | BU7: =BT8 | BV7: =BU8 | BW7: =BV8 | ... CS7: =CR8 | CU7: =CS8 | CV7: =CU8 | CW7: =CV8 | CX7: =CW8 | CY7: =CX8 | CZ7: =CY8 | DA7: =CZ8 | DB7: =DA8 | DC7: =DB8 | ... DX7: =DW8 | DZ7: =DX8 | EA7: =DZ8 | EB7: =EA8 | EC7: =EB8 | ED7: =EC8 | EE7: =ED8 | EF7: =EE8 | EG7: =EF8 | EH7: =EG8 | ... FD7: =FC8 | FF7: =FD8 | FG7: =FF8 | FH7: =FG8 | FI7: =FH8 | FJ7: =FI8 | FK7: =FJ8 | FL7: =FK8 | FM7: =FL8 | FN7: =FM8 | ... GJ7: =GI8 | GK7: =SUM(FF7:GJ7) | GL7: =GJ8 | GM7: =GL8 | GN7: =GM8 | GO7: =GN8 | GP7: =GO8 | GQ7: =GP8 | GR7: =GQ8 | GS7: =GR8 | GT7: =GS8 | ... HN7: =HM8 | HO7: =SUM(GL7:HN7) | HP7: =HN8 | HQ7: =HP8 | HR7: =HQ8 | HS7: =HR8 | HT7: =HS8 | HU7: =HT8 | HV7: =HU8 | HW7: =HV8 | HX7: =HW8 | ... IT7: =IS8 | IU7: =SUM(HP7:IT7) | IV7: =IT8 | IW7: =IV8 | IX7: =IW8 | IY7: =IX8 | IZ7: =IY8 | JA7: =IZ8 | JB7: =JA8 | JC7: =JB8 | JD7: =JC8 | ... JY7: =JX8 | KA7: =JY8 | KB7: =KA8 | KC7: =KB8 | KD7: =KC8 | KE7: =KD8 | KF7: =KE8 | KG7: =KF8 | KH7: =KG8 | KI7: =KH8 | ... LE7: =LD8 | LG7: =LE8 | LH7: =LG8 | LI7: =LH8 | LJ7: =LI8 | LK7: =LJ8 | LL7: =LK8 | LM7: =LL8 | LN7: =LM8 | LO7: =LN8 | ... MJ7: =MI8 | ML7: =MJ8 | MM7: =ML8 | MN7: =MM8 | MO7: =MN8 | MP7: =MO8 | MQ7: =MP8 | MR7: =MQ8 | MS7: =MR8 | MT7: =MS8 | ... NP7: =NO8 | NR7: =NP8 | NS7: =NR8 | NT7: =NS8 | NU7: =NT8 | NV7: =NU8 | NW7: =NV8 | NX7: =NW8 | NY7: =NX8 | NZ7: =NY8 | ... OV7: =OU8 | OX7: =OV8 | OY7: =OX8 | OZ7: =OY8 | PA7: =OZ8 | PB7: =PA8 | PC7: =PB8 | PD7: =PC8 | PE7: =PD8 | PF7: =PE8 | ... QA7: =PZ8 | QC7: =QA8 | QD7: =QC8 | QE7: =QD8 | QF7: =QE8 | QG7: =QF8 | QH7: =QG8 | QI7: =QH8 | QJ7: =QI8 | QK7: =QJ8 | ... RG7: =RF8 | RI7: =RG8 | RJ7: =RI8 | RK7: =RJ8 | RL7: =RK8 | RM7: =RL8 | RN7: =RM8 | RO7: =RN8 | RP7: =RO8 | RQ7: =RP8 | ... SL7: =SK8 | SN7: =SL8 | SO7: =SN8 | SP7: =SO8 | SQ7: =SP8 | SR7: =SQ8 | SS7: =SR8 | ST7: =SS8 | SU7: =ST8 | SV7: =SU8 | ... TR7: =TQ8 | TT7: =TR8 | TU7: =TT8 | TV7: =TU8 | TW7: =TV8 | TX7: =TW8 | TY7: =TX8 | TZ7: =TY8 | UA7: =TZ8 | UB7: =UA8 | ... UX7: =UW8 | UZ7: =UX8 | VA7: =UZ8 | VB7: =VA8 | VC7: =VB8 | VD7: =VC8 | VE7: =VD8 | VF7: =VE8 | VG7: =VF8 | VH7: =VG8 | ... WA7: =VZ8 | WC7: =WA8 | WD7: =WC8 | WE7: =WD8 | WF7: =WE8 | WG7: =WF8 | WH7: =WG8 | WI7: =WH8 | WJ7: =WI8 | WK7: =WJ8 | ... XG7: =XF8 | XI7: =XG8 | XJ7: =XI8 | XK7: =XJ8 | XL7: =XK8 | XM7: =XL8 | XN7: =XM8 | XO7: =XN8 | XP7: =XO8 | XQ7: =XP8 | ... YL7: =YK8 | YN7: =YL8 | YO7: =YN8 | YP7: =YO8 | YQ7: =YP8 | YR7: =YQ8 | YS7: =YR8 | YT7: =YS8 | YU7: =YT8 | YV7: =YU8 | ... ZR7: =ZQ8 | ZT7: =ZR8 | ZU7: =ZT8 | ZV7: =ZU8 | ZW7: =ZV8 | ZX7: =ZW8 | ZY7: =ZX8 | ZZ7: =ZY8 | AAA7: =ZZ8 | AAB7: =AAA8 | ... AAW7: =AAV8 | AAY7: =AAW8 | AAZ7: =AAY8 | ABA7: =AAZ8 | ABB7: =ABA8 | ABC7: =ABB8 | ABD7: =ABC8 | ABE7: =ABD8 | ABF7: =ABE8 | ABG7: =ABF8 | ... ACC7: =ACB8 | ACE7: =ACC8 | ACF7: =ACE8 | ACG7: =ACF8 | ACH7: =ACG8 | ACI7: =ACH8 | ACJ7: =ACI8 | ACK7: =ACJ8 | ACL7: =ACK8 | ACM7: =ACL8 | ... ADI7: =ADH8 | ADK7: =ADI8 | ADL7: =ADK8 | ADM7: =ADL8 | ADN7: =ADM8 | ADO7: =ADN8 | ADP7: =ADO8 | ADQ7: =ADP8 | ADR7: =ADQ8 | ADS7: =ADR8 | ... AEN7: =AEM8 | AEP7: =AEN8 | AEQ7: =AEP8 | AER7: =AEQ8 | AES7: =AER8 | AET7: =AES8 | AEU7: =AET8 | AEV7: =AEU8 | AEW7: =AEV8 | AEX7: =AEW8 | ... AFT7: =AFS8 | AFV7: =AFT8 | AFW7: =AFV8 | AFX7: =AFW8 | AFY7: =AFX8 | AFZ7: =AFY8 | AGA7: =AFZ8 | AGB7: =AGA8 | AGC7: =AGB8 | AGD7: =AGC8 | ... AGY7: =AGX8 | AHA7: =AGY8 | AHB7: =AHA8 | AHC7: =AHB8 | AHD7: =AHC8 | AHE7: =AHD8 | AHF7: =AHE8 | AHG7: =AHF8 | AHH7: =AHG8 | AHI7: =AHH8 | ... AIE7: =AID8 | AIG7: =AIE8 | AIH7: =AIG8 | AII7: =AIH8 | AIJ7: =AII8 | AIK7: =AIJ8 | AIL7: =AIK8 | AIM7: =AIL8 | AIN7: =AIM8 | AIO7: =AIN8 | ... AJK7: =AJJ8 | AJM7: =AJK8 | AJN7: =AJM8 | AJO7: =AJN8 | AJP7: =AJO8 | AJQ7: =AJP8 | AJR7: =AJQ8 | AJS7: =AJR8 | AJT7: =AJS8 | AJU7: =AJT8 | ... AKN7: =AKM8 | AKP7: =AKN8 | AKQ7: =AKP8 | AKR7: =AKQ8 | AKS7: =AKR8 | AKT7: =AKS8 | AKU7: =AKT8 | AKV7: =AKU8 | AKW7: =AKV8 | AKX7: =AKW8 | ... ALT7: =ALS8 | ALV7: =ALT8 | ALW7: =ALV8 | ALX7: =ALW8 | ALY7: =ALX8 | ALZ7: =ALY8 | AMA7: =ALZ8 | AMB7: =AMA8 | AMC7: =AMB8 | AMD7: =AMC8 | ... AMY7: =AMX8 | ANA7: =AMY8 | ANB7: =ANA8 | ANC7: =ANB8 | AND7: =ANC8 | ANE7: =AND8 | ANF7: =ANE8 | ANG7: =ANF8 | ANH7: =ANG8 | ANI7: =ANH8 | ... AOC7: =AOB8 | AOD7: 672625.91 | AOE7: 672625.91 | AOF7: 1387010
